Workbook

Sheet Dashboard
U1: CHART DATA (linked)
B2: FIELD SERVICE DASHBOARD
B3: May 2026 • Solar Module Complaints & Defect Analysis | U3: Site | V3: Modules
U4: ='May-26 Analysis'!A19 | V4: ='May-26 Analysis'!B19
B5: Total Complaints | E5: Closed Modules | H5: WIP / Open | K5: Closure Rate | N5: Avg Resolution | U5: ='May-26 Analysis'!A20 | V5: ='May-26 Analysis'!B20
B6: ='May-26 Analysis'!B5 | E6: ='May-26 Analysis'!C5 | H6: ='May-26 Analysis'!D5 | K6: ='May-26 Analysis'!F5 | N6: ='May-26 Analysis'!I5 | U6: ='May-26 Analysis'!A21 | V6: ='May-26 Analysis'!B21
U7: ='May-26 Analysis'!A22 | V7: ='May-26 Analysis'!B22
B8: Daily Complaints Trend - May 2026 | U8: ='May-26 Analysis'!A23 | V8: ='May-26 Analysis'!B23
U9: ='May-26 Analysis'!A24 | V9: ='May-26 Analysis'!B24
U10: ='May-26 Analysis'!A25 | V10: ='May-26 Analysis'!B25
U11: ='May-26 Analysis'!A26 | V11: ='May-26 Analysis'!B26
U12: State | V12: Modules
U13: ='May-26 Analysis'!G19 | V13: ='May-26 Analysis'!H19
U14: ='May-26 Analysis'!G20 | V14: ='May-26 Analysis'!H20
U15: ='May-26 Analysis'!G21 | V15: ='May-26 Analysis'!H21
U16: ='May-26 Analysis'!G22 | V16: ='May-26 Analysis'!H22
U17: ='May-26 Analysis'!G23 | V17: ='May-26 Analysis'!H23
U18: ='May-26 Analysis'!G24 | V18: ='May-26 Analysis'!H24
U19: ='May-26 Analysis'!G25 | V19: ='May-26 Analysis'!H25
U20: ='May-26 Analysis'!G26 | V20: ='May-26 Analysis'!H26
U22: Defect Type | V22: Count
B23: Complaints by Site (Top 8) | H23: Complaints by State | N23: Defect Type Mix | U23: ='Defect Analysis May-26'!A9 | V23: ='Defect Analysis May-26'!B9
U24: ='Defect Analysis May-26'!A13 | V24: ='Defect Analysis May-26'!B13
U25: ='Defect Analysis May-26'!A16 | V25: ='Defect Analysis May-26'!B16
U26: ='Defect Analysis May-26'!A11 | V26: ='Defect Analysis May-26'!B11
U27: Others | V27: ='Defect Analysis May-26'!B18+'Defect Analysis May-26'!B6+'Defect Analysis May-26'!B7+'Defect Analysis May-26'!B8+'Defect Analysis May-26'!B10+'Defect Analysis May-26'!B12+'Defect Analysis May-26'!B14+'Defect Analysis May-26'!B17
U37: Week | V37: Modules
U38: ='May-26 Analysis'!G46 | V38: ='May-26 Analysis'!H46
U39: ='May-26 Analysis'!G47 | V39: ='May-26 Analysis'!H47
B40: Resolution Time (TAT) Distribution | H40: Weekly Complaint Volume | U40: ='May-26 Analysis'!G48 | V40: ='May-26 Analysis'!H48
U41: ='May-26 Analysis'!G49 | V41: ='May-26 Analysis'!H49
U42: ='May-26 Analysis'!G50 | V42: ='May-26 Analysis'!H50
U45: Date | V45: Visited | W45: Closed
U46: ='May-26 Analysis'!A40 | V46: ='May-26 Analysis'!B40 | W46: ='May-26 Analysis'!C40
U47: ='May-26 Analysis'!A41 | V47: ='May-26 Analysis'!B41 | W47: ='May-26 Analysis'!C41
U48: ='May-26 Analysis'!A42 | V48: ='May-26 Analysis'!B42 | W48: ='May-26 Analysis'!C42
U49: ='May-26 Analysis'!A43 | V49: ='May-26 Analysis'!B43 | W49: ='May-26 Analysis'!C43
U50: ='May-26 Analysis'!A44 | V50: ='May-26 Analysis'!B44 | W50: ='May-26 Analysis'!C44
U51: ='May-26 Analysis'!A45 | V51: ='May-26 Analysis'!B45 | W51: ='May-26 Analysis'!C45
U52: ='May-26 Analysis'!A46 | V52: ='May-26 Analysis'!B46 | W52: ='May-26 Analysis'!C46
U53: ='May-26 Analysis'!A47 | V53: ='May-26 Analysis'!B47 | W53: ='May-26 Analysis'!C47
U54: ='May-26 Analysis'!A48 | V54: ='May-26 Analysis'!B48 | W54: ='May-26 Analysis'!C48
U55: ='May-26 Analysis'!A49 | V55: ='May-26 Analysis'!B49 | W55: ='May-26 Analysis'!C49
U56: ='May-26 Analysis'!A50 | V56: ='May-26 Analysis'!B50 | W56: ='May-26 Analysis'!C50
U57: ='May-26 Analysis'!A51 | V57: ='May-26 Analysis'!B51 | W57: ='May-26 Analysis'!C51
B58: MANUFACTURING PLANT-WISE | K58: MODULE TYPE DEFECT ANALYSIS - MAY 2026 | U58: ='May-26 Analysis'!A52 | V58: ='May-26 Analysis'!B52 | W58: ='May-26 Analysis'!C52
U59: ='May-26 Analysis'!A53 | V59: ='May-26 Analysis'!B53 | W59: ='May-26 Analysis'!C53
U60: ='May-26 Analysis'!A54 | V60: ='May-26 Analysis'!B54 | W60: ='May-26 Analysis'!C54
U61: ='May-26 Analysis'!A55 | V61: ='May-26 Analysis'!B55 | W61: ='May-26 Analysis'!C55
U62: ='May-26 Analysis'!A56 | V62: ='May-26 Analysis'!B56 | W62: ='May-26 Analysis'!C56
U63: ='May-26 Analysis'!A57 | V63: ='May-26 Analysis'!B57 | W63: ='May-26 Analysis'!C57
U64: ='May-26 Analysis'!A58 | V64: ='May-26 Analysis'!B58 | W64: ='May-26 Analysis'!C58
U65: ='May-26 Analysis'!A59 | V65: ='May-26 Analysis'!B59 | W65: ='May-26 Analysis'!C59
U66: ='May-26 Analysis'!A60 | V66: ='May-26 Analysis'!B60 | W66: ='May-26 Analysis'!C60
U67: ='May-26 Analysis'!A61 | V67: ='May-26 Analysis'!B61 | W67: ='May-26 Analysis'!C61
U68: ='May-26 Analysis'!A62 | V68: ='May-26 Analysis'!B62 | W68: ='May-26 Analysis'!C62
U69: ='May-26 Analysis'!A63 | V69: ='May-26 Analysis'!B63 | W69: ='May-26 Analysis'!C63
U70: ='May-26 Analysis'!A64 | V70: ='May-26 Analysis'!B64 | W70: ='May-26 Analysis'!C64
... U74: ='May-26 Analysis'!A68 | V74: ='May-26 Analysis'!B68 | W74: ='May-26 Analysis'!C68

Sheet Daily Report May-26 
A1: Date | B1: Site | C1: Area | D1: State | E1: No Of Complaints | F1: Visited by | G1: Complaint ID | H1: Status | I1: Remarks | J1: Complaints Register Link | K1: Start Date | L1: End Day | M1: Remarka
A2: 46143 | B2: Panasonic | C2: Mysore | D2: Karnataka | E2: 1 | F2: Amit | G2: PE28042604 | H2: Closed | I2: Retrofit | J2: PE28042604 | K2: 46143 | L2: 46144
A3: 46143 | B3: Axitec Energy | C3: Chinchwad | D3: Maharashtra | E3: 2 | F3: Bani | G3: PE21042602 | H3: Closed | I3: Retrofit | J3: PE21042602 | K3: 46143
A4: 46143 | B4: First Energy | C4: Rajkot | D4: Gujarat | E4: 24 | F4: Kunal & Nilanjan | G4: PE25032601 | H4: WIP | I4: Inspection | J4: PE25032601 | K4: 46143
A5: 46144 | B5: First Energy | C5: Rajkot | D5: Gujarat | E5: 20 | F5: Kunal & Nilanjan | G5: PE25032601 | H5: WIP | I5: Inspection | J5: PE25032601
A6: 46144 | B6: Blupine | C6: Sadla | D6: Gujarat | E6: 52 | F6: Bhimsen + Raja | G6: PE26032601 | H6: Closed | I6: Retrofit | J6: PE26032601 | K6: 46143
A7: 46144 | B7: Panasonic | C7: Dhule | D7: Maharashtra | E7: 1 | F7: Bani | G7: PE06042602 | H7: Closed | I7: Rejected | J7: PE06042602
A8: 46144 | B8: Panasonic | C8: Dhule | D8: Maharashtra | E8: 1 | F8: Bani | G8: PE06042602 | H8: WIP | I8: Inspection | J8: PE06042602
A9: 46146 | B9: Solar Square | C9: Hyderabad | D9: Telangana | E9: 4 | F9: By Mail | G9: PE26032602 | H9: Closed | I9: CN | J9: PE26032602
A10: 46146 | B10: TRUE SUN TRADING COMPANY | C10: CHANGANASSERRY | D10: Kerala | E10: 1 | F10: By Mail | G10: PE27042603 | H10: Closed | I10: CN | J10: PE27042603
A11: 46146 | B11: RA GREEN ENERGks | C11: Nagpur | D11: Maharashtra | E11: 1 | F11: Bani | G11: PE31032602 | H11: Closed | I11: Retrofit | J11: PE31032602
A12: 46146 | B12: Panasonic | C12: Lucknow | D12: UP | E12: 3 | F12: Kamal | G12: PE07042601 | H12: Closed | I12: Repair | J12: PE07042601 | K12: 46145
A13: 46146 | B13: Oyster Technocon | C13: Nagpur | D13: Maharashtra | E13: 12 | F13: Bani | G13: PE02052601 | H13: Closed | I13: Retrofit | J13: PE02052601
A14: 46146 | B14: First Energy | C14: Rajkot | D14: Gujarat | E14: 53 | F14: Kunal & Nilanjan | G14: PE25032601 | H14: WIP | I14: Inspection | J14: PE25032601
A15: 46146 | B15: Blupine | C15: Sadla | D15: Gujarat | E15: 64 | F15: Bhimsen + Raja | G15: PE26032601 | H15: Closed | I15: Retrofit | J15: PE26032601
A16: 46147 | B16: Solar Square | C16: Kanpur | D16: UP | E16: 1 | F16: Kamal | G16: PE30042601 | H16: Closed | I16: Retrofit | J16: PE30042601 | L16: 46147
A17: 46147 | B17: Solar Square | C17: Jabalpur | D17: MP | E17: 1 | F17: Bani | G17: PE29042602 | H17: Closed | I17: Retrofit | J17: PE29042602
A18: 46147 | B18: Solar Square | C18: Jabalpur | D18: MP | E18: 1 | F18: Bani | G18: PE09042601 | H18: Closed | I18: Retrofit | J18: PE09042601
A19: 46147 | B19: First Energy | C19: Rajkot | D19: Gujarat | E19: 55 | F19: Kunal & Nilanjan | G19: PE25032601 | H19: WIP | I19: Inspection | J19: PE25032601
A20: 46147 | B20: Blupine | C20: Sadla | D20: Gujarat | E20: 53 | F20: Bhimsen + Raja | G20: PE26032601 | H20: Closed | I20: Retrofit | J20: PE26032601
A21: 46147 | B21: TRUE SUN TRADING COMPANY | C21: Trivandram | D21: Kerala | E21: 1 | F21: By Mail | G21: PE18022602 | H21: Closed | I21: CN | J21: PE18022602
A22: 46147 | B22: TRUE SUN TRADING COMPANY | C22: Thrissur | D22: Kerala | E22: 1 | F22: By Mail | G22: PE20022602 | H22: Closed | I22: CN | J22: PE20022602
A23: 46147 | B23: TRUE SUN TRADING COMPANY | C23: TRIVANDRAM | D23: Kerala | E23: 1 | F23: By Mail | G23: PE24042601 | H23: Closed | I23: CN | J23: PE24042601
A24: 46147 | B24: TRUE SUN TRADING COMPANY | C24: TRIVANDRAM | D24: Kerala | E24: 1 | F24: By Mail | G24: PE24042602 | H24: Closed | I24: CN | J24: PE24042602
A25: 46148 | B25: Solar Square | C25: Indore | D25: MP | E25: 2 | F25: Bani | G25: PE26022602 | H25: Closed | I25: Retrofit | J25: PE26022602 | M25: 46150
A26: 46148 | B26: Blupine | C26: Sadla | D26: Gujarat | E26: 58 | F26: Bhimsen + Raja | G26: PE26032601 | H26: Closed | I26: Retrofit | J26: PE26032601
A27: 46148 | B27: First Energy | C27: Rajkot | D27: Gujarat | E27: 34 | F27: Kunal & Nilanjan | G27: PE25032601 | H27: WIP | I27: Inspection | J27: PE25032601
A28: 46149 | B28: First Energy | C28: Rajkot | D28: Gujarat | E28: 5 | F28: Kunal & Nilanjan | G28: PE25032601 | H28: WIP | I28: Inspection | J28: PE25032601 | L28: 46149
A29: 46149 | B29: Blupine | C29: Sadla | D29: Gujarat | E29: 44 | F29: Bhimsen + Raja | G29: PE26032601 | H29: Closed | I29: Retrofit | J29: PE26032601
A30: 46150 | B30: Cresta solar | C30: Hyderabad | D30: Telangana | E30: 1 | F30: By Mail | G30: PE07052601 | H30: Closed | I30: Replacement | J30: PE07052601
A31: 46150 | B31: Blupine | C31: Sadla | D31: Gujarat | E31: 52 | F31: Bhimsen + Raja | G31: PE26032601 | H31: Closed | I31: Retrofit | J31: PE26032601
A32: 46151 | B32: Blupine | C32: Sadla | D32: Gujarat | E32: 80 | F32: Bhimsen + Raja + Nilanjan + Kunal | G32: PE26032601 | H32: Closed | I32: Retrofit | J32: PE26032601
A33: 46153 | B33: Blupine | C33: Sadla | D33: Gujarat | E33: 85 | F33: Bhimsen + Raja + Nilanjan + Kunal | G33: PE26032601 | H33: Closed | I33: Retrofit | J33: PE26032601
A34: 46153 | B34: Yanara Power | C34: Holi | D34: Maharashtra | E34: 26 | F34: Gourab + Amit + Bani | G34: PE01052601 | H34: Closed | I34: Retrofit | J34: PE01052601 | K34: 46149
A35: 46154 | B35: Blupine | C35: Sadla | D35: Gujarat | E35: 88 | F35: Bhimsen + Raja + Nilanjan + Kunal | G35: PE26032601 | H35: Closed | I35: Retrofit | J35: PE26032601
A36: 46155 | B36: Uma Trading | C36: Sangli | D36: Maharashtra | E36: 1 | F36: By Mail | G36: PE12052604 | H36: Closed | I36: Rejected | J36: PE12052604
A37: 46155 | B37: Blupine | C37: Sadla | D37: Gujarat | E37: 55 | F37: Bhimsen + Raja + Kunal + Kamal | G37: PE26032601 | H37: Closed | I37: Retrofit | J37: PE26032601
A38: 46155 | B38: Yanara Power | C38: Holi | D38: Maharashtra | E38: 37 | F38: Gourab + Amit + Bani | G38: PE01052601 | H38: Closed | I38: Retrofit | J38: PE01052601
A39: 46156 | B39: Solar Square | C39: Hyderabad | D39: Telangana | E39: 1 | F39: Pavan | G39: PE27042601 | H39: Closed | I39: Retrofit | J39: PE27042601 | K39: 46156
A40: 46156 | B40: Solar Square | C40: Hyderabad | D40: Telangana | E40: 2 | F40: Pavan | G40: PE27042602 | H40: Closed | I40: Retrofit | J40: PE27042602 | M40: 46156
A41: 46156 | B41: Blupine | C41: Sadla | D41: Gujarat | E41: 101 | F41: Bhimsen + Raja + Kunal + Kamal | G41: PE26032601 | H41: Closed | I41: Retrofit | J41: PE26032601
A42: 46156 | B42: Yanara Power | C42: Holi | D42: Maharashtra | E42: 52 | F42: Gourab + Amit + Bani | G42: PE01052601 | H42: Closed | I42: Retrofit | J42: PE01052601
A43: 46156 | B43: SILRES Energy Solutions Private Limited | C43: Chennai | D43: Tamil Nadu | E43: 1 | F43: By Mail | G43: PE5052601 | H43: Closed | I43: Refund | J43: PE5052601
A44: 46157 | B44: Blupine | C44: Sadla | D44: Gujarat | E44: 51 | F44: Bhimsen + Raja + Kunal + Kamal | G44: PE26032601 | H44: Closed | I44: Retrofit | J44: PE26032601
A45: 46157 | B45: Yanara Power | C45: Holi | D45: Maharashtra | E45: 43 | F45: Gourab + Amit + Bani | G45: PE01052601 | H45: Closed | I45: Retrofit | J45: PE01052601
A46: 46158 | B46: Blupine | C46: Sadla | D46: Gujarat | E46: 87 | F46: Bhimsen + Raja + Kunal + Kamal | G46: PE26032601 | H46: Closed | I46: Retrofit | J46: PE26032601
A47: 46158 | B47: Yanara Power | C47: Holi | D47: Maharashtra | E47: 34 | F47: Gourab + Amit + Bani | G47: PE01052601 | H47: Closed | I47: Retrofit | J47: PE01052601
A48: 46158 | B48: Nabhas Constructions | C48: Kovvuru | D48: Andhra Predesh | E48: 1 | F48: By Mail | G48: PE16052601 | H48: Closed | I48: Replacement | J48: PE16052601
A49: 46159 | B49: Blupine | C49: Sadla | D49: Gujarat | E49: 62 | F49: Bhimsen + Raja + Kunal + Kamal | G49: PE26032601 | H49: Closed | I49: Retrofit | J49: PE26032601
A50: 46159 | B50: Yanara Power | C50: Holi | D50: Maharashtra | E50: 41 | F50: Gourab + Amit + Bani | G50: PE01052601 | H50: Closed | I50: Retrofit | J50: PE01052601
A51: 46160 | B51: Blupine | C51: Sadla | D51: Gujarat | E51: 31 | F51: Bhimsen + Raja + Kunal + Kamal | G51: PE26032601 | H51: Closed | I51: Retrofit | J51: PE26032601
A52: 46160 | B52: Yanara Power | C52: Holi | D52: Maharashtra | E52: 58 | F52: Gourab + Amit + Bani | G52: PE01052601 | H52: Closed | I52: Retrofit | J52: PE01052601
... A63: 46167 | B63: Continuum | C63: Bhavnagar | D63: Gujarat | E63: 78 | F63: Bhimsen + Raja + Kunal + Kamal | G63: PE06052602 | H63: Closed | I63: Retrofit | J63: PE06052602
A64: 46167 | B64: Panasonic | C64: Kochi | D64: Kerala | E64: 5 | F64: Pavan | G64: PE23052601 | H64: Closed | I64: Retrofit | J64: PE23052601 | K64: 46166
A65: 46167 | B65: Yanara Power | C65: Holi | D65: Maharashtra | E65: 57 | F65: Gourab + Amit | G65: PE01052601 | H65: Closed | I65: Retrofit | J65: PE01052601
A66: 46168 | B66: SUNRISE TECHNOLOGIES | C66: Hyderabad | D66: Telangana | E66: 1 | F66: By Mail | G66: PE06052603 | H66: Closed | I66: Replacement | J66: PE06052603
A67: 46168 | B67: Continuum | C67: Bhavnagar | D67: Gujarat | E67: 28 | F67: Bhimsen + Raja + Kunal + Kamal | G67: PE06052602 | H67: Closed | I67: Retrofit | J67: PE06052602
A68: 46168 | B68: TRUE SUN TRADING COMPANY | C68: TRIVANDRUM | D68: Kerala | E68: 1 | F68: Pavan | G68: PE20052603 | H68: Closed | I68: Retrofit | J68: PE20052603
A69: 46168 | B69: TRUE SUN TRADING COMPANY | C69: TRIVANDRUM | D69: Kerala | E69: 1 | F69: Pavan | G69: PE07052602 | H69: Closed | I69: Retrofit | J69: PE07052602
A70: 46168 | B70: Yanara Power | C70: Holi | D70: Maharashtra | E70: 55 | F70: Gourab + Amit | G70: PE01052601 | H70: Closed | I70: Retrofit | J70: PE01052601
A71: 46169 | B71: Continuum | C71: Bhavnagar | D71: Gujarat | E71: 86 | F71: Bhimsen + Raja + Kunal + Kamal | G71: PE06052602 | H71: Closed | I71: Retrofit | J71: PE06052602
A72: 46169 | B72: Yanara Power | C72: Holi | D72: Maharashtra | E72: 24 | F72: Gourab + Amit | G72: PE01052601 | H72: Closed | I72: Retrofit | J72: PE01052601
A73: 46169 | B73: TRUE SUN TRADING COMPANY | C73: Pattoor | D73: Kerala | E73: 1 | F73: Pavan | G73: PE28032601 | H73: Closed | I73: Retrofit | J73: PE28032601
A74: 46167 | B74: TRUE SUN TRADING COMPANY | C74: Chandanappally PTA | D74: Kerala | E74: 1 | F74: Pavan | G74: PE25052601 | H74: Closed | I74: Retrofit | J74: PE25052601
A75: 46170 | B75: Continuum | C75: Bhavnagar | D75: Gujarat | E75: 74 | F75: Bhimsen + Raja + Kunal + Kamal | G75: PE06052602 | H75: Closed | I75: Retrofit | J75: PE06052602
A76: 46170 | B76: TRUE SUN TRADING COMPANY | C76: Manakkakadavu | D76: Kerala | E76: 1 | F76: Pavan | G76: PE26052603 | H76: Closed | I76: Retrofit | J76: PE26052603 | L76: 46171
A77: 46170 | B77: Yanara Power | C77: Holi | D77: Maharashtra | E77: 61 | F77: Gourab + Amit | G77: PE01052601 | H77: Closed | I77: Retrofit | J77: PE01052601
A78: 46171 | B78: Solar Square | C78: Nagpur | D78: Maharashtra | E78: 2 | F78: Chanchal | G78: PE18052601 | H78: Closed | I78: Retrofit | J78: PE18052601 | K78: 46170
A79: 46171 | B79: Solar Square | C79: Nagpur | D79: Maharashtra | E79: 5 | F79: Chanchal | G79: PE26052601 | H79: Closed | I79: Retrofit | J79: PE26052601
A80: 46171 | B80: Continuum | C80: Bhavnagar | D80: Gujarat | E80: 12 | F80: Bhimsen + Raja + Kunal + Kamal | G80: PE06052602 | H80: Closed | I80: Retrofit | J80: PE06052602
A81: 46171 | B81: Yanara Power | C81: Holi | D81: Maharashtra | E81: 65 | F81: Gourab + Amit | G81: PE01052601 | H81: Closed | I81: Retrofit | J81: PE01052601
A82: 46172 | B82: Continuum | C82: Bhavnagar | D82: Gujarat | E82: 58 | F82: Bhimsen + Raja + Kunal + Kamal | G82: PE06052602 | H82: Closed | I82: Retrofit | J82: PE06052602
A83: 46172 | B83: Maya Power | C83: Nagpur | D83: Maharashtra | E83: 6 | F83: Chanchal | G83: PE25052602 | H83: Closed | I83: Retrofit | J83: PE25052602
A84: 46172 | B84: Yanara Power | C84: Holi | D84: Maharashtra | E84: 64 | F84: Gourab + Amit | G84: PE01052601 | H84: Closed | I84: Retrofit | J84: PE01052601
A85: 46173 | B85: Yanara Power | C85: Holi | D85: Maharashtra | E85: 62 | F85: Gourab + Amit | G85: PE01052601 | H85: Closed | I85: Retrofit | J85: PE01052601
A86: 46174 | B86: Continuum | C86: Bhavnagar | D86: Gujarat | E86: 107 | F86: Kamal + Raja + Kunal | G86: PE06052602 | H86: Closed | I86: Retrofit | J86: PE06052602
A87: 46174 | B87: Yanara Power | C87: Holi | D87: Maharashtra | E87: 62 | F87: Gourab + Amit | G87: PE01052601 | H87: Closed | I87: Retrofit | J87: PE01052601

Sheet Monthly Report May-26 (2)
A1: Date | B1: Year | C1: Complaint Raised By | D1: Customer Type | E1: Project Name | F1: Current Status | G1: Claim Reported By | H1: Contact No. | I1: Contract / Complaint / Invoice No. | J1: Customer Reported Problem | K1: Venue / Location | L1: State | M1: Field Evaluation | N1: Our Evaluation | O1: PV Panels Wp | P1: Module Serial Number | Q1: Module Make Year | R1: Module Make Month | S1: Moduel Type | T1: Manufacturing Plant | U1: Remark | V1: Action Taken | W1: Resolution Type | X1: Date of Claim Settled | Y1: Claim Settlement Duration | Z1: Visit Date | AA1: Rework Srl No. | AB1: Work details
A2: 46140 | B2: 2026 | C2: Panasonic | D2: OEM | F2: Closed | G2: Chirag Tare | H2: 7719846027 | I2: PE28042604 | J2: Low VOC | K2: Mysore | L2: Karnataka | M2: JB Issue | N2: JB Issue | O2: 550 | P2: NSMP2304007550 | Q2: =MID(P2,5,2) | R2: =MID(P2,7,2) | S2: G2B | T2: P2 | U2: All JB Issue | V2: JB Changed | W2: Repair | X2: 46143 | Y2: =X2-A2 | Z2: 46143
A3: 46133 | B3: 2026 | C3: Axitec Energy | D3: OEM | F3: Closed | G3: Dushyant | H3: 8826633540 | I3: PE21042602 | J3: Diode Failure | K3: Chinchwad | L3: Maharashtra | M3: Cold Soldering | N3: Cold Soldering | O3: 520 | P3: 26230431008130 | Q3: =MID(P3,3,2) | R3: =MID(P3,5,2) | S3: G2B | T3: P2 | U3: P JB Cold Soldering | V3: Soldering | W3: Repair | X3: 46143 | Y3: =X3-A3 | Z3: 46143
A4: 46133 | B4: 2026 | C4: Axitec Energy | D4: OEM | F4: Closed | G4: Dushyant | H4: 8826633540 | I4: PE21042602 | J4: Diode Failure | K4: Chinchwad | L4: Maharashtra | M4: Cold Soldering | N4: Cold Soldering | O4: 520 | P4: 26230431008116 | Q4: =MID(P4,3,2) | R4: =MID(P4,5,2) | S4: G2B | T4: P2 | U4: P JB Cold Soldering | V4: Soldering | W4: Repair | X4: 46143 | Y4: =X4-A4 | Z4: 46143
A5: 46106 | B5: 2026 | C5: First Energy | D5: Utility and C&I | F5: WIP | G5: Mr. Gaurav | H5: 9979185999 | I5: PE25032601 | J5: Module Defects | K5: Rajkot | L5: Gujarat | M5: hotspot found | N5: Hotspot | O5: 550 | P5: NSMP2409546021 | Q5: =MID(P5,5,2) | R5: =MID(P5,7,2) | S5: G2TB | T5: P2 | U5: Multi Cell Hotspot | V5: Inspection | W5: WIP | Y5: =X5-A5 | Z5: 46143
A6: 46106 | B6: 2026 | C6: First Energy | D6: Utility and C&I | F6: WIP | G6: Mr. Gaurav | H6: 9979185999 | I6: PE25032601 | J6: Module Defects | K6: Rajkot | L6: Gujarat | M6: hotspot found | N6: Hotspot | O6: 550 | P6: NSMP2212269256 | Q6: =MID(P6,5,2) | R6: =MID(P6,7,2) | S6: G2TB | T6: P2 | U6: Multi Cell Hotspot | V6: Inspection | W6: WIP | Y6: =X6-A6 | Z6: 46143
A7: 46106 | B7: 2026 | C7: First Energy | D7: Utility and C&I | F7: WIP | G7: Mr. Gaurav | H7: 9979185999 | I7: PE25032601 | J7: Module Defects | K7: Rajkot | L7: Gujarat | M7: hotspot found | N7: Hotspot | O7: 550 | P7: NSMP2212269311 | Q7: =MID(P7,5,2) | R7: =MID(P7,7,2) | S7: G2TB | T7: P2 | U7: Multi Cell Hotspot | V7: Inspection | W7: WIP | Y7: =X7-A7 | Z7: 46143
A8: 46106 | B8: 2026 | C8: First Energy | D8: Utility and C&I | F8: WIP | G8: Mr. Gaurav | H8: 9979185999 | I8: PE25032601 | J8: Module Defects | K8: Rajkot | L8: Gujarat | M8: hotspot found | N8: Hotspot | O8: 550 | P8: NSMP2212269144 | Q8: =MID(P8,5,2) | R8: =MID(P8,7,2) | S8: G2TB | T8: P2 | U8: Single Cell Hotspot | V8: Inspection | W8: WIP | Y8: =X8-A8 | Z8: 46143
A9: 46106 | B9: 2026 | C9: First Energy | D9: Utility and C&I | F9: WIP | G9: Mr. Gaurav | H9: 9979185999 | I9: PE25032601 | J9: Module Defects | K9: Rajkot | L9: Gujarat | M9: hotspot found | N9: Hotspot | O9: 550 | P9: NSMP2301302211 | Q9: =MID(P9,5,2) | R9: =MID(P9,7,2) | S9: G2TB | T9: P2 | U9: Multi Cell Hotspot | V9: Inspection | W9: WIP | Y9: =X9-A9 | Z9: 46143
A10: 46106 | B10: 2026 | C10: First Energy | D10: Utility and C&I | F10: WIP | G10: Mr. Gaurav | H10: 9979185999 | I10: PE25032601 | J10: Module Defects | K10: Rajkot | L10: Gujarat | M10: hotspot found | N10: Hotspot | O10: 550 | P10: NSMP2301328092 | Q10: =MID(P10,5,2) | R10: =MID(P10,7,2) | S10: G2TB | T10: P2 | U10: Single Cell Hotspot | V10: Inspection | W10: WIP | Y10: =X10-A10 | Z10: 46143
A11: 46106 | B11: 2026 | C11: First Energy | D11: Utility and C&I | F11: WIP | G11: Mr. Gaurav | H11: 9979185999 | I11: PE25032601 | J11: Module Defects | K11: Rajkot | L11: Gujarat | M11: hotspot found | N11: Hotspot | O11: 550 | P11: NSMP2212258292 | Q11: =MID(P11,5,2) | R11: =MID(P11,7,2) | S11: G2TB | T11: P2 | U11: Multi Cell Hotspot | V11: Inspection | W11: WIP | Y11: =X11-A11 | Z11: 46143
A12: 46106 | B12: 2026 | C12: First Energy | D12: Utility and C&I | F12: WIP | G12: Mr. Gaurav | H12: 9979185999 | I12: PE25032601 | J12: Module Defects | K12: Rajkot | L12: Gujarat | M12: hotspot found | N12: Hotspot | O12: 550 | P12: NSMP2212269072 | Q12: =MID(P12,5,2) | R12: =MID(P12,7,2) | S12: G2TB | T12: P2 | U12: Multi Cell Hotspot | V12: Inspection | W12: WIP | Y12: =X12-A12 | Z12: 46143
A13: 46106 | B13: 2026 | C13: First Energy | D13: Utility and C&I | F13: WIP | G13: Mr. Gaurav | H13: 9979185999 | I13: PE25032601 | J13: Module Defects | K13: Rajkot | L13: Gujarat | M13: Broken Module | N13: Hotspot | O13: 550 | P13: NSMP2212277874 | Q13: =MID(P13,5,2) | R13: =MID(P13,7,2) | S13: G2TB | T13: P2 | U13: Multi Cell Hotspot | V13: Inspection | W13: WIP | Y13: =X13-A13 | Z13: 46143
A14: 46106 | B14: 2026 | C14: First Energy | D14: Utility and C&I | F14: WIP | G14: PE02052602 | H14: 9979185999 | I14: PE25032601 | J14: Module Defects | K14: Rajkot | L14: Gujarat | M14: hotspot found | N14: Hotspot | O14: 550 | P14: NSMP2212277882 | Q14: =MID(P14,5,2) | R14: =MID(P14,7,2) | S14: G2TB | T14: P2 | U14: Multi Cell Hotspot | V14: Inspection | W14: WIP | Y14: =X14-A14 | Z14: 46143
A15: 46106 | B15: 2026 | C15: First Energy | D15: Utility and C&I | F15: WIP | G15: Mr. Gaurav | H15: 9979185999 | I15: PE25032601 | J15: Module Defects | K15: Rajkot | L15: Gujarat | M15: hotspot found | N15: Hotspot | O15: 550 | P15: NSMP2212270587 | Q15: =MID(P15,5,2) | R15: =MID(P15,7,2) | S15: G2TB | T15: P2 | U15: Multi Cell Hotspot | V15: Inspection | W15: WIP | Y15: =X15-A15 | Z15: 46143
A16: 46106 | B16: 2026 | C16: First Energy | D16: Utility and C&I | F16: WIP | G16: Mr. Gaurav | H16: 9979185999 | I16: PE25032601 | J16: Module Defects | K16: Rajkot | L16: Gujarat | M16: hotspot found | N16: Hotspot | O16: 550 | P16: NSMP2212277215 | Q16: =MID(P16,5,2) | R16: =MID(P16,7,2) | S16: G2TB | T16: P2 | U16: Multi Cell Hotspot | V16: Inspection | W16: WIP | Y16: =X16-A16 | Z16: 46143
... A48: 46106 | B48: 2026 | C48: First Energy | D48: Utility and C&I | F48: WIP | G48: Mr. Gaurav | H48: 9979185999 | I48: PE25032601 | J48: Module Defects | K48: Rajkot | L48: Gujarat | M48: hotspot found | N48: Hotspot | O48: 550 | P48: NSMP2212283852 | Q48: =MID(P48,5,2) | R48: =MID(P48,7,2) | S48: G2TB | T48: P2 | U48: Single Cell Hotspot | V48: Inspection | W48: WIP | Y48: =X48-A48 | Z48: 46144
A49: 46107 | B49: 2026 | C49: Blupine | D49: Utility and C&I | F49: Closed | G49: Chandrashekar Patidar | H49: 7879764773 | I49: PE26032601 | J49: Module Diode Failure | K49: Sadla | L49: Gujarat | M49: PS | N49: Cold Soldering | O49: 570 | P49: NSMI24050051443 | Q49: =MID(P49,5,2) | R49: =MID(P49,7,2) | S49: G2G | T49: P4 | U49: P JB Cold Soldering | V49: Soldering | W49: Repair | X49: 46144 | Y49: =X49-A49 | Z49: 46144
A50: 46107 | B50: 2026 | C50: Blupine | D50: Utility and C&I | F50: Closed | G50: Chandrashekar Patidar | H50: 7879764773 | I50: PE26032601 | J50: Module Diode Failure | K50: Sadla | L50: Gujarat | M50: NS | N50: Cold Soldering | O50: 570 | P50: NSMI24050044810 | Q50: =MID(P50,5,2) | R50: =MID(P50,7,2) | S50: G2G | T50: P4 | U50: N JB Cold Soldering | V50: Soldering | W50: Repair | X50: 46144 | Y50: =X50-A50 | Z50: 46144
A51: 46107 | B51: 2026 | C51: Blupine | D51: Utility and C&I | F51: Closed | G51: Chandrashekar Patidar | H51: 7879764773 | I51: PE26032601 | J51: Module Diode Failure | K51: Sadla | L51: Gujarat | M51: NS | N51: Cold Soldering | O51: 570 | P51: NSMI24050047018 | Q51: =MID(P51,5,2) | R51: =MID(P51,7,2) | S51: G2G | T51: P4 | U51: N JB Cold Soldering | V51: Soldering | W51: Repair | X51: 46144 | Y51: =X51-A51 | Z51: 46144
A52: 46107 | B52: 2026 | C52: Blupine | D52: Utility and C&I | F52: Closed | G52: Chandrashekar Patidar | H52: 7879764773 | I52: PE26032601 | J52: Module Diode Failure | K52: Sadla | L52: Gujarat | M52: PR | N52: JB Issue | O52: 570 | P52: NSMI24060074092 | Q52: =MID(P52,5,2) | R52: =MID(P52,7,2) | S52: G2G | T52: P4 | U52: P JB Issue | V52: JB Changed | W52: Repair | X52: 46144 | Y52: =X52-A52 | Z52: 46144
A53: 46107 | B53: 2026 | C53: Blupine | D53: Utility and C&I | F53: Closed | G53: Chandrashekar Patidar | H53: 7879764773 | I53: PE26032601 | J53: Module Diode Failure | K53: Sadla | L53: Gujarat | M53: NR | N53: JB Issue | O53: 570 | P53: NSMI24050045987 | Q53: =MID(P53,5,2) | R53: =MID(P53,7,2) | S53: G2G | T53: P4 | U53: N JB Issue | V53: JB Changed | W53: Repair | X53: 46144 | Y53: =X53-A53 | Z53: 46144
A54: 46107 | B54: 2026 | C54: Blupine | D54: Utility and C&I | F54: Closed | G54: Chandrashekar Patidar | H54: 7879764773 | I54: PE26032601 | J54: Module Diode Failure | K54: Sadla | L54: Gujarat | M54: PS | N54: Cold Soldering | O54: 570 | P54: NSMI24050049041 | Q54: =MID(P54,5,2) | R54: =MID(P54,7,2) | S54: G2G | T54: P4 | U54: P JB Cold Soldering | V54: Soldering | W54: Repair | X54: 46144 | Y54: =X54-A54 | Z54: 46144
A55: 46107 | B55: 2026 | C55: Blupine | D55: Utility and C&I | F55: Closed | G55: Chandrashekar Patidar | H55: 7879764773 | I55: PE26032601 | J55: Module Diode Failure | K55: Sadla | L55: Gujarat | M55: NS | N55: Cold Soldering | O55: 570 | P55: NSMI24050045772 | Q55: =MID(P55,5,2) | R55: =MID(P55,7,2) | S55: G2G | T55: P4 | U55: N JB Cold Soldering | V55: Soldering | W55: Repair | X55: 46144 | Y55: =X55-A55 | Z55: 46144
A56: 46107 | B56: 2026 | C56: Blupine | D56: Utility and C&I | F56: Closed | G56: Chandrashekar Patidar | H56: 7879764773 | I56: PE26032601 | J56: Module Diode Failure | K56: Sadla | L56: Gujarat | M56: NS | N56: Cold Soldering | O56: 570 | P56: NSMI24050045804 | Q56: =MID(P56,5,2) | R56: =MID(P56,7,2) | S56: G2G | T56: P4 | U56: N JB Cold Soldering | V56: Soldering | W56: Repair | X56: 46144 | Y56: =X56-A56 | Z56: 46144
A57: 46107 | B57: 2026 | C57: Blupine | D57: Utility and C&I | F57: Closed | G57: Chandrashekar Patidar | H57: 7879764773 | I57: PE26032601 | J57: Module Diode Failure | K57: Sadla | L57: Gujarat | M57: NS | N57: Cold Soldering | O57: 570 | P57: NSMI24050045790 | Q57: =MID(P57,5,2) | R57: =MID(P57,7,2) | S57: G2G | T57: P4 | U57: N JB Cold Soldering | V57: Soldering | W57: Repair | X57: 46144 | Y57: =X57-A57 | Z57: 46144
A58: 46107 | B58: 2026 | C58: Blupine | D58: Utility and C&I | F58: Closed | G58: Chandrashekar Patidar | H58: 7879764773 | I58: PE26032601 | J58: Module Diode Failure | K58: Sadla | L58: Gujarat | M58: PNS | N58: Cold Soldering | O58: 570 | P58: NSMI24080334590 | Q58: =MID(P58,5,2) | R58: =MID(P58,7,2) | S58: G2G | T58: P4 | U58: P & N JB Cold Soldering | V58: Soldering | W58: Repair | X58: 46144 | Y58: =X58-A58 | Z58: 46144
A59: 46107 | B59: 2026 | C59: Blupine | D59: Utility and C&I | F59: Closed | G59: Chandrashekar Patidar | H59: 7879764773 | I59: PE26032601 | J59: Module Diode Failure | K59: Sadla | L59: Gujarat | M59: NS | N59: Cold Soldering | O59: 570 | P59: NSMI24050045988 | Q59: =MID(P59,5,2) | R59: =MID(P59,7,2) | S59: G2G | T59: P4 | U59: N JB Cold Soldering | V59: Soldering | W59: Repair | X59: 46144 | Y59: =X59-A59 | Z59: 46144
A60: 46107 | B60: 2026 | C60: Blupine | D60: Utility and C&I | F60: Closed | G60: Chandrashekar Patidar | H60: 7879764773 | I60: PE26032601 | J60: Module Diode Failure | K60: Sadla | L60: Gujarat | M60: NS | N60: Cold Soldering | O60: 570 | P60: NSMI24050045952 | Q60: =MID(P60,5,2) | R60: =MID(P60,7,2) | S60: G2G | T60: P4 | U60: N JB Cold Soldering | V60: Soldering | W60: Repair | X60: 46144 | Y60: =X60-A60 | Z60: 46144
... A100: 46107 | B100: 2026 | C100: Blupine | D100: Utility and C&I | F100: Closed | G100: Chandrashekar Patidar | H100: 7879764773 | I100: PE26032601 | J100: Module Diode Failure | K100: Sadla | L100: Gujarat | M100: PS | N100: Cold Soldering | O100: 570 | P100: NSMI24060079795 | Q100: =MID(P100,5,2) | R100: =MID(P100,7,2) | S100: G2G | T100: P4 | U100: P JB Cold Soldering | V100: Soldering | W100: Repair | X100: 46144 | Y100: =X100-A100 | Z100: 46144
A101: 46118 | B101: 2026 | C101: Panasonic | D101: OEM | F101: WIP | G101: Chirag Tare | H101: 7719846027 | I101: PE06042602 | J101: Low VOC | K101: Dhule | L101: Maharashtra | M101: Backsheet Scratches | N101: Backsheet Scratches | O101: 330 | P101: NSM210403505 | Q101: =MID(P101,4,2) | R101: =MID(P101,6,2) | S101: G2B | T101: P1 | U101: Backsheet Scratches | V101: Rejected | W101: Rejected | X101: 46144 | Y101: =X101-A101 | Z101: 46144
A102: 46118 | B102: 2026 | C102: Panasonic | D102: OEM | F102: WIP | G102: Chirag Tare | H102: 7719846027 | I102: PE06042602 | J102: Low VOC | K102: Dhule | L102: Maharashtra | M102: Cell Contamination | N102: Cell Contamination | O102: 330 | P102: NSM210446420 | Q102: =MID(P102,4,2) | R102: =MID(P102,6,2) | S102: G2B | T102: P1 | U102: Cell Contamination | V102: Inspection | W102: WIP | Y102: =X102-A102 | Z102: 46144
A103: 46112 | B103: 2026 | C103: RA GREEN ENERGks | D103: Channel Sales | F103: Closed | G103: Kumar Tale | H103: 9518921202 | I103: PE31032602 | J103: MC 4 Connector Burn | K103: Nagpur | L103: Maharashtra | M103: Found okay | N103: No Issue | O103: 540 | P103: NSMP25050188956 | Q103: =MID(P103,5,2) | R103: =MID(P103,7,2) | S103: G2TB | T103: P2 | U103: No Issue Found | V103: Found OK | W103: Repair | X103: 46146 | Y103: =X103-A103 | Z103: 46146
A104: 46119 | B104: 2026 | C104: Panasonic | D104: OEM | F104: Closed | G104: Chirag Tare | H104: 7719846027 | I104: PE07042601 | J104: Low VOC | K104: Lucknow | L104: UP | M104: Negative JB Soldering | N104: Cold Soldering | O104: 495 | P104: NSMP2211233510 | Q104: =MID(P104,5,2) | R104: =MID(P104,7,2) | S104: G2B | T104: P2 | U104: N JB Cold Soldering | V104: Soldering | W104: Repair | X104: 46146 | Y104: =X104-A104 | Z104: 46146
A105: 46119 | B105: 2026 | C105: Panasonic | D105: OEM | F105: Closed | G105: Chirag Tare | H105: 7719846027 | I105: PE07042601 | J105: Low VOC | K105: Lucknow | L105: UP | M105: Negative JB Soldering | N105: Cold Soldering | O105: 495 | P105: NSMP2211233542 | Q105: =MID(P105,5,2) | R105: =MID(P105,7,2) | S105: G2B | T105: P2 | U105: N JB Cold Soldering | V105: Soldering | W105: Repair | X105: 46146 | Y105: =X105-A105 | Z105: 46146
A106: 46119 | B106: 2026 | C106: Panasonic | D106: OEM | F106: Closed | G106: Chirag Tare | H106: 7719846027 | I106: PE07042601 | J106: Low VOC | K106: Lucknow | L106: UP | M106: Negative JB Soldering | N106: Cold Soldering | O106: 495 | P106: NSMP2211233550 | Q106: =MID(P106,5,2) | R106: =MID(P106,7,2) | S106: G2B | T106: P2 | U106: N JB Cold Soldering | V106: Soldering | W106: Repair | X106: 46146 | Y106: =X106-A106 | Z106: 46146
A107: 46144 | B107: 2026 | C107: Oyster Technocon | D107: Channel Sales | F107: Closed | G107: Inderpal Singh | H107: 9028940248 | I107: PE02052601 | J107: Low solar panel generation | K107: Nagpur | L107: Maharashtra | M107: Found okay | N107: No Issue | O107: 540 | P107: N/A | Q107: =MID(P107,5,2) | R107: =MID(P107,7,2) | S107: G2TB | T107: P2 | U107: No Issue Found | V107: Found OK | W107: Repair | X107: 46146 | Y107: =X107-A107 | Z107: 46146
A108: 46144 | B108: 2026 | C108: Oyster Technocon | D108: Channel Sales | F108: Closed | G108: Inderpal Singh | H108: 9028940248 | I108: PE02052601 | J108: Low solar panel generation | K108: Nagpur | L108: Maharashtra | M108: Found okay | N108: No Issue | O108: 540 | P108: N/A | Q108: =MID(P108,5,2) | R108: =MID(P108,7,2) | S108: G2TB | T108: P2 | U108: No Issue Found | V108: Found OK | W108: Repair | X108: 46146 | Y108: =X108-A108 | Z108: 46146
A109: 46144 | B109: 2026 | C109: Oyster Technocon | D109: Channel Sales | F109: Closed | G109: Inderpal Singh | H109: 9028940248 | I109: PE02052601 | J109: Low solar panel generation | K109: Nagpur | L109: Maharashtra | M109: Found okay | N109: No Issue | O109: 540 | P109: N/A | Q109: =MID(P109,5,2) | R109: =MID(P109,7,2) | S109: G2TB | T109: P2 | U109: No Issue Found | V109: Found OK | W109: Repair | X109: 46146 | Y109: =X109-A109 | Z109: 46146
A110: 46144 | B110: 2026 | C110: Oyster Technocon | D110: Channel Sales | F110: Closed | G110: Inderpal Singh | H110: 9028940248 | I110: PE02052601 | J110: Low solar panel generation | K110: Nagpur | L110: Maharashtra | M110: Found okay | N110: No Issue | O110: 540 | P110: N/A | Q110: =MID(P110,5,2) | R110: =MID(P110,7,2) | S110: G2TB | T110: P2 | U110: No Issue Found | V110: Found OK | W110: Repair | X110: 46146 | Y110: =X110-A110 | Z110: 46146
A111: 46144 | B111: 2026 | C111: Oyster Technocon | D111: Channel Sales | F111: Closed | G111: Inderpal Singh | H111: 9028940248 | I111: PE02052601 | J111: Low solar panel generation | K111: Nagpur | L111: Maharashtra | M111: Found okay | N111: No Issue | O111: 540 | P111: N/A | Q111: =MID(P111,5,2) | R111: =MID(P111,7,2) | S111: G2TB | T111: P2 | U111: No Issue Found | V111: Found OK | W111: Repair | X111: 46146 | Y111: =X111-A111 | Z111: 46146
A112: 46144 | B112: 2026 | C112: Oyster Technocon | D112: Channel Sales | F112: Closed | G112: Inderpal Singh | H112: 9028940248 | I112: PE02052601 | J112: Low solar panel generation | K112: Nagpur | L112: Maharashtra | M112: Found okay | N112: No Issue | O112: 540 | P112: N/A | Q112: =MID(P112,5,2) | R112: =MID(P112,7,2) | S112: G2TB | T112: P2 | U112: No Issue Found | V112: Found OK | W112: Repair | X112: 46146 | Y112: =X112-A112 | Z112: 46146
A113: 46144 | B113: 2026 | C113: Oyster Technocon | D113: Channel Sales | F113: Closed | G113: Inderpal Singh | H113: 9028940248 | I113: PE02052602 | J113: Low solar panel generation | K113: Nagpur | L113: Maharashtra | M113: AR | N113: JB Issue | O113: 540 | P113: NSMP24101626059 | Q113: =MID(P113,5,2) | R113: =MID(P113,7,2) | S113: G2TB | T113: P2 | U113: All JB Issue | V113: JB Changed | W113: Repair | X113: 46146 | Y113: =X113-A113 | Z113: 46146
A114: 46144 | B114: 2026 | C114: Oyster Technocon | D114: Channel Sales | F114: Closed | G114: Inderpal Singh | H114: 9028940248 | I114: PE02052602 | J114: Low solar panel generation | K114: Nagpur | L114: Maharashtra | M114: AR | N114: JB Issue | O114: 540 | P114: NSMP24101626041 | Q114: =MID(P114,5,2) | R114: =MID(P114,7,2) | S114: G2TB | T114: P2 | U114: All JB Issue | V114: JB Changed | W114: Repair | X114: 46146 | Y114: =X114-A114 | Z114: 46146
... A118: 46144 | B118: 2026 | C118: Oyster Technocon | D118: Channel Sales | F118: Closed | G118: Inderpal Singh | H118: 9028940248 | I118: PE02052602 | J118: Low solar panel generation | K118: Nagpur | L118: Maharashtra | M118: Found okay | N118: No Issue | O118: 540 | P118: N/A | Q118: =MID(P118,5,2) | R118: =MID(P118,7,2) | S118: G2TB | T118: P2 | U118: No Issue Found | V118: Found OK | W118: Repair | X118: 46146 | Y118: =X118-A118 | Z118: 46146
A119: 46106 | B119: 2026 | C119: First Energy | D119: Utility and C&I | F119: WIP | G119: Mr. Gaurav | H119: 9979185999 | I119: PE25032601 | J119: Module Defects | K119: Rajkot | L119: Gujarat | M119: hotspot found | N119: Hotspot | O119: 550 | P119: NSMP2212285926 | Q119: =MID(P119,5,2) | R119: =MID(P119,7,2) | S119: G2TB | T119: P2 | U119: Multi Cell Hotspot | V119: Inspection | W119: WIP | Y119: =X119-A119 | Z119: 46146
A120: 46106 | B120: 2026 | C120: First Energy | D120: Utility and C&I | F120: WIP | G120: Mr. Gaurav | H120: 9979185999 | I120: PE25032601 | J120: Module Defects | K120: Rajkot | L120: Gujarat | M120: hotspot found | N120: Hotspot | O120: 550 | P120: NSMP2212276765 | Q120: =MID(P120,5,2) | R120: =MID(P120,7,2) | S120: G2TB | T120: P2 | U120: Single Cell Hotspot | V120: Inspection | W120: WIP | Y120: =X120-A120 | Z120: 46146
A121: 46106 | B121: 2026 | C121: First Energy | D121: Utility and C&I | F121: WIP | G121: Mr. Gaurav | H121: 9979185999 | I121: PE25032601 | J121: Module Defects | K121: Rajkot | L121: Gujarat | M121: Broken Module | N121: Hotspot | O121: 550 | P121: NSMP2301293423 | Q121: =MID(P121,5,2) | R121: =MID(P121,7,2) | S121: G2TB | T121: P2 | U121: Multi Cell Hotspot | V121: Inspection | W121: WIP | Y121: =X121-A121 | Z121: 46146
A122: 46106 | B122: 2026 | C122: First Energy | D122: Utility and C&I | F122: WIP | G122: Mr. Gaurav | H122: 9979185999 | I122: PE25032601 | J122: Module Defects | K122: Rajkot | L122: Gujarat | M122: hotspot found | N122: Hotspot | O122: 550 | P122: NSMP2301328643 | Q122: =MID(P122,5,2) | R122: =MID(P122,7,2) | S122: G2TB | T122: P2 | U122: Multi Cell Hotspot | V122: Inspection | W122: WIP | Y122: =X122-A122 | Z122: 46146
A123: 46106 | B123: 2026 | C123: First Energy | D123: Utility and C&I | F123: WIP | G123: Mr. Gaurav | H123: 9979185999 | I123: PE25032601 | J123: Module Defects | K123: Rajkot | L123: Gujarat | M123: hotspot found | N123: Hotspot | O123: 550 | P123: NSMP2212270666 | Q123: =MID(P123,5,2) | R123: =MID(P123,7,2) | S123: G2TB | T123: P2 | U123: Multi Cell Hotspot | V123: Inspection | W123: WIP | Y123: =X123-A123 | Z123: 46146
A124: 46106 | B124: 2026 | C124: First Energy | D124: Utility and C&I | F124: WIP | G124: Mr. Gaurav | H124: 9979185999 | I124: PE25032601 | J124: Module Defects | K124: Rajkot | L124: Gujarat | M124: hotspot found | N124: Hotspot | O124: 550 | P124: NSMP2212268452 | Q124: =MID(P124,5,2) | R124: =MID(P124,7,2) | S124: G2TB | T124: P2 | U124: Single Cell Hotspot | V124: Inspection | W124: WIP | Y124: =X124-A124 | Z124: 46146
A125: 46106 | B125: 2026 | C125: First Energy | D125: Utility and C&I | F125: WIP | G125: Mr. Gaurav | H125: 9979185999 | I125: PE25032601 | J125: Module Defects | K125: Rajkot | L125: Gujarat | M125: hotspot found | N125: Hotspot | O125: 550 | P125: NSMP2212271260 | Q125: =MID(P125,5,2) | R125: =MID(P125,7,2) | S125: G2TB | T125: P2 | U125: Multi Cell Hotspot | V125: Inspection | W125: WIP | Y125: =X125-A125 | Z125: 46146
A126: 46106 | B126: 2026 | C126: First Energy | D126: Utility and C&I | F126: WIP | G126: Mr. Gaurav | H126: 9979185999 | I126: PE25032601 | J126: Module Defects | K126: Rajkot | L126: Gujarat | M126: hotspot found | N126: Hotspot | O126: 550 | P126: NSMP2301334386 | Q126: =MID(P126,5,2) | R126: =MID(P126,7,2) | S126: G2TB | T126: P2 | U126: Multi Cell Hotspot | V126: Inspection | W126: WIP | Y126: =X126-A126 | Z126: 46146
A127: 46106 | B127: 2026 | C127: First Energy | D127: Utility and C&I | F127: WIP | G127: Mr. Gaurav | H127: 9979185999 | I127: PE25032601 | J127: Module Defects | K127: Rajkot | L127: Gujarat | M127: hotspot found | N127: Hotspot | O127: 550 | P127: NSMP2301334369 | Q127: =MID(P127,5,2) | R127: =MID(P127,7,2) | S127: G2TB | T127: P2 | U127: Multi Cell Hotspot | V127: Inspection | W127: WIP | Y127: =X127-A127 | Z127: 46146
A128: 46106 | B128: 2026 | C128: First Energy | D128: Utility and C&I | F128: WIP | G128: Mr. Gaurav | H128: 9979185999 | I128: PE25032601 | J128: Module Defects | K128: Rajkot | L128: Gujarat | M128: hotspot found | N128: Hotspot | O128: 550 | P128: NSMP2301306009 | Q128: =MID(P128,5,2) | R128: =MID(P128,7,2) | S128: G2TB | T128: P2 | U128: Multi Cell Hotspot | V128: Inspection | W128: WIP | Y128: =X128-A128 | Z128: 46146
A129: 46106 | B129: 2026 | C129: First Energy | D129: Utility and C&I | F129: WIP | G129: Mr. Gaurav | H129: 9979185999 | I129: PE25032601 | J129: Module Defects | K129: Rajkot | L129: Gujarat | M129: hotspot found | N129: Hotspot | O129: 550 | P129: NSMP2212268876 | Q129: =MID(P129,5,2) | R129: =MID(P129,7,2) | S129: G2TB | T129: P2 | U129: Multi Cell Hotspot | V129: Inspection | W129: WIP | Y129: =X129-A129 | Z129: 46146
A130: 46106 | B130: 2026 | C130: First Energy | D130: Utility and C&I | F130: WIP | G130: Mr. Gaurav | H130: 9979185999 | I130: PE25032601 | J130: Module Defects | K130: Rajkot | L130: Gujarat | M130: hotspot found | N130: Hotspot | O130: 550 | P130: NSMP2301294074 | Q130: =MID(P130,5,2) | R130: =MID(P130,7,2) | S130: G2TB | T130: P2 | U130: Multi Cell Hotspot | V130: Inspection | W130: WIP | Y130: =X130-A130 | Z130: 46146
... A171: 46106 | B171: 2026 | C171: First Energy | D171: Utility and C&I | F171: WIP | G171: Mr. Gaurav | H171: 9979185999 | I171: PE25032601 | J171: Module Defects | K171: Rajkot | L171: Gujarat | M171: hotspot found | N171: Hotspot | O171: 550 | P171: NSMP2212268843 | Q171: =MID(P171,5,2) | R171: =MID(P171,7,2) | S171: G2TB | T171: P2 | U171: Multi Cell Hotspot | V171: Inspection | W171: WIP | Y171: =X171-A171 | Z171: 46146
A172: 46107 | B172: 2026 | C172: Blupine | D172: Utility and C&I | F172: Closed | G172: Chandrashekar Patidar | H172: 7879764773 | I172: PE26032601 | J172: Module Diode Failure | K172: Sadla | L172: Gujarat | M172: PS | N172: Cold Soldering | O172: 570 | P172: NSMI24060082881 | Q172: =MID(P172,5,2) | R172: =MID(P172,7,2) | S172: G2G | T172: P4 | U172: P JB Cold Soldering | V172: Soldering | W172: Repair | X172: 46146 | Y172: =X172-A172 | Z172: 46146
A173: 46107 | B173: 2026 | C173: Blupine | D173: Utility and C&I | F173: Closed | G173: Chandrashekar Patidar | H173: 7879764773 | I173: PE26032601 | J173: Module Diode Failure | K173: Sadla | L173: Gujarat | M173: PR | N173: JB Issue | O173: 570 | P173: NSMI24060078866 | Q173: =MID(P173,5,2) | R173: =MID(P173,7,2) | S173: G2G | T173: P4 | U173: P JB Issue | V173: JB Changed | W173: Repair | X173: 46146 | Y173: =X173-A173 | Z173: 46146
A174: 46107 | B174: 2026 | C174: Blupine | D174: Utility and C&I | F174: Closed | G174: Chandrashekar Patidar | H174: 7879764773 | I174: PE26032601 | J174: Module Diode Failure | K174: Sadla | L174: Gujarat | M174: NS | N174: Cold Soldering | O174: 570 | P174: NSMI24050045117 | Q174: =MID(P174,5,2) | R174: =MID(P174,7,2) | S174: G2G | T174: P4 | U174: N JB Cold Soldering | V174: Soldering | W174: Repair | X174: 46146 | Y174: =X174-A174 | Z174: 46146
A175: 46107 | B175: 2026 | C175: Blupine | D175: Utility and C&I | F175: Closed | G175: Chandrashekar Patidar | H175: 7879764773 | I175: PE26032601 | J175: Module Diode Failure | K175: Sadla | L175: Gujarat | M175: PS | N175: Cold Soldering | O175: 570 | P175: NSMI24050046653 | Q175: =MID(P175,5,2) | R175: =MID(P175,7,2) | S175: G2G | T175: P4 | U175: P JB Cold Soldering | V175: Soldering | W175: Repair | X175: 46146 | Y175: =X175-A175 | Z175: 46146
A176: 46107 | B176: 2026 | C176: Blupine | D176: Utility and C&I | F176: Closed | G176: Chandrashekar Patidar | H176: 7879764773 | I176: PE26032601 | J176: Module Diode Failure | K176: Sadla | L176: Gujarat | M176: NS | N176: Cold Soldering | O176: 570 | P176: NSMI24050047065 | Q176: =MID(P176,5,2) | R176: =MID(P176,7,2) | S176: G2G | T176: P4 | U176: N JB Cold Soldering | V176: Soldering | W176: Repair | X176: 46146 | Y176: =X176-A176 | Z176: 46146
A177: 46107 | B177: 2026 | C177: Blupine | D177: Utility and C&I | F177: Closed | G177: Chandrashekar Patidar | H177: 7879764773 | I177: PE26032601 | J177: Module Diode Failure | K177: Sadla | L177: Gujarat | M177: NS | N177: Cold Soldering | O177: 570 | P177: NSMI24050047103 | Q177: =MID(P177,5,2) | R177: =MID(P177,7,2) | S177: G2G | T177: P4 | U177: N JB Cold Soldering | V177: Soldering | W177: Repair | X177: 46146 | Y177: =X177-A177 | Z177: 46146
A178: 46107 | B178: 2026 | C178: Blupine | D178: Utility and C&I | F178: Closed | G178: Chandrashekar Patidar | H178: 7879764773 | I178: PE26032601 | J178: Module Diode Failure | K178: Sadla | L178: Gujarat | M178: NS | N178: Cold Soldering | O178: 570 | P178: NSMI24050047066 | Q178: =MID(P178,5,2) | R178: =MID(P178,7,2) | S178: G2G | T178: P4 | U178: N JB Cold Soldering | V178: Soldering | W178: Repair | X178: 46146 | Y178: =X178-A178 | Z178: 46146
A179: 46107 | B179: 2026 | C179: Blupine | D179: Utility and C&I | F179: Closed | G179: Chandrashekar Patidar | H179: 7879764773 | I179: PE26032601 | J179: Module Diode Failure | K179: Sadla | L179: Gujarat | M179: PS | N179: Cold Soldering | O179: 570 | P179: NSMI24050062182 | Q179: =MID(P179,5,2) | R179: =MID(P179,7,2) | S179: G2G | T179: P4 | U179: P JB Cold Soldering | V179: Soldering | W179: Repair | X179: 46146 | Y179: =X179-A179 | Z179: 46146
A180: 46107 | B180: 2026 | C180: Blupine | D180: Utility and C&I | F180: Closed | G180: Chandrashekar Patidar | H180: 7879764773 | I180: PE26032601 | J180: Module Diode Failure | K180: Sadla | L180: Gujarat | M180: PS | N180: Cold Soldering | O180: 570 | P180: NSMI24050062296 | Q180: =MID(P180,5,2) | R180: =MID(P180,7,2) | S180: G2G | T180: P4 | U180: P JB Cold Soldering | V180: Soldering | W180: Repair | X180: 46146 | Y180: =X180-A180 | Z180: 46146
A181: 46107 | B181: 2026 | C181: Blupine | D181: Utility and C&I | F181: Closed | G181: Chandrashekar Patidar | H181: 7879764773 | I181: PE26032601 | J181: Module Diode Failure | K181: Sadla | L181: Gujarat | M181: PS | N181: Cold Soldering | O181: 570 | P181: NSMI24050058917 | Q181: =MID(P181,5,2) | R181: =MID(P181,7,2) | S181: G2G | T181: P4 | U181: P JB Cold Soldering | V181: Soldering | W181: Repair | X181: 46146 | Y181: =X181-A181 | Z181: 46146
A182: 46107 | B182: 2026 | C182: Blupine | D182: Utility and C&I | F182: Closed | G182: Chandrashekar Patidar | H182: 7879764773 | I182: PE26032601 | J182: Module Diode Failure | K182: Sadla | L182: Gujarat | M182: NS | N182: Cold Soldering | O182: 570 | P182: NSMI24050058951 | Q182: =MID(P182,5,2) | R182: =MID(P182,7,2) | S182: G2G | T182: P4 | U182: N JB Cold Soldering | V182: Soldering | W182: Repair | X182: 46146 | Y182: =X182-A182 | Z182: 46146
A183: 46107 | B183: 2026 | C183: Blupine | D183: Utility and C&I | F183: Closed | G183: Chandrashekar Patidar | H183: 7879764773 | I183: PE26032601 | J183: Module Diode Failure | K183: Sadla | L183: Gujarat | M183: NS | N183: Cold Soldering | O183: 570 | P183: NSMI24050048483 | Q183: =MID(P183,5,2) | R183: =MID(P183,7,2) | S183: G2G | T183: P4 | U183: N JB Cold Soldering | V183: Soldering | W183: Repair | X183: 46146 | Y183: =X183-A183 | Z183: 46146
... A202: 46107 | B202: 2026 | C202: Blupine | D202: Utility and C&I | F202: Closed | G202: Chandrashekar Patidar | H202: 7879764773 | I202: PE26032601 | J202: Module Diode Failure | K202: Sadla | L202: Gujarat | M202: PS | N202: Cold Soldering | O202: 570 | P202: NSMI24050060839 | Q202: =MID(P202,5,2) | R202: =MID(P202,7,2) | S202: G2G | T202: P4 | U202: P JB Cold Soldering | V202: Soldering | W202: Repair | X202: 46146 | Y202: =X202-A202 | Z202: 46146
A203: 46107 | B203: 2026 | C203: Blupine | D203: Utility and C&I | F203: Closed | G203: Chandrashekar Patidar | H203: 7879764773 | I203: PE26032601 | J203: Module Diode Failure | K203: Sadla | L203: Gujarat | M203: Both Glass Broken | N203: Glass Breakage | O203: 570 | P203: NSMI24050064954 | Q203: =MID(P203,5,2) | R203: =MID(P203,7,2) | S203: G2G | T203: P4 | U203: Both Side Glass Breakage | V203: Inspection | W203: WIP | Y203: =X203-A203 | Z203: 46146
A204: 46107 | B204: 2026 | C204: Blupine | D204: Utility and C&I | F204: Closed | G204: Chandrashekar Patidar | H204: 7879764773 | I204: PE26032601 | J204: Module Diode Failure | K204: Sadla | L204: Gujarat | M204: PR | N204: JB Issue | O204: 570 | P204: NSMI24050064599 | Q204: =MID(P204,5,2) | R204: =MID(P204,7,2) | S204: G2G | T204: P4 | U204: P JB Issue | V204: JB Changed | W204: Repair | X204: 46146 | Y204: =X204-A204 | Z204: 46146
A205: 46107 | B205: 2026 | C205: Blupine | D205: Utility and C&I | F205: Closed | G205: Chandrashekar Patidar | H205: 7879764773 | I205: PE26032601 | J205: Module Diode Failure | K205: Sadla | L205: Gujarat | M205: NS | N205: Cold Soldering | O205: 570 | P205: NSMI24050057589 | Q205: =MID(P205,5,2) | R205: =MID(P205,7,2) | S205: G2G | T205: P4 | U205: N JB Cold Soldering | V205: Soldering | W205: Repair | X205: 46146 | Y205: =X205-A205 | Z205: 46146
A206: 46107 | B206: 2026 | C206: Blupine | D206: Utility and C&I | F206: Closed | G206: Chandrashekar Patidar | H206: 7879764773 | I206: PE26032601 | J206: Module Diode Failure | K206: Sadla | L206: Gujarat | M206: NS | N206: Cold Soldering | O206: 570 | P206: NSMI24050057259 | Q206: =MID(P206,5,2) | R206: =MID(P206,7,2) | S206: G2G | T206: P4 | U206: N JB Cold Soldering | V206: Soldering | W206: Repair | X206: 46146 | Y206: =X206-A206 | Z206: 46146
A207: 46107 | B207: 2026 | C207: Blupine | D207: Utility and C&I | F207: Closed | G207: Chandrashekar Patidar | H207: 7879764773 | I207: PE26032601 | J207: Module Diode Failure | K207: Sadla | L207: Gujarat | M207: Glass Broken & Burn Spot | N207: Glass Breakage | O207: 570 | P207: NSMI24050053859 | Q207: =MID(P207,5,2) | R207: =MID(P207,7,2) | S207: G2G | T207: P4 | U207: Glass Breakage & Burn Spot | V207: Inspection | W207: WIP | Y207: =X207-A207 | Z207: 46146
A208: 46107 | B208: 2026 | C208: Blupine | D208: Utility and C&I | F208: Closed | G208: Chandrashekar Patidar | H208: 7879764773 | I208: PE26032601 | J208: Module Diode Failure | K208: Sadla | L208: Gujarat | M208: NS | N208: Cold Soldering | O208: 570 | P208: NSMI24050063310 | Q208: =MID(P208,5,2) | R208: =MID(P208,7,2) | S208: G2G | T208: P4 | U208: N JB Cold Soldering | V208: Soldering | W208: Repair | X208: 46146 | Y208: =X208-A208 | Z208: 46146
A209: 46107 | B209: 2026 | C209: Blupine | D209: Utility and C&I | F209: Closed | G209: Chandrashekar Patidar | H209: 7879764773 | I209: PE26032601 | J209: Module Diode Failure | K209: Sadla | L209: Gujarat | M209: PS | N209: Cold Soldering | O209: 570 | P209: NSMI24050057514 | Q209: =MID(P209,5,2) | R209: =MID(P209,7,2) | S209: G2G | T209: P4 | U209: P JB Cold Soldering | V209: Soldering | W209: Repair | X209: 46146 | Y209: =X209-A209 | Z209: 46146
A210: 46107 | B210: 2026 | C210: Blupine | D210: Utility and C&I | F210: Closed | G210: Chandrashekar Patidar | H210: 7879764773 | I210: PE26032601 | J210: Module Diode Failure | K210: Sadla | L210: Gujarat | M210: Ok | N210: No Issue | O210: 570 | P210: NSMI24050053698 | Q210: =MID(P210,5,2) | R210: =MID(P210,7,2) | S210: G2G | T210: P4 | U210: No Issue Found | V210: Found OK | W210: Repair | X210: 46146 | Y210: =X210-A210 | Z210: 46146
A211: 46107 | B211: 2026 | C211: Blupine | D211: Utility and C&I | F211: Closed | G211: Chandrashekar Patidar | H211: 7879764773 | I211: PE26032601 | J211: Module Diode Failure | K211: Sadla | L211: Gujarat | M211: NS | N211: Cold Soldering | O211: 570 | P211: NSMI24050061694 | Q211: =MID(P211,5,2) | R211: =MID(P211,7,2) | S211: G2G | T211: P4 | U211: N JB Cold Soldering | V211: Soldering | W211: Repair | X211: 46146 | Y211: =X211-A211 | Z211: 46146
A212: 46107 | B212: 2026 | C212: Blupine | D212: Utility and C&I | F212: Closed | G212: Chandrashekar Patidar | H212: 7879764773 | I212: PE26032601 | J212: Module Diode Failure | K212: Sadla | L212: Gujarat | M212: Glass Broken & Burn Spot | N212: Glass Breakage | O212: 570 | P212: NSMI24050065938 | Q212: =MID(P212,5,2) | R212: =MID(P212,7,2) | S212: G2G | T212: P4 | U212: Glass Breakage & Burn Spot | V212: Inspection | W212: WIP | Y212: =X212-A212 | Z212: 46146
A213: 46107 | B213: 2026 | C213: Blupine | D213: Utility and C&I | F213: Closed | G213: Chandrashekar Patidar | H213: 7879764773 | I213: PE26032601 | J213: Module Diode Failure | K213: Sadla | L213: Gujarat | M213: NS | N213: Cold Soldering | O213: 570 | P213: NSMI24050066111 | Q213: =MID(P213,5,2) | R213: =MID(P213,7,2) | S213: G2G | T213: P4 | U213: N JB Cold Soldering | V213: Soldering | W213: Repair | X213: 46146 | Y213: =X213-A213 | Z213: 46146
A214: 46107 | B214: 2026 | C214: Blupine | D214: Utility and C&I | F214: Closed | G214: Chandrashekar Patidar | H214: 7879764773 | I214: PE26032601 | J214: Module Diode Failure | K214: Sadla | L214: Gujarat | M214: NS | N214: Cold Soldering | O214: 570 | P214: NSMI24060078566 | Q214: =MID(P214,5,2) | R214: =MID(P214,7,2) | S214: G2G | T214: P4 | U214: N JB Cold Soldering | V214: Soldering | W214: Repair | X214: 46146 | Y214: =X214-A214 | Z214: 46146
A215: 46107 | B215: 2026 | C215: Blupine | D215: Utility and C&I | F215: Closed | G215: Chandrashekar Patidar | H215: 7879764773 | I215: PE26032601 | J215: Module Diode Failure | K215: Sadla | L215: Gujarat | M215: PS | N215: Cold Soldering | O215: 570 | P215: NSMI24060085543 | Q215: =MID(P215,5,2) | R215: =MID(P215,7,2) | S215: G2G | T215: P4 | U215: P JB Cold Soldering | V215: Soldering | W215: Repair | X215: 46146 | Y215: =X215-A215 | Z215: 46146
A216: 46107 | B216: 2026 | C216: Blupine | D216: Utility and C&I | F216: Closed | G216: Chandrashekar Patidar | H216: 7879764773 | I216: PE26032601 | J216: Module Diode Failure | K216: Sadla | L216: Gujarat | M216: PNS | N216: Cold Soldering | O216: 570 | P216: NSMI24060115780 | Q216: =MID(P216,5,2) | R216: =MID(P216,7,2) | S216: G2G | T216: P4 | U216: P & N JB Cold Soldering | V216: Soldering | W216: Repair | X216: 46146 | Y216: =X216-A216 | Z216: 46146
A217: 46107 | B217: 2026 | C217: Blupine | D217: Utility and C&I | F217: Closed | G217: Chandrashekar Patidar | H217: 7879764773 | I217: PE26032601 | J217: Module Diode Failure | K217: Sadla | L217: Gujarat | M217: PS | N217: Cold Soldering | O217: 570 | P217: NSMI24050066982 | Q217: =MID(P217,5,2) | R217: =MID(P217,7,2) | S217: G2G | T217: P4 | U217: P JB Cold Soldering | V217: Soldering | W217: Repair | X217: 46146 | Y217: =X217-A217 | Z217: 46146
A218: 46107 | B218: 2026 | C218: Blupine | D218: Utility and C&I | F218: Closed | G218: Chandrashekar Patidar | H218: 7879764773 | I218: PE26032601 | J218: Module Diode Failure | K218: Sadla | L218: Gujarat | M218: NS | N218: Cold Soldering | O218: 570 | P218: NSMI24050066988 | Q218: =MID(P218,5,2) | R218: =MID(P218,7,2) | S218: G2G | T218: P4 | U218: N JB Cold Soldering | V218: Soldering | W218: Repair | X218: 46146 | Y218: =X218-A218 | Z218: 46146
A219: 46107 | B219: 2026 | C219: Blupine | D219: Utility and C&I | F219: Closed | G219: Chandrashekar Patidar | H219: 7879764773 | I219: PE26032601 | J219: Module Diode Failure | K219: Sadla | L219: Gujarat | M219: NS | N219: Cold Soldering | O219: 570 | P219: NSMI24050055968 | Q219: =MID(P219,5,2) | R219: =MID(P219,7,2) | S219: G2G | T219: P4 | U219: N JB Cold Soldering | V219: Soldering | W219: Repair | X219: 46146 | Y219: =X219-A219 | Z219: 46146
A220: 46107 | B220: 2026 | C220: Blupine | D220: Utility and C&I | F220: Closed | G220: Chandrashekar Patidar | H220: 7879764773 | I220: PE26032601 | J220: Module Diode Failure | K220: Sadla | L220: Gujarat | M220: PS | N220: Cold Soldering | O220: 570 | P220: NSMI24050067490 | Q220: =MID(P220,5,2) | R220: =MID(P220,7,2) | S220: G2G | T220: P4 | U220: P JB Cold Soldering | V220: Soldering | W220: Repair | X220: 46146 | Y220: =X220-A220 | Z220: 46146
A221: 46107 | B221: 2026 | C221: Blupine | D221: Utility and C&I | F221: Closed | G221: Chandrashekar Patidar | H221: 7879764773 | I221: PE26032601 | J221: Module Diode Failure | K221: Sadla | L221: Gujarat | M221: NR | N221: JB Issue | O221: 570 | P221: NSMI24060116495 | Q221: =MID(P221,5,2) | R221: =MID(P221,7,2) | S221: G2G | T221: P4 | U221: N JB Issue | V221: JB Changed | W221: Repair | X221: 46146 | Y221: =X221-A221 | Z221: 46146
A222: 46107 | B222: 2026 | C222: Blupine | D222: Utility and C&I | F222: Closed | G222: Chandrashekar Patidar | H222: 7879764773 | I222: PE26032601 | J222: Module Diode Failure | K222: Sadla | L222: Gujarat | M222: NS | N222: Cold Soldering | O222: 570 | P222: NSMI24060075015 | Q222: =MID(P222,5,2) | R222: =MID(P222,7,2) | S222: G2G | T222: P4 | U222: N JB Cold Soldering | V222: Soldering | W222: Repair | X222: 46146 | Y222: =X222-A222 | Z222: 46146
A223: 46107 | B223: 2026 | C223: Blupine | D223: Utility and C&I | F223: Closed | G223: Chandrashekar Patidar | H223: 7879764773 | I223: PE26032601 | J223: Module Diode Failure | K223: Sadla | L223: Gujarat | M223: NS | N223: Cold Soldering | O223: 570 | P223: NSMI24050067044 | Q223: =MID(P223,5,2) | R223: =MID(P223,7,2) | S223: G2G | T223: P4 | U223: N JB Cold Soldering | V223: Soldering | W223: Repair | X223: 46146 | Y223: =X223-A223 | Z223: 46146
A224: 46107 | B224: 2026 | C224: Blupine | D224: Utility and C&I | F224: Closed | G224: Chandrashekar Patidar | H224: 7879764773 | I224: PE26032601 | J224: Module Diode Failure | K224: Sadla | L224: Gujarat | M224: NS | N224: Cold Soldering | O224: 570 | P224: NSMI24050067187 | Q224: =MID(P224,5,2) | R224: =MID(P224,7,2) | S224: G2G | T224: P4 | U224: N JB Cold Soldering | V224: Soldering | W224: Repair | X224: 46146 | Y224: =X224-A224 | Z224: 46146
... A235: 46107 | B235: 2026 | C235: Blupine | D235: Utility and C&I | F235: Closed | G235: Chandrashekar Patidar | H235: 7879764773 | I235: PE26032601 | J235: Module Diode Failure | K235: Sadla | L235: Gujarat | M235: NS | N235: Cold Soldering | O235: 570 | P235: NSMI24050044536 | Q235: =MID(P235,5,2) | R235: =MID(P235,7,2) | S235: G2G | T235: P4 | U235: N JB Cold Soldering | V235: Soldering | W235: Repair | X235: 46146 | Y235: =X235-A235 | Z235: 46146
A236: 46139 | B236: 2026 | C236: TRUE SUN TRADING COMPANY | D236: Channel Sales | F236: Closed | G236: Joel Jacob | H236: 7902222180 | I236: PE27042603 | J236: Panel Blast | K236: CHANGANASSERRY | L236: Kerala | M236: No Visit | N236: Tab lead Burn | O236: 540 | P236: NSMP25080647747 | Q236: =MID(P236,5,2) | R236: =MID(P236,7,2) | S236: G2TB | T236: P2 | U236: Tab lead Burn | V236: CN | W236: Replacement | X236: 46146 | Y236: =X236-A236 | Z236: No Visit
A237: 46107 | B237: 2026 | C237: Solar Square | D237: OEM | F237: Closed | G237: Murali | H237: 9703345015 | I237: PE26032602 | J237: Multiple Defects Identified | K237: Hyderabad | L237: Telangana | M237: No Visit | N237: Improper Ribbon Soldering | O237: 540 | P237: NSMP25121224541 | Q237: =MID(P237,5,2) | R237: =MID(P237,7,2) | S237: G2TB | T237: P2 | U237: Improper Ribbon Soldering | V237: CN / Replacement | W237: Replacement | X237: 46146 | Y237: =X237-A237 | Z237: No Visit
A238: 46107 | B238: 2026 | C238: Solar Square | D238: OEM | F238: Closed | G238: Murali | H238: 9703345015 | I238: PE26032602 | J238: Multiple Defects Identified | K238: Hyderabad | L238: Telangana | M238: No Visit | N238: Forign Particle - Cell Piece | O238: 540 | P238: NSMP25121227616 | Q238: =MID(P238,5,2) | R238: =MID(P238,7,2) | S238: G2TB | T238: P2 | U238: Forign Particle - Cell Piece | V238: CN / Replacement | W238: Replacement | X238: 46146 | Y238: =X238-A238 | Z238: No Visit
A239: 46107 | B239: 2026 | C239: Solar Square | D239: OEM | F239: Closed | G239: Murali | H239: 9703345015 | I239: PE26032602 | J239: Multiple Defects Identified | K239: Hyderabad | L239: Telangana | M239: No Visit | N239: Cell Chip | O239: 540 | P239: NSMP26021318226 | Q239: =MID(P239,5,2) | R239: =MID(P239,7,2) | S239: G2TB | T239: P2 | U239: Cell Chip | V239: CN / Replacement | W239: Replacement | X239: 46146 | Y239: =X239-A239 | Z239: No Visit
A240: 46107 | B240: 2026 | C240: Solar Square | D240: OEM | F240: Closed | G240: Murali | H240: 9703345015 | I240: PE26032602 | J240: Multiple Defects Identified | K240: Hyderabad | L240: Telangana | M240: No Visit | N240: Cell Crack | O240: 540 | P240: NSMP26011281494 | Q240: =MID(P240,5,2) | R240: =MID(P240,7,2) | S240: G2TB | T240: P2 | U240: Cell Crack | V240: CN / Replacement | W240: Replacement | X240: 46146 | Y240: =X240-A240 | Z240: No Visit
A241: 46141 | B241: 2026 | C241: Solar Square | D241: OEM | F241: Closed | G241: Murali | H241: 9703345015 | I241: PE30042601 | J241: JB Melting | K241: Kanpur | L241: UP | M241: N JB Burn marks observed | N241: JB Issue | O241: 540 | P241: NSMP26011281961 | Q241: =MID(P241,5,2) | R241: =MID(P241,7,2) | S241: G2TB | T241: P2 | U241: N JB Issue | V241: JB Changed | W241: Repair | X241: 46147 | Y241: =X241-A241 | Z241: 46147
...

Sheet Monthly Report May-26 Cleaned
A1: Complaint Received Date | B1: Year | C1: Complaint Raised By | D1: Customer Type | E1: Project Name | F1: Current Status | G1: Claim Reported By | H1: Contact No. | I1: Contract / Complaint / Invoice No. | J1: Customer Reported Problem | K1: Venue / Location | L1: State | M1: Field Evaluation | N1: Our Evaluation | O1: PV Panels Wp | P1: Module Serial Number | Q1: Module Make Year | R1: Module Make Month | S1: Moduel Type | T1: Manufacturing Plant | U1: Remark | V1: Action Taken | W1: Resolution Type | X1: Date of Claim Settled | Y1: Claim Settlement Duration | Z1: Visit Date | AA1: Rework Srl No. | AB1: Work details | AF1: May Closed Flag
A2: 46140 | B2: 2026 | C2: Panasonic | D2: OEM | F2: Closed | G2: Chirag Tare | H2: 7719846027 | I2: PE28042604 | J2: Low VOC | K2: Mysore | L2: Karnataka | M2: JB Issue | N2: JB Issue | O2: 550 | P2: NSMP2304007550 | Q2: =MID(P2,5,2) | R2: =MID(P2,7,2) | S2: G2B | T2: P2 | U2: All JB Issue | V2: JB Changed | W2: Repair | X2: 46143 | Y2: =IF(X2="","",X2-A2) | Z2: 46143 | AF2: =IF(AND($F2="Closed",$X2>=DATE(2026,5,1),$X2<=DATE(2026,5,31)),"Closed in May","Other")
A3: 46133 | B3: 2026 | C3: Axitec Energy | D3: OEM | F3: Closed | G3: Dushyant | H3: 8826633540 | I3: PE21042602 | J3: Diode Failure | K3: Chinchwad | L3: Maharashtra | M3: Cold Soldering | N3: Cold Soldering | O3: 520 | P3: 26230431008130 | Q3: =MID(P3,3,2) | R3: =MID(P3,5,2) | S3: G2B | T3: P2 | U3: P JB Cold Soldering | V3: Soldering | W3: Repair | X3: 46143 | Y3: =IF(X3="","",X3-A3) | Z3: 46143 | AF3: =IF(AND($F3="Closed",$X3>=DATE(2026,5,1),$X3<=DATE(2026,5,31)),"Closed in May","Other")
A4: 46133 | B4: 2026 | C4: Axitec Energy | D4: OEM | F4: Closed | G4: Dushyant | H4: 8826633540 | I4: PE21042602 | J4: Diode Failure | K4: Chinchwad | L4: Maharashtra | M4: Cold Soldering | N4: Cold Soldering | O4: 520 | P4: 26230431008116 | Q4: =MID(P4,3,2) | R4: =MID(P4,5,2) | S4: G2B | T4: P2 | U4: P JB Cold Soldering | V4: Soldering | W4: Repair | X4: 46143 | Y4: =IF(X4="","",X4-A4) | Z4: 46143 | AF4: =IF(AND($F4="Closed",$X4>=DATE(2026,5,1),$X4<=DATE(2026,5,31)),"Closed in May","Other")
A5: 46106 | B5: 2026 | C5: First Energy | D5: Utility and C&I | F5: Closed | G5: Mr. Gaurav | H5: 9979185999 | I5: PE25032601 | J5: Module Defects | K5: Rajkot | L5: Gujarat | M5: hotspot found | N5: Hotspot | O5: 550 | P5: NSMP2409546021 | Q5: =MID(P5,5,2) | R5: =MID(P5,7,2) | S5: G2B | T5: P2 | U5: Multi Cell Hotspot | V5: Inspection | W5: Rejected | X5: =Z5 | Y5: =IF(X5="","",X5-A5) | Z5: 46143 | AF5: =IF(AND($F5="Closed",$X5>=DATE(2026,5,1),$X5<=DATE(2026,5,31)),"Closed in May","Other")
A6: 46106 | B6: 2026 | C6: First Energy | D6: Utility and C&I | F6: Closed | G6: Mr. Gaurav | H6: 9979185999 | I6: PE25032601 | J6: Module Defects | K6: Rajkot | L6: Gujarat | M6: hotspot found | N6: Hotspot | O6: 550 | P6: NSMP2212269256 | Q6: =MID(P6,5,2) | R6: =MID(P6,7,2) | S6: G2B | T6: P2 | U6: Multi Cell Hotspot | V6: Inspection | W6: Rejected | X6: =Z6 | Y6: =IF(X6="","",X6-A6) | Z6: 46143 | AF6: =IF(AND($F6="Closed",$X6>=DATE(2026,5,1),$X6<=DATE(2026,5,31)),"Closed in May","Other")
A7: 46106 | B7: 2026 | C7: First Energy | D7: Utility and C&I | F7: Closed | G7: Mr. Gaurav | H7: 9979185999 | I7: PE25032601 | J7: Module Defects | K7: Rajkot | L7: Gujarat | M7: hotspot found | N7: Hotspot | O7: 550 | P7: NSMP2212269311 | Q7: =MID(P7,5,2) | R7: =MID(P7,7,2) | S7: G2B | T7: P2 | U7: Multi Cell Hotspot | V7: Inspection | W7: Rejected | X7: =Z7 | Y7: =IF(X7="","",X7-A7) | Z7: 46143 | AF7: =IF(AND($F7="Closed",$X7>=DATE(2026,5,1),$X7<=DATE(2026,5,31)),"Closed in May","Other")
A8: 46106 | B8: 2026 | C8: First Energy | D8: Utility and C&I | F8: Closed | G8: Mr. Gaurav | H8: 9979185999 | I8: PE25032601 | J8: Module Defects | K8: Rajkot | L8: Gujarat | M8: hotspot found | N8: Hotspot | O8: 550 | P8: NSMP2212269144 | Q8: =MID(P8,5,2) | R8: =MID(P8,7,2) | S8: G2B | T8: P2 | U8: Single Cell Hotspot | V8: Inspection | W8: Rejected | X8: =Z8 | Y8: =IF(X8="","",X8-A8) | Z8: 46143 | AF8: =IF(AND($F8="Closed",$X8>=DATE(2026,5,1),$X8<=DATE(2026,5,31)),"Closed in May","Other")
A9: 46106 | B9: 2026 | C9: First Energy | D9: Utility and C&I | F9: Closed | G9: Mr. Gaurav | H9: 9979185999 | I9: PE25032601 | J9: Module Defects | K9: Rajkot | L9: Gujarat | M9: hotspot found | N9: Hotspot | O9: 550 | P9: NSMP2301302211 | Q9: =MID(P9,5,2) | R9: =MID(P9,7,2) | S9: G2B | T9: P2 | U9: Multi Cell Hotspot | V9: Inspection | W9: Rejected | X9: =Z9 | Y9: =IF(X9="","",X9-A9) | Z9: 46143 | AF9: =IF(AND($F9="Closed",$X9>=DATE(2026,5,1),$X9<=DATE(2026,5,31)),"Closed in May","Other")
A10: 46106 | B10: 2026 | C10: First Energy | D10: Utility and C&I | F10: Closed | G10: Mr. Gaurav | H10: 9979185999 | I10: PE25032601 | J10: Module Defects | K10: Rajkot | L10: Gujarat | M10: hotspot found | N10: Hotspot | O10: 550 | P10: NSMP2301328092 | Q10: =MID(P10,5,2) | R10: =MID(P10,7,2) | S10: G2B | T10: P2 | U10: Single Cell Hotspot | V10: Inspection | W10: Rejected | X10: =Z10 | Y10: =IF(X10="","",X10-A10) | Z10: 46143 | AF10: =IF(AND($F10="Closed",$X10>=DATE(2026,5,1),$X10<=DATE(2026,5,31)),"Closed in May","Other")
A11: 46106 | B11: 2026 | C11: First Energy | D11: Utility and C&I | F11: Closed | G11: Mr. Gaurav | H11: 9979185999 | I11: PE25032601 | J11: Module Defects | K11: Rajkot | L11: Gujarat | M11: hotspot found | N11: Hotspot | O11: 550 | P11: NSMP2212258292 | Q11: =MID(P11,5,2) | R11: =MID(P11,7,2) | S11: G2B | T11: P2 | U11: Multi Cell Hotspot | V11: Inspection | W11: Rejected | X11: =Z11 | Y11: =IF(X11="","",X11-A11) | Z11: 46143 | AF11: =IF(AND($F11="Closed",$X11>=DATE(2026,5,1),$X11<=DATE(2026,5,31)),"Closed in May","Other")
A12: 46106 | B12: 2026 | C12: First Energy | D12: Utility and C&I | F12: Closed | G12: Mr. Gaurav | H12: 9979185999 | I12: PE25032601 | J12: Module Defects | K12: Rajkot | L12: Gujarat | M12: hotspot found | N12: Hotspot | O12: 550 | P12: NSMP2212269072 | Q12: =MID(P12,5,2) | R12: =MID(P12,7,2) | S12: G2B | T12: P2 | U12: Multi Cell Hotspot | V12: Inspection | W12: Rejected | X12: =Z12 | Y12: =IF(X12="","",X12-A12) | Z12: 46143 | AF12: =IF(AND($F12="Closed",$X12>=DATE(2026,5,1),$X12<=DATE(2026,5,31)),"Closed in May","Other")
A13: 46106 | B13: 2026 | C13: First Energy | D13: Utility and C&I | F13: WIP | G13: Mr. Gaurav | H13: 9979185999 | I13: PE25032601 | J13: Module Defects | K13: Rajkot | L13: Gujarat | M13: Broken Module | N13: Hotspot | O13: 550 | P13: NSMP2212277874 | Q13: =MID(P13,5,2) | R13: =MID(P13,7,2) | S13: G2B | T13: P2 | U13: Multi Cell Hotspot | V13: Inspection | W13: WIP | Y13: =IF(X13="","",X13-A13) | Z13: 46143 | AF13: =IF(AND($F13="Closed",$X13>=DATE(2026,5,1),$X13<=DATE(2026,5,31)),"Closed in May","Other")
A14: 46106 | B14: 2026 | C14: First Energy | D14: Utility and C&I | F14: Closed | G14: PE02052602 | H14: 9979185999 | I14: PE25032601 | J14: Module Defects | K14: Rajkot | L14: Gujarat | M14: hotspot found | N14: Hotspot | O14: 550 | P14: NSMP2212277882 | Q14: =MID(P14,5,2) | R14: =MID(P14,7,2) | S14: G2B | T14: P2 | U14: Multi Cell Hotspot | V14: Inspection | W14: Rejected | X14: =Z14 | Y14: =IF(X14="","",X14-A14) | Z14: 46143 | AF14: =IF(AND($F14="Closed",$X14>=DATE(2026,5,1),$X14<=DATE(2026,5,31)),"Closed in May","Other")
A15: 46106 | B15: 2026 | C15: First Energy | D15: Utility and C&I | F15: Closed | G15: Mr. Gaurav | H15: 9979185999 | I15: PE25032601 | J15: Module Defects | K15: Rajkot | L15: Gujarat | M15: hotspot found | N15: Hotspot | O15: 550 | P15: NSMP2212270587 | Q15: =MID(P15,5,2) | R15: =MID(P15,7,2) | S15: G2B | T15: P2 | U15: Multi Cell Hotspot | V15: Inspection | W15: Rejected | X15: =Z15 | Y15: =IF(X15="","",X15-A15) | Z15: 46143 | AF15: =IF(AND($F15="Closed",$X15>=DATE(2026,5,1),$X15<=DATE(2026,5,31)),"Closed in May","Other")
A16: 46106 | B16: 2026 | C16: First Energy | D16: Utility and C&I | F16: Closed | G16: Mr. Gaurav | H16: 9979185999 | I16: PE25032601 | J16: Module Defects | K16: Rajkot | L16: Gujarat | M16: hotspot found | N16: Hotspot | O16: 550 | P16: NSMP2212277215 | Q16: =MID(P16,5,2) | R16: =MID(P16,7,2) | S16: G2B | T16: P2 | U16: Multi Cell Hotspot | V16: Inspection | W16: Rejected | X16: =Z16 | Y16: =IF(X16="","",X16-A16) | Z16: 46143 | AF16: =IF(AND($F16="Closed",$X16>=DATE(2026,5,1),$X16<=DATE(2026,5,31)),"Closed in May","Other")
A17: 46106 | B17: 2026 | C17: First Energy | D17: Utility and C&I | F17: Closed | G17: Mr. Gaurav | H17: 9979185999 | I17: PE25032601 | J17: Module Defects | K17: Rajkot | L17: Gujarat | M17: hotspot found | N17: Hotspot | O17: 550 | P17: NSMP2212268823 | Q17: =MID(P17,5,2) | R17: =MID(P17,7,2) | S17: G2B | T17: P2 | U17: Multi Cell Hotspot | V17: Inspection | W17: Rejected | X17: =Z17 | Y17: =IF(X17="","",X17-A17) | Z17: 46143 | AF17: =IF(AND($F17="Closed",$X17>=DATE(2026,5,1),$X17<=DATE(2026,5,31)),"Closed in May","Other")
A18: 46106 | B18: 2026 | C18: First Energy | D18: Utility and C&I | F18: Closed | G18: Mr. Gaurav | H18: 9979185999 | I18: PE25032601 | J18: Module Defects | K18: Rajkot | L18: Gujarat | M18: hotspot found | N18: Hotspot | O18: 550 | P18: NSMP2301334793 | Q18: =MID(P18,5,2) | R18: =MID(P18,7,2) | S18: G2B | T18: P2 | U18: Multi Cell Hotspot | V18: Inspection | W18: Rejected | X18: =Z18 | Y18: =IF(X18="","",X18-A18) | Z18: 46143 | AF18: =IF(AND($F18="Closed",$X18>=DATE(2026,5,1),$X18<=DATE(2026,5,31)),"Closed in May","Other")
A19: 46106 | B19: 2026 | C19: First Energy | D19: Utility and C&I | F19: Closed | G19: Mr. Gaurav | H19: 9979185999 | I19: PE25032601 | J19: Module Defects | K19: Rajkot | L19: Gujarat | M19: hotspot found | N19: Hotspot | O19: 550 | P19: NSMP2301304875 | Q19: =MID(P19,5,2) | R19: =MID(P19,7,2) | S19: G2B | T19: P2 | U19: Single Cell Hotspot | V19: Inspection | W19: Rejected | X19: =Z19 | Y19: =IF(X19="","",X19-A19) | Z19: 46143 | AF19: =IF(AND($F19="Closed",$X19>=DATE(2026,5,1),$X19<=DATE(2026,5,31)),"Closed in May","Other")
A20: 46106 | B20: 2026 | C20: First Energy | D20: Utility and C&I | F20: Closed | G20: Mr. Gaurav | H20: 9979185999 | I20: PE25032601 | J20: Module Defects | K20: Rajkot | L20: Gujarat | M20: hotspot found | N20: Hotspot | O20: 550 | P20: NSMP2212279131 | Q20: =MID(P20,5,2) | R20: =MID(P20,7,2) | S20: G2B | T20: P2 | U20: Multi Cell Hotspot | V20: Inspection | W20: Rejected | X20: =Z20 | Y20: =IF(X20="","",X20-A20) | Z20: 46143 | AF20: =IF(AND($F20="Closed",$X20>=DATE(2026,5,1),$X20<=DATE(2026,5,31)),"Closed in May","Other")
A21: 46106 | B21: 2026 | C21: First Energy | D21: Utility and C&I | F21: Closed | G21: Mr. Gaurav | H21: 9979185999 | I21: PE25032601 | J21: Module Defects | K21: Rajkot | L21: Gujarat | M21: hotspot found | N21: Hotspot | O21: 550 | P21: NSMP2212282140 | Q21: =MID(P21,5,2) | R21: =MID(P21,7,2) | S21: G2B | T21: P2 | U21: Multi Cell Hotspot | V21: Inspection | W21: Rejected | X21: =Z21 | Y21: =IF(X21="","",X21-A21) | Z21: 46143 | AF21: =IF(AND($F21="Closed",$X21>=DATE(2026,5,1),$X21<=DATE(2026,5,31)),"Closed in May","Other")
A22: 46106 | B22: 2026 | C22: First Energy | D22: Utility and C&I | F22: Closed | G22: Mr. Gaurav | H22: 9979185999 | I22: PE25032601 | J22: Module Defects | K22: Rajkot | L22: Gujarat | M22: hotspot found | N22: Hotspot | O22: 550 | P22: NSMP2212268033 | Q22: =MID(P22,5,2) | R22: =MID(P22,7,2) | S22: G2B | T22: P2 | U22: Single Cell Hotspot | V22: Inspection | W22: Rejected | X22: =Z22 | Y22: =IF(X22="","",X22-A22) | Z22: 46143 | AF22: =IF(AND($F22="Closed",$X22>=DATE(2026,5,1),$X22<=DATE(2026,5,31)),"Closed in May","Other")
A23: 46106 | B23: 2026 | C23: First Energy | D23: Utility and C&I | F23: Closed | G23: Mr. Gaurav | H23: 9979185999 | I23: PE25032601 | J23: Module Defects | K23: Rajkot | L23: Gujarat | M23: hotspot found | N23: Hotspot | O23: 550 | P23: NSMP2212268494 | Q23: =MID(P23,5,2) | R23: =MID(P23,7,2) | S23: G2B | T23: P2 | U23: Single Cell Hotspot | V23: Inspection | W23: Rejected | X23: =Z23 | Y23: =IF(X23="","",X23-A23) | Z23: 46143 | AF23: =IF(AND($F23="Closed",$X23>=DATE(2026,5,1),$X23<=DATE(2026,5,31)),"Closed in May","Other")
A24: 46106 | B24: 2026 | C24: First Energy | D24: Utility and C&I | F24: Closed | G24: Mr. Gaurav | H24: 9979185999 | I24: PE25032601 | J24: Module Defects | K24: Rajkot | L24: Gujarat | M24: hotspot found | N24: Hotspot | O24: 550 | P24: NSMP2212268542 | Q24: =MID(P24,5,2) | R24: =MID(P24,7,2) | S24: G2B | T24: P2 | U24: Single Cell Hotspot | V24: Inspection | W24: Rejected | X24: =Z24 | Y24: =IF(X24="","",X24-A24) | Z24: 46143 | AF24: =IF(AND($F24="Closed",$X24>=DATE(2026,5,1),$X24<=DATE(2026,5,31)),"Closed in May","Other")
A25: 46106 | B25: 2026 | C25: First Energy | D25: Utility and C&I | F25: Closed | G25: Mr. Gaurav | H25: 9979185999 | I25: PE25032601 | J25: Module Defects | K25: Rajkot | L25: Gujarat | M25: hotspot found | N25: Hotspot | O25: 550 | P25: NSMP2212268029 | Q25: =MID(P25,5,2) | R25: =MID(P25,7,2) | S25: G2B | T25: P2 | U25: Single Cell Hotspot | V25: Inspection | W25: Rejected | X25: =Z25 | Y25: =IF(X25="","",X25-A25) | Z25: 46143 | AF25: =IF(AND($F25="Closed",$X25>=DATE(2026,5,1),$X25<=DATE(2026,5,31)),"Closed in May","Other")
... A30: 46106 | B30: 2026 | C30: First Energy | D30: Utility and C&I | F30: Closed | G30: Mr. Gaurav | H30: 9979185999 | I30: PE25032601 | J30: Module Defects | K30: Rajkot | L30: Gujarat | M30: hotspot found | N30: Hotspot | O30: 550 | P30: NSMP2212268150 | Q30: =MID(P30,5,2) | R30: =MID(P30,7,2) | S30: G2B | T30: P2 | U30: Single Cell Hotspot | V30: Inspection | W30: Rejected | X30: =Z30 | Y30: =IF(X30="","",X30-A30) | Z30: 46144 | AF30: =IF(AND($F30="Closed",$X30>=DATE(2026,5,1),$X30<=DATE(2026,5,31)),"Closed in May","Other")
A31: 46106 | B31: 2026 | C31: First Energy | D31: Utility and C&I | F31: Closed | G31: Mr. Gaurav | H31: 9979185999 | I31: PE25032601 | J31: Module Defects | K31: Rajkot | L31: Gujarat | M31: hotspot found | N31: Hotspot | O31: 550 | P31: NSMP2212268242 | Q31: =MID(P31,5,2) | R31: =MID(P31,7,2) | S31: G2B | T31: P2 | U31: Single Cell Hotspot | V31: Inspection | W31: Rejected | X31: =Z31 | Y31: =IF(X31="","",X31-A31) | Z31: 46144 | AD31: =COUNTIF(W:W,"WIP") | AF31: =IF(AND($F31="Closed",$X31>=DATE(2026,5,1),$X31<=DATE(2026,5,31)),"Closed in May","Other")
A32: 46106 | B32: 2026 | C32: First Energy | D32: Utility and C&I | F32: Closed | G32: Mr. Gaurav | H32: 9979185999 | I32: PE25032601 | J32: Module Defects | K32: Rajkot | L32: Gujarat | M32: hotspot found | N32: Hotspot | O32: 550 | P32: NSMP2212268992 | Q32: =MID(P32,5,2) | R32: =MID(P32,7,2) | S32: G2B | T32: P2 | U32: Single Cell Hotspot | V32: Inspection | W32: Rejected | X32: =Z32 | Y32: =IF(X32="","",X32-A32) | Z32: 46144 | AF32: =IF(AND($F32="Closed",$X32>=DATE(2026,5,1),$X32<=DATE(2026,5,31)),"Closed in May","Other")
A33: 46106 | B33: 2026 | C33: First Energy | D33: Utility and C&I | F33: Closed | G33: Mr. Gaurav | H33: 9979185999 | I33: PE25032601 | J33: Module Defects | K33: Rajkot | L33: Gujarat | M33: hotspot found | N33: Hotspot | O33: 550 | P33: NSMP2212276699 | Q33: =MID(P33,5,2) | R33: =MID(P33,7,2) | S33: G2B | T33: P2 | U33: Single Cell Hotspot | V33: Inspection | W33: Rejected | X33: =Z33 | Y33: =IF(X33="","",X33-A33) | Z33: 46144 | AF33: =IF(AND($F33="Closed",$X33>=DATE(2026,5,1),$X33<=DATE(2026,5,31)),"Closed in May","Other")
A34: 46106 | B34: 2026 | C34: First Energy | D34: Utility and C&I | F34: Closed | G34: Mr. Gaurav | H34: 9979185999 | I34: PE25032601 | J34: Module Defects | K34: Rajkot | L34: Gujarat | M34: hotspot found | N34: Hotspot | O34: 550 | P34: NSMP2301333643 | Q34: =MID(P34,5,2) | R34: =MID(P34,7,2) | S34: G2B | T34: P2 | U34: Multi Cell Hotspot | V34: Inspection | W34: Rejected | X34: =Z34 | Y34: =IF(X34="","",X34-A34) | Z34: 46144 | AF34: =IF(AND($F34="Closed",$X34>=DATE(2026,5,1),$X34<=DATE(2026,5,31)),"Closed in May","Other")
A35: 46106 | B35: 2026 | C35: First Energy | D35: Utility and C&I | F35: Closed | G35: Mr. Gaurav | H35: 9979185999 | I35: PE25032601 | J35: Module Defects | K35: Rajkot | L35: Gujarat | M35: hotspot found | N35: Hotspot | O35: 550 | P35: NSMP2212284630 | Q35: =MID(P35,5,2) | R35: =MID(P35,7,2) | S35: G2B | T35: P2 | U35: Multi Cell Hotspot | V35: Inspection | W35: Rejected | X35: =Z35 | Y35: =IF(X35="","",X35-A35) | Z35: 46144 | AF35: =IF(AND($F35="Closed",$X35>=DATE(2026,5,1),$X35<=DATE(2026,5,31)),"Closed in May","Other")
A36: 46106 | B36: 2026 | C36: First Energy | D36: Utility and C&I | F36: WIP | G36: Mr. Gaurav | H36: 9979185999 | I36: PE25032601 | J36: Module Defects | K36: Rajkot | L36: Gujarat | M36: Broken Module | N36: Hotspot | O36: 550 | P36: NSMP2212278079 | Q36: =MID(P36,5,2) | R36: =MID(P36,7,2) | S36: G2B | T36: P2 | U36: Multi Cell Hotspot | V36: Inspection | W36: WIP | Y36: =IF(X36="","",X36-A36) | Z36: 46144 | AF36: =IF(AND($F36="Closed",$X36>=DATE(2026,5,1),$X36<=DATE(2026,5,31)),"Closed in May","Other")
A37: 46106 | B37: 2026 | C37: First Energy | D37: Utility and C&I | F37: Closed | G37: Mr. Gaurav | H37: 9979185999 | I37: PE25032601 | J37: Module Defects | K37: Rajkot | L37: Gujarat | M37: hotspot found | N37: Hotspot | O37: 550 | P37: NSMP2301348215 | Q37: =MID(P37,5,2) | R37: =MID(P37,7,2) | S37: G2B | T37: P2 | U37: Single Cell Hotspot | V37: Inspection | W37: Rejected | X37: =Z37 | Y37: =IF(X37="","",X37-A37) | Z37: 46144 | AF37: =IF(AND($F37="Closed",$X37>=DATE(2026,5,1),$X37<=DATE(2026,5,31)),"Closed in May","Other")
A38: 46106 | B38: 2026 | C38: First Energy | D38: Utility and C&I | F38: Closed | G38: Mr. Gaurav | H38: 9979185999 | I38: PE25032601 | J38: Module Defects | K38: Rajkot | L38: Gujarat | M38: hotspot found | N38: Hotspot | O38: 550 | P38: NSMP2212273080 | Q38: =MID(P38,5,2) | R38: =MID(P38,7,2) | S38: G2B | T38: P2 | U38: Single Cell Hotspot | V38: Inspection | W38: Rejected | X38: =Z38 | Y38: =IF(X38="","",X38-A38) | Z38: 46144 | AF38: =IF(AND($F38="Closed",$X38>=DATE(2026,5,1),$X38<=DATE(2026,5,31)),"Closed in May","Other")
A39: 46106 | B39: 2026 | C39: First Energy | D39: Utility and C&I | F39: Closed | G39: Mr. Gaurav | H39: 9979185999 | I39: PE25032601 | J39: Module Defects | K39: Rajkot | L39: Gujarat | M39: hotspot found | N39: Hotspot | O39: 550 | P39: NSMP2301313309 | Q39: =MID(P39,5,2) | R39: =MID(P39,7,2) | S39: G2B | T39: P2 | U39: Multi Cell Hotspot | V39: Inspection | W39: Rejected | X39: =Z39 | Y39: =IF(X39="","",X39-A39) | Z39: 46144 | AF39: =IF(AND($F39="Closed",$X39>=DATE(2026,5,1),$X39<=DATE(2026,5,31)),"Closed in May","Other")
A40: 46106 | B40: 2026 | C40: First Energy | D40: Utility and C&I | F40: Closed | G40: Mr. Gaurav | H40: 9979185999 | I40: PE25032601 | J40: Module Defects | K40: Rajkot | L40: Gujarat | M40: hotspot found | N40: Hotspot | O40: 550 | P40: NSMP2212281907 | Q40: =MID(P40,5,2) | R40: =MID(P40,7,2) | S40: G2B | T40: P2 | U40: Multi Cell Hotspot | V40: Inspection | W40: Rejected | X40: =Z40 | Y40: =IF(X40="","",X40-A40) | Z40: 46144 | AF40: =IF(AND($F40="Closed",$X40>=DATE(2026,5,1),$X40<=DATE(2026,5,31)),"Closed in May","Other")
A41: 46106 | B41: 2026 | C41: First Energy | D41: Utility and C&I | F41: Closed | G41: Mr. Gaurav | H41: 9979185999 | I41: PE25032601 | J41: Module Defects | K41: Rajkot | L41: Gujarat | M41: hotspot found | N41: Hotspot | O41: 550 | P41: NSMP2212280150 | Q41: =MID(P41,5,2) | R41: =MID(P41,7,2) | S41: G2B | T41: P2 | U41: Multi Cell Hotspot | V41: Inspection | W41: Rejected | X41: =Z41 | Y41: =IF(X41="","",X41-A41) | Z41: 46144 | AF41: =IF(AND($F41="Closed",$X41>=DATE(2026,5,1),$X41<=DATE(2026,5,31)),"Closed in May","Other")
A42: 46106 | B42: 2026 | C42: First Energy | D42: Utility and C&I | F42: Closed | G42: Mr. Gaurav | H42: 9979185999 | I42: PE25032601 | J42: Module Defects | K42: Rajkot | L42: Gujarat | M42: hotspot found | N42: Hotspot | O42: 550 | P42: NSMP2212275577 | Q42: =MID(P42,5,2) | R42: =MID(P42,7,2) | S42: G2B | T42: P2 | U42: Multi Cell Hotspot | V42: Inspection | W42: Rejected | X42: =Z42 | Y42: =IF(X42="","",X42-A42) | Z42: 46144 | AF42: =IF(AND($F42="Closed",$X42>=DATE(2026,5,1),$X42<=DATE(2026,5,31)),"Closed in May","Other")
A43: 46106 | B43: 2026 | C43: First Energy | D43: Utility and C&I | F43: Closed | G43: Mr. Gaurav | H43: 9979185999 | I43: PE25032601 | J43: Module Defects | K43: Rajkot | L43: Gujarat | M43: hotspot found | N43: Hotspot | O43: 550 | P43: NSMP2212297259 | Q43: =MID(P43,5,2) | R43: =MID(P43,7,2) | S43: G2B | T43: P2 | U43: Multi Cell Hotspot | V43: Inspection | W43: Rejected | X43: =Z43 | Y43: =IF(X43="","",X43-A43) | Z43: 46144 | AF43: =IF(AND($F43="Closed",$X43>=DATE(2026,5,1),$X43<=DATE(2026,5,31)),"Closed in May","Other")
A44: 46106 | B44: 2026 | C44: First Energy | D44: Utility and C&I | F44: Closed | G44: Mr. Gaurav | H44: 9979185999 | I44: PE25032601 | J44: Module Defects | K44: Rajkot | L44: Gujarat | M44: hotspot found | N44: Hotspot | O44: 550 | P44: NSMP2212283814 | Q44: =MID(P44,5,2) | R44: =MID(P44,7,2) | S44: G2B | T44: P2 | U44: Single Cell Hotspot | V44: Inspection | W44: Rejected | X44: =Z44 | Y44: =IF(X44="","",X44-A44) | Z44: 46144 | AF44: =IF(AND($F44="Closed",$X44>=DATE(2026,5,1),$X44<=DATE(2026,5,31)),"Closed in May","Other")
A45: 46106 | B45: 2026 | C45: First Energy | D45: Utility and C&I | F45: Closed | G45: Mr. Gaurav | H45: 9979185999 | I45: PE25032601 | J45: Module Defects | K45: Rajkot | L45: Gujarat | M45: hotspot found | N45: Hotspot | O45: 550 | P45: NSMP2212283822 | Q45: =MID(P45,5,2) | R45: =MID(P45,7,2) | S45: G2B | T45: P2 | U45: Single Cell Hotspot | V45: Inspection | W45: Rejected | X45: =Z45 | Y45: =IF(X45="","",X45-A45) | Z45: 46144 | AF45: =IF(AND($F45="Closed",$X45>=DATE(2026,5,1),$X45<=DATE(2026,5,31)),"Closed in May","Other")
A46: 46106 | B46: 2026 | C46: First Energy | D46: Utility and C&I | F46: Closed | G46: Mr. Gaurav | H46: 9979185999 | I46: PE25032601 | J46: Module Defects | K46: Rajkot | L46: Gujarat | M46: hotspot found | N46: Hotspot | O46: 550 | P46: NSMP2212268653 | Q46: =MID(P46,5,2) | R46: =MID(P46,7,2) | S46: G2B | T46: P2 | U46: Multi Cell Hotspot | V46: Inspection | W46: Rejected | X46: =Z46 | Y46: =IF(X46="","",X46-A46) | Z46: 46144 | AF46: =IF(AND($F46="Closed",$X46>=DATE(2026,5,1),$X46<=DATE(2026,5,31)),"Closed in May","Other")
A47: 46106 | B47: 2026 | C47: First Energy | D47: Utility and C&I | F47: Closed | G47: Mr. Gaurav | H47: 9979185999 | I47: PE25032601 | J47: Module Defects | K47: Rajkot | L47: Gujarat | M47: hotspot found | N47: Hotspot | O47: 550 | P47: NSMP2212283892 | Q47: =MID(P47,5,2) | R47: =MID(P47,7,2) | S47: G2B | T47: P2 | U47: Single Cell Hotspot | V47: Inspection | W47: Rejected | X47: =Z47 | Y47: =IF(X47="","",X47-A47) | Z47: 46144 | AF47: =IF(AND($F47="Closed",$X47>=DATE(2026,5,1),$X47<=DATE(2026,5,31)),"Closed in May","Other")
A48: 46106 | B48: 2026 | C48: First Energy | D48: Utility and C&I | F48: Closed | G48: Mr. Gaurav | H48: 9979185999 | I48: PE25032601 | J48: Module Defects | K48: Rajkot | L48: Gujarat | M48: hotspot found | N48: Hotspot | O48: 550 | P48: NSMP2212283852 | Q48: =MID(P48,5,2) | R48: =MID(P48,7,2) | S48: G2B | T48: P2 | U48: Single Cell Hotspot | V48: Inspection | W48: Rejected | X48: =Z48 | Y48: =IF(X48="","",X48-A48) | Z48: 46144 | AF48: =IF(AND($F48="Closed",$X48>=DATE(2026,5,1),$X48<=DATE(2026,5,31)),"Closed in May","Other")
A49: 46107 | B49: 2026 | C49: Blupine Energy | D49: Utility and C&I | F49: Closed | G49: Chandrashekar Patidar | H49: 7879764773 | I49: PE26032601 | J49: Module Diode Failure | K49: Sadla | L49: Gujarat | M49: PS | N49: Cold Soldering | O49: 570 | P49: NSMI24050051443 | Q49: =MID(P49,5,2) | R49: =MID(P49,7,2) | S49: G2G | T49: P4 | U49: P JB Cold Soldering | V49: Soldering | W49: Repair | X49: 46144 | Y49: =IF(X49="","",X49-A49) | Z49: 46144 | AF49: =IF(AND($F49="Closed",$X49>=DATE(2026,5,1),$X49<=DATE(2026,5,31)),"Closed in May","Other")
A50: 46107 | B50: 2026 | C50: Blupine Energy | D50: Utility and C&I | F50: Closed | G50: Chandrashekar Patidar | H50: 7879764773 | I50: PE26032601 | J50: Module Diode Failure | K50: Sadla | L50: Gujarat | M50: NS | N50: Cold Soldering | O50: 570 | P50: NSMI24050044810 | Q50: =MID(P50,5,2) | R50: =MID(P50,7,2) | S50: G2G | T50: P4 | U50: N JB Cold Soldering | V50: Soldering | W50: Repair | X50: 46144 | Y50: =IF(X50="","",X50-A50) | Z50: 46144 | AF50: =IF(AND($F50="Closed",$X50>=DATE(2026,5,1),$X50<=DATE(2026,5,31)),"Closed in May","Other")
A51: 46107 | B51: 2026 | C51: Blupine Energy | D51: Utility and C&I | F51: Closed | G51: Chandrashekar Patidar | H51: 7879764773 | I51: PE26032601 | J51: Module Diode Failure | K51: Sadla | L51: Gujarat | M51: NS | N51: Cold Soldering | O51: 570 | P51: NSMI24050047018 | Q51: =MID(P51,5,2) | R51: =MID(P51,7,2) | S51: G2G | T51: P4 | U51: N JB Cold Soldering | V51: Soldering | W51: Repair | X51: 46144 | Y51: =IF(X51="","",X51-A51) | Z51: 46144 | AF51: =IF(AND($F51="Closed",$X51>=DATE(2026,5,1),$X51<=DATE(2026,5,31)),"Closed in May","Other")
A52: 46107 | B52: 2026 | C52: Blupine Energy | D52: Utility and C&I | F52: Closed | G52: Chandrashekar Patidar | H52: 7879764773 | I52: PE26032601 | J52: Module Diode Failure | K52: Sadla | L52: Gujarat | M52: PR | N52: JB Issue | O52: 570 | P52: NSMI24060074092 | Q52: =MID(P52,5,2) | R52: =MID(P52,7,2) | S52: G2G | T52: P4 | U52: P JB Issue | V52: JB Changed | W52: Repair | X52: 46144 | Y52: =IF(X52="","",X52-A52) | Z52: 46144 | AF52: =IF(AND($F52="Closed",$X52>=DATE(2026,5,1),$X52<=DATE(2026,5,31)),"Closed in May","Other")
A53: 46107 | B53: 2026 | C53: Blupine Energy | D53: Utility and C&I | F53: Closed | G53: Chandrashekar Patidar | H53: 7879764773 | I53: PE26032601 | J53: Module Diode Failure | K53: Sadla | L53: Gujarat | M53: NR | N53: JB Issue | O53: 570 | P53: NSMI24050045987 | Q53: =MID(P53,5,2) | R53: =MID(P53,7,2) | S53: G2G | T53: P4 | U53: N JB Issue | V53: JB Changed | W53: Repair | X53: 46144 | Y53: =IF(X53="","",X53-A53) | Z53: 46144 | AF53: =IF(AND($F53="Closed",$X53>=DATE(2026,5,1),$X53<=DATE(2026,5,31)),"Closed in May","Other")
A54: 46107 | B54: 2026 | C54: Blupine Energy | D54: Utility and C&I | F54: Closed | G54: Chandrashekar Patidar | H54: 7879764773 | I54: PE26032601 | J54: Module Diode Failure | K54: Sadla | L54: Gujarat | M54: PS | N54: Cold Soldering | O54: 570 | P54: NSMI24050049041 | Q54: =MID(P54,5,2) | R54: =MID(P54,7,2) | S54: G2G | T54: P4 | U54: P JB Cold Soldering | V54: Soldering | W54: Repair | X54: 46144 | Y54: =IF(X54="","",X54-A54) | Z54: 46144 | AF54: =IF(AND($F54="Closed",$X54>=DATE(2026,5,1),$X54<=DATE(2026,5,31)),"Closed in May","Other")
A55: 46107 | B55: 2026 | C55: Blupine Energy | D55: Utility and C&I | F55: Closed | G55: Chandrashekar Patidar | H55: 7879764773 | I55: PE26032601 | J55: Module Diode Failure | K55: Sadla | L55: Gujarat | M55: NS | N55: Cold Soldering | O55: 570 | P55: NSMI24050045772 | Q55: =MID(P55,5,2) | R55: =MID(P55,7,2) | S55: G2G | T55: P4 | U55: N JB Cold Soldering | V55: Soldering | W55: Repair | X55: 46144 | Y55: =IF(X55="","",X55-A55) | Z55: 46144 | AF55: =IF(AND($F55="Closed",$X55>=DATE(2026,5,1),$X55<=DATE(2026,5,31)),"Closed in May","Other")
A56: 46107 | B56: 2026 | C56: Blupine Energy | D56: Utility and C&I | F56: Closed | G56: Chandrashekar Patidar | H56: 7879764773 | I56: PE26032601 | J56: Module Diode Failure | K56: Sadla | L56: Gujarat | M56: NS | N56: Cold Soldering | O56: 570 | P56: NSMI24050045804 | Q56: =MID(P56,5,2) | R56: =MID(P56,7,2) | S56: G2G | T56: P4 | U56: N JB Cold Soldering | V56: Soldering | W56: Repair | X56: 46144 | Y56: =IF(X56="","",X56-A56) | Z56: 46144 | AF56: =IF(AND($F56="Closed",$X56>=DATE(2026,5,1),$X56<=DATE(2026,5,31)),"Closed in May","Other")
A57: 46107 | B57: 2026 | C57: Blupine Energy | D57: Utility and C&I | F57: Closed | G57: Chandrashekar Patidar | H57: 7879764773 | I57: PE26032601 | J57: Module Diode Failure | K57: Sadla | L57: Gujarat | M57: NS | N57: Cold Soldering | O57: 570 | P57: NSMI24050045790 | Q57: =MID(P57,5,2) | R57: =MID(P57,7,2) | S57: G2G | T57: P4 | U57: N JB Cold Soldering | V57: Soldering | W57: Repair | X57: 46144 | Y57: =IF(X57="","",X57-A57) | Z57: 46144 | AF57: =IF(AND($F57="Closed",$X57>=DATE(2026,5,1),$X57<=DATE(2026,5,31)),"Closed in May","Other")
A58: 46107 | B58: 2026 | C58: Blupine Energy | D58: Utility and C&I | F58: Closed | G58: Chandrashekar Patidar | H58: 7879764773 | I58: PE26032601 | J58: Module Diode Failure | K58: Sadla | L58: Gujarat | M58: PNS | N58: Cold Soldering | O58: 570 | P58: NSMI24080334590 | Q58: =MID(P58,5,2) | R58: =MID(P58,7,2) | S58: G2G | T58: P4 | U58: P & N JB Cold Soldering | V58: Soldering | W58: Repair | X58: 46144 | Y58: =IF(X58="","",X58-A58) | Z58: 46144 | AF58: =IF(AND($F58="Closed",$X58>=DATE(2026,5,1),$X58<=DATE(2026,5,31)),"Closed in May","Other")
A59: 46107 | B59: 2026 | C59: Blupine Energy | D59: Utility and C&I | F59: Closed | G59: Chandrashekar Patidar | H59: 7879764773 | I59: PE26032601 | J59: Module Diode Failure | K59: Sadla | L59: Gujarat | M59: NS | N59: Cold Soldering | O59: 570 | P59: NSMI24050045988 | Q59: =MID(P59,5,2) | R59: =MID(P59,7,2) | S59: G2G | T59: P4 | U59: N JB Cold Soldering | V59: Soldering | W59: Repair | X59: 46144 | Y59: =IF(X59="","",X59-A59) | Z59: 46144 | AF59: =IF(AND($F59="Closed",$X59>=DATE(2026,5,1),$X59<=DATE(2026,5,31)),"Closed in May","Other")
A60: 46107 | B60: 2026 | C60: Blupine Energy | D60: Utility and C&I | F60: Closed | G60: Chandrashekar Patidar | H60: 7879764773 | I60: PE26032601 | J60: Module Diode Failure | K60: Sadla | L60: Gujarat | M60: NS | N60: Cold Soldering | O60: 570 | P60: NSMI24050045952 | Q60: =MID(P60,5,2) | R60: =MID(P60,7,2) | S60: G2G | T60: P4 | U60: N JB Cold Soldering | V60: Soldering | W60: Repair | X60: 46144 | Y60: =IF(X60="","",X60-A60) | Z60: 46144 | AF60: =IF(AND($F60="Closed",$X60>=DATE(2026,5,1),$X60<=DATE(2026,5,31)),"Closed in May","Other")
... A100: 46107 | B100: 2026 | C100: Blupine Energy | D100: Utility and C&I | F100: Closed | G100: Chandrashekar Patidar | H100: 7879764773 | I100: PE26032601 | J100: Module Diode Failure | K100: Sadla | L100: Gujarat | M100: PS | N100: Cold Soldering | O100: 570 | P100: NSMI24060079795 | Q100: =MID(P100,5,2) | R100: =MID(P100,7,2) | S100: G2G | T100: P4 | U100: P JB Cold Soldering | V100: Soldering | W100: Repair | X100: 46144 | Y100: =IF(X100="","",X100-A100) | Z100: 46144 | AF100: =IF(AND($F100="Closed",$X100>=DATE(2026,5,1),$X100<=DATE(2026,5,31)),"Closed in May","Other")
A101: 46118 | B101: 2026 | C101: Panasonic | D101: OEM | F101: Closed | G101: Chirag Tare | H101: 7719846027 | I101: PE06042602 | J101: Low VOC | K101: Dhule | L101: Maharashtra | M101: Backsheet Scratches | N101: Backsheet Scratches | O101: 330 | P101: NSM210403505 | Q101: =MID(P101,4,2) | R101: =MID(P101,6,2) | S101: G2B | T101: P1 | U101: Backsheet Scratches | V101: Rejected | W101: Rejected | X101: 46144 | Y101: =IF(X101="","",X101-A101) | Z101: 46144 | AF101: =IF(AND($F101="Closed",$X101>=DATE(2026,5,1),$X101<=DATE(2026,5,31)),"Closed in May","Other")
A102: 46118 | B102: 2026 | C102: Panasonic | D102: OEM | F102: WIP | G102: Chirag Tare | H102: 7719846027 | I102: PE06042602 | J102: Low VOC | K102: Dhule | L102: Maharashtra | M102: Cell Contamination | N102: Cell Contamination | O102: 330 | P102: NSM210446420 | Q102: =MID(P102,4,2) | R102: =MID(P102,6,2) | S102: G2B | T102: P1 | U102: Cell Contamination | V102: Inspection | W102: WIP | Y102: =IF(X102="","",X102-A102) | Z102: 46144 | AF102: =IF(AND($F102="Closed",$X102>=DATE(2026,5,1),$X102<=DATE(2026,5,31)),"Closed in May","Other")
A103: 46112 | B103: 2026 | C103: RA GREEN ENERGks | D103: Channel Sales | F103: Closed | G103: Kumar Tale | H103: 9518921202 | I103: PE31032602 | J103: MC 4 Connector Burn | K103: Nagpur | L103: Maharashtra | M103: Found okay | N103: No Issue | O103: 540 | P103: NSMP25050188956 | Q103: =MID(P103,5,2) | R103: =MID(P103,7,2) | S103: G2TB | T103: P2 | U103: No Issue Found | V103: Found OK | W103: Inspection | X103: 46146 | Y103: =IF(X103="","",X103-A103) | Z103: 46146 | AF103: =IF(AND($F103="Closed",$X103>=DATE(2026,5,1),$X103<=DATE(2026,5,31)),"Closed in May","Other")
A104: 46119 | B104: 2026 | C104: Panasonic | D104: OEM | F104: Closed | G104: Chirag Tare | H104: 7719846027 | I104: PE07042601 | J104: Low VOC | K104: Lucknow | L104: UP | M104: Negative JB Soldering | N104: Cold Soldering | O104: 495 | P104: NSMP2211233510 | Q104: =MID(P104,5,2) | R104: =MID(P104,7,2) | S104: G2B | T104: P2 | U104: N JB Cold Soldering | V104: Soldering | W104: Repair | X104: 46146 | Y104: =IF(X104="","",X104-A104) | Z104: 46146 | AF104: =IF(AND($F104="Closed",$X104>=DATE(2026,5,1),$X104<=DATE(2026,5,31)),"Closed in May","Other")
A105: 46119 | B105: 2026 | C105: Panasonic | D105: OEM | F105: Closed | G105: Chirag Tare | H105: 7719846027 | I105: PE07042601 | J105: Low VOC | K105: Lucknow | L105: UP | M105: Negative JB Soldering | N105: Cold Soldering | O105: 495 | P105: NSMP2211233542 | Q105: =MID(P105,5,2) | R105: =MID(P105,7,2) | S105: G2B | T105: P2 | U105: N JB Cold Soldering | V105: Soldering | W105: Repair | X105: 46146 | Y105: =IF(X105="","",X105-A105) | Z105: 46146 | AF105: =IF(AND($F105="Closed",$X105>=DATE(2026,5,1),$X105<=DATE(2026,5,31)),"Closed in May","Other")
A106: 46119 | B106: 2026 | C106: Panasonic | D106: OEM | F106: Closed | G106: Chirag Tare | H106: 7719846027 | I106: PE07042601 | J106: Low VOC | K106: Lucknow | L106: UP | M106: Negative JB Soldering | N106: Cold Soldering | O106: 495 | P106: NSMP2211233550 | Q106: =MID(P106,5,2) | R106: =MID(P106,7,2) | S106: G2B | T106: P2 | U106: N JB Cold Soldering | V106: Soldering | W106: Repair | X106: 46146 | Y106: =IF(X106="","",X106-A106) | Z106: 46146 | AF106: =IF(AND($F106="Closed",$X106>=DATE(2026,5,1),$X106<=DATE(2026,5,31)),"Closed in May","Other")
A107: 46144 | B107: 2026 | C107: Oyster Technocon | D107: Channel Sales | F107: Closed | G107: Inderpal Singh | H107: 9028940248 | I107: PE02052601 | J107: Low solar panel generation | K107: Nagpur | L107: Maharashtra | M107: Found okay | N107: No Issue | O107: 540 | P107: N/A | Q107: =MID(P107,5,2) | R107: =MID(P107,7,2) | S107: G2TB | T107: P2 | U107: No Issue Found | V107: Found OK | W107: Repair | X107: 46146 | Y107: =IF(X107="","",X107-A107) | Z107: 46146 | AF107: =IF(AND($F107="Closed",$X107>=DATE(2026,5,1),$X107<=DATE(2026,5,31)),"Closed in May","Other")
A108: 46144 | B108: 2026 | C108: Oyster Technocon | D108: Channel Sales | F108: Closed | G108: Inderpal Singh | H108: 9028940248 | I108: PE02052601 | J108: Low solar panel generation | K108: Nagpur | L108: Maharashtra | M108: Found okay | N108: No Issue | O108: 540 | P108: N/A | Q108: =MID(P108,5,2) | R108: =MID(P108,7,2) | S108: G2TB | T108: P2 | U108: No Issue Found | V108: Found OK | W108: Repair | X108: 46146 | Y108: =IF(X108="","",X108-A108) | Z108: 46146 | AF108: =IF(AND($F108="Closed",$X108>=DATE(2026,5,1),$X108<=DATE(2026,5,31)),"Closed in May","Other")
A109: 46144 | B109: 2026 | C109: Oyster Technocon | D109: Channel Sales | F109: Closed | G109: Inderpal Singh | H109: 9028940248 | I109: PE02052601 | J109: Low solar panel generation | K109: Nagpur | L109: Maharashtra | M109: Found okay | N109: No Issue | O109: 540 | P109: N/A | Q109: =MID(P109,5,2) | R109: =MID(P109,7,2) | S109: G2TB | T109: P2 | U109: No Issue Found | V109: Found OK | W109: Repair | X109: 46146 | Y109: =IF(X109="","",X109-A109) | Z109: 46146 | AF109: =IF(AND($F109="Closed",$X109>=DATE(2026,5,1),$X109<=DATE(2026,5,31)),"Closed in May","Other")
A110: 46144 | B110: 2026 | C110: Oyster Technocon | D110: Channel Sales | F110: Closed | G110: Inderpal Singh | H110: 9028940248 | I110: PE02052601 | J110: Low solar panel generation | K110: Nagpur | L110: Maharashtra | M110: Found okay | N110: No Issue | O110: 540 | P110: N/A | Q110: =MID(P110,5,2) | R110: =MID(P110,7,2) | S110: G2TB | T110: P2 | U110: No Issue Found | V110: Found OK | W110: Repair | X110: 46146 | Y110: =IF(X110="","",X110-A110) | Z110: 46146 | AF110: =IF(AND($F110="Closed",$X110>=DATE(2026,5,1),$X110<=DATE(2026,5,31)),"Closed in May","Other")
A111: 46144 | B111: 2026 | C111: Oyster Technocon | D111: Channel Sales | F111: Closed | G111: Inderpal Singh | H111: 9028940248 | I111: PE02052601 | J111: Low solar panel generation | K111: Nagpur | L111: Maharashtra | M111: Found okay | N111: No Issue | O111: 540 | P111: N/A | Q111: =MID(P111,5,2) | R111: =MID(P111,7,2) | S111: G2TB | T111: P2 | U111: No Issue Found | V111: Found OK | W111: Repair | X111: 46146 | Y111: =IF(X111="","",X111-A111) | Z111: 46146 | AF111: =IF(AND($F111="Closed",$X111>=DATE(2026,5,1),$X111<=DATE(2026,5,31)),"Closed in May","Other")
A112: 46144 | B112: 2026 | C112: Oyster Technocon | D112: Channel Sales | F112: Closed | G112: Inderpal Singh | H112: 9028940248 | I112: PE02052601 | J112: Low solar panel generation | K112: Nagpur | L112: Maharashtra | M112: Found okay | N112: No Issue | O112: 540 | P112: N/A | Q112: =MID(P112,5,2) | R112: =MID(P112,7,2) | S112: G2TB | T112: P2 | U112: No Issue Found | V112: Found OK | W112: Repair | X112: 46146 | Y112: =IF(X112="","",X112-A112) | Z112: 46146 | AF112: =IF(AND($F112="Closed",$X112>=DATE(2026,5,1),$X112<=DATE(2026,5,31)),"Closed in May","Other")
A113: 46144 | B113: 2026 | C113: Oyster Technocon | D113: Channel Sales | F113: Closed | G113: Inderpal Singh | H113: 9028940248 | I113: PE02052602 | J113: Low solar panel generation | K113: Nagpur | L113: Maharashtra | M113: AR | N113: JB Issue | O113: 540 | P113: NSMP24101626059 | Q113: =MID(P113,5,2) | R113: =MID(P113,7,2) | S113: G2TB | T113: P2 | U113: All JB Issue | V113: JB Changed | W113: Repair | X113: 46146 | Y113: =IF(X113="","",X113-A113) | Z113: 46146 | AF113: =IF(AND($F113="Closed",$X113>=DATE(2026,5,1),$X113<=DATE(2026,5,31)),"Closed in May","Other")
A114: 46144 | B114: 2026 | C114: Oyster Technocon | D114: Channel Sales | F114: Closed | G114: Inderpal Singh | H114: 9028940248 | I114: PE02052602 | J114: Low solar panel generation | K114: Nagpur | L114: Maharashtra | M114: AR | N114: JB Issue | O114: 540 | P114: NSMP24101626041 | Q114: =MID(P114,5,2) | R114: =MID(P114,7,2) | S114: G2TB | T114: P2 | U114: All JB Issue | V114: JB Changed | W114: Repair | X114: 46146 | Y114: =IF(X114="","",X114-A114) | Z114: 46146 | AF114: =IF(AND($F114="Closed",$X114>=DATE(2026,5,1),$X114<=DATE(2026,5,31)),"Closed in May","Other")
... A118: 46144 | B118: 2026 | C118: Oyster Technocon | D118: Channel Sales | F118: Closed | G118: Inderpal Singh | H118: 9028940248 | I118: PE02052602 | J118: Low solar panel generation | K118: Nagpur | L118: Maharashtra | M118: Found okay | N118: No Issue | O118: 540 | P118: N/A | Q118: =MID(P118,5,2) | R118: =MID(P118,7,2) | S118: G2TB | T118: P2 | U118: No Issue Found | V118: Found OK | W118: Repair | X118: 46146 | Y118: =IF(X118="","",X118-A118) | Z118: 46146 | AF118: =IF(AND($F118="Closed",$X118>=DATE(2026,5,1),$X118<=DATE(2026,5,31)),"Closed in May","Other")
A119: 46106 | B119: 2026 | C119: First Energy | D119: Utility and C&I | F119: Closed | G119: Mr. Gaurav | H119: 9979185999 | I119: PE25032601 | J119: Module Defects | K119: Rajkot | L119: Gujarat | M119: hotspot found | N119: Hotspot | O119: 550 | P119: NSMP2212285926 | Q119: =MID(P119,5,2) | R119: =MID(P119,7,2) | S119: G2B | T119: P2 | U119: Multi Cell Hotspot | V119: Inspection | W119: Rejected | X119: =Z119 | Y119: =IF(X119="","",X119-A119) | Z119: 46146 | AF119: =IF(AND($F119="Closed",$X119>=DATE(2026,5,1),$X119<=DATE(2026,5,31)),"Closed in May","Other")
A120: 46106 | B120: 2026 | C120: First Energy | D120: Utility and C&I | F120: Closed | G120: Mr. Gaurav | H120: 9979185999 | I120: PE25032601 | J120: Module Defects | K120: Rajkot | L120: Gujarat | M120: hotspot found | N120: Hotspot | O120: 550 | P120: NSMP2212276765 | Q120: =MID(P120,5,2) | R120: =MID(P120,7,2) | S120: G2B | T120: P2 | U120: Single Cell Hotspot | V120: Inspection | W120: Rejected | X120: =Z120 | Y120: =IF(X120="","",X120-A120) | Z120: 46146 | AF120: =IF(AND($F120="Closed",$X120>=DATE(2026,5,1),$X120<=DATE(2026,5,31)),"Closed in May","Other")
A121: 46106 | B121: 2026 | C121: First Energy | D121: Utility and C&I | F121: WIP | G121: Mr. Gaurav | H121: 9979185999 | I121: PE25032601 | J121: Module Defects | K121: Rajkot | L121: Gujarat | M121: Broken Module | N121: Hotspot | O121: 550 | P121: NSMP2301293423 | Q121: =MID(P121,5,2) | R121: =MID(P121,7,2) | S121: G2B | T121: P2 | U121: Multi Cell Hotspot | V121: Inspection | W121: WIP | Y121: =IF(X121="","",X121-A121) | Z121: 46146 | AF121: =IF(AND($F121="Closed",$X121>=DATE(2026,5,1),$X121<=DATE(2026,5,31)),"Closed in May","Other")
A122: 46106 | B122: 2026 | C122: First Energy | D122: Utility and C&I | F122: Closed | G122: Mr. Gaurav | H122: 9979185999 | I122: PE25032601 | J122: Module Defects | K122: Rajkot | L122: Gujarat | M122: hotspot found | N122: Hotspot | O122: 550 | P122: NSMP2301328643 | Q122: =MID(P122,5,2) | R122: =MID(P122,7,2) | S122: G2B | T122: P2 | U122: Multi Cell Hotspot | V122: Inspection | W122: Rejected | X122: =Z122 | Y122: =IF(X122="","",X122-A122) | Z122: 46146 | AF122: =IF(AND($F122="Closed",$X122>=DATE(2026,5,1),$X122<=DATE(2026,5,31)),"Closed in May","Other")
A123: 46106 | B123: 2026 | C123: First Energy | D123: Utility and C&I | F123: Closed | G123: Mr. Gaurav | H123: 9979185999 | I123: PE25032601 | J123: Module Defects | K123: Rajkot | L123: Gujarat | M123: hotspot found | N123: Hotspot | O123: 550 | P123: NSMP2212270666 | Q123: =MID(P123,5,2) | R123: =MID(P123,7,2) | S123: G2B | T123: P2 | U123: Multi Cell Hotspot | V123: Inspection | W123: Rejected | X123: =Z123 | Y123: =IF(X123="","",X123-A123) | Z123: 46146 | AF123: =IF(AND($F123="Closed",$X123>=DATE(2026,5,1),$X123<=DATE(2026,5,31)),"Closed in May","Other")
A124: 46106 | B124: 2026 | C124: First Energy | D124: Utility and C&I | F124: Closed | G124: Mr. Gaurav | H124: 9979185999 | I124: PE25032601 | J124: Module Defects | K124: Rajkot | L124: Gujarat | M124: hotspot found | N124: Hotspot | O124: 550 | P124: NSMP2212268452 | Q124: =MID(P124,5,2) | R124: =MID(P124,7,2) | S124: G2B | T124: P2 | U124: Single Cell Hotspot | V124: Inspection | W124: Rejected | X124: =Z124 | Y124: =IF(X124="","",X124-A124) | Z124: 46146 | AF124: =IF(AND($F124="Closed",$X124>=DATE(2026,5,1),$X124<=DATE(2026,5,31)),"Closed in May","Other")
A125: 46106 | B125: 2026 | C125: First Energy | D125: Utility and C&I | F125: Closed | G125: Mr. Gaurav | H125: 9979185999 | I125: PE25032601 | J125: Module Defects | K125: Rajkot | L125: Gujarat | M125: hotspot found | N125: Hotspot | O125: 550 | P125: NSMP2212271260 | Q125: =MID(P125,5,2) | R125: =MID(P125,7,2) | S125: G2B | T125: P2 | U125: Multi Cell Hotspot | V125: Inspection | W125: Rejected | X125: =Z125 | Y125: =IF(X125="","",X125-A125) | Z125: 46146 | AF125: =IF(AND($F125="Closed",$X125>=DATE(2026,5,1),$X125<=DATE(2026,5,31)),"Closed in May","Other")
A126: 46106 | B126: 2026 | C126: First Energy | D126: Utility and C&I | F126: Closed | G126: Mr. Gaurav | H126: 9979185999 | I126: PE25032601 | J126: Module Defects | K126: Rajkot | L126: Gujarat | M126: hotspot found | N126: Hotspot | O126: 550 | P126: NSMP2301334386 | Q126: =MID(P126,5,2) | R126: =MID(P126,7,2) | S126: G2B | T126: P2 | U126: Multi Cell Hotspot | V126: Inspection | W126: Rejected | X126: =Z126 | Y126: =IF(X126="","",X126-A126) | Z126: 46146 | AF126: =IF(AND($F126="Closed",$X126>=DATE(2026,5,1),$X126<=DATE(2026,5,31)),"Closed in May","Other")
A127: 46106 | B127: 2026 | C127: First Energy | D127: Utility and C&I | F127: Closed | G127: Mr. Gaurav | H127: 9979185999 | I127: PE25032601 | J127: Module Defects | K127: Rajkot | L127: Gujarat | M127: hotspot found | N127: Hotspot | O127: 550 | P127: NSMP2301334369 | Q127: =MID(P127,5,2) | R127: =MID(P127,7,2) | S127: G2B | T127: P2 | U127: Multi Cell Hotspot | V127: Inspection | W127: Rejected | X127: =Z127 | Y127: =IF(X127="","",X127-A127) | Z127: 46146 | AF127: =IF(AND($F127="Closed",$X127>=DATE(2026,5,1),$X127<=DATE(2026,5,31)),"Closed in May","Other")
A128: 46106 | B128: 2026 | C128: First Energy | D128: Utility and C&I | F128: Closed | G128: Mr. Gaurav | H128: 9979185999 | I128: PE25032601 | J128: Module Defects | K128: Rajkot | L128: Gujarat | M128: hotspot found | N128: Hotspot | O128: 550 | P128: NSMP2301306009 | Q128: =MID(P128,5,2) | R128: =MID(P128,7,2) | S128: G2B | T128: P2 | U128: Multi Cell Hotspot | V128: Inspection | W128: Rejected | X128: =Z128 | Y128: =IF(X128="","",X128-A128) | Z128: 46146 | AF128: =IF(AND($F128="Closed",$X128>=DATE(2026,5,1),$X128<=DATE(2026,5,31)),"Closed in May","Other")
A129: 46106 | B129: 2026 | C129: First Energy | D129: Utility and C&I | F129: Closed | G129: Mr. Gaurav | H129: 9979185999 | I129: PE25032601 | J129: Module Defects | K129: Rajkot | L129: Gujarat | M129: hotspot found | N129: Hotspot | O129: 550 | P129: NSMP2212268876 | Q129: =MID(P129,5,2) | R129: =MID(P129,7,2) | S129: G2B | T129: P2 | U129: Multi Cell Hotspot | V129: Inspection | W129: Rejected | X129: =Z129 | Y129: =IF(X129="","",X129-A129) | Z129: 46146 | AF129: =IF(AND($F129="Closed",$X129>=DATE(2026,5,1),$X129<=DATE(2026,5,31)),"Closed in May","Other")
A130: 46106 | B130: 2026 | C130: First Energy | D130: Utility and C&I | F130: Closed | G130: Mr. Gaurav | H130: 9979185999 | I130: PE25032601 | J130: Module Defects | K130: Rajkot | L130: Gujarat | M130: hotspot found | N130: Hotspot | O130: 550 | P130: NSMP2301294074 | Q130: =MID(P130,5,2) | R130: =MID(P130,7,2) | S130: G2B | T130: P2 | U130: Multi Cell Hotspot | V130: Inspection | W130: Rejected | X130: =Z130 | Y130: =IF(X130="","",X130-A130) | Z130: 46146 | AF130: =IF(AND($F130="Closed",$X130>=DATE(2026,5,1),$X130<=DATE(2026,5,31)),"Closed in May","Other")
A131: 46106 | B131: 2026 | C131: First Energy | D131: Utility and C&I | F131: WIP | G131: Mr. Gaurav | H131: 9979185999 | I131: PE25032601 | J131: Module Defects | K131: Rajkot | L131: Gujarat | M131: Broken Module | N131: Hotspot | O131: 550 | P131: NSMP2301290174 | Q131: =MID(P131,5,2) | R131: =MID(P131,7,2) | S131: G2B | T131: P2 | U131: Multi Cell Hotspot | V131: Inspection | W131: WIP | Y131: =IF(X131="","",X131-A131) | Z131: 46146 | AF131: =IF(AND($F131="Closed",$X131>=DATE(2026,5,1),$X131<=DATE(2026,5,31)),"Closed in May","Other")
A132: 46106 | B132: 2026 | C132: First Energy | D132: Utility and C&I | F132: Closed | G132: Mr. Gaurav | H132: 9979185999 | I132: PE25032601 | J132: Module Defects | K132: Rajkot | L132: Gujarat | M132: hotspot found | N132: Hotspot | O132: 550 | P132: NSMP2212268256 | Q132: =MID(P132,5,2) | R132: =MID(P132,7,2) | S132: G2B | T132: P2 | U132: Multi Cell Hotspot | V132: Inspection | W132: Rejected | X132: =Z132 | Y132: =IF(X132="","",X132-A132) | Z132: 46146 | AF132: =IF(AND($F132="Closed",$X132>=DATE(2026,5,1),$X132<=DATE(2026,5,31)),"Closed in May","Other")
A133: 46106 | B133: 2026 | C133: First Energy | D133: Utility and C&I | F133: Closed | G133: Mr. Gaurav | H133: 9979185999 | I133: PE25032601 | J133: Module Defects | K133: Rajkot | L133: Gujarat | M133: hotspot found | N133: Hotspot | O133: 550 | P133: NSMP2212268206 | Q133: =MID(P133,5,2) | R133: =MID(P133,7,2) | S133: G2B | T133: P2 | U133: Multi Cell Hotspot | V133: Inspection | W133: Rejected | X133: =Z133 | Y133: =IF(X133="","",X133-A133) | Z133: 46146 | AF133: =IF(AND($F133="Closed",$X133>=DATE(2026,5,1),$X133<=DATE(2026,5,31)),"Closed in May","Other")
A134: 46106 | B134: 2026 | C134: First Energy | D134: Utility and C&I | F134: Closed | G134: Mr. Gaurav | H134: 9979185999 | I134: PE25032601 | J134: Module Defects | K134: Rajkot | L134: Gujarat | M134: hotspot found | N134: Hotspot | O134: 550 | P134: NSMP2212269350 | Q134: =MID(P134,5,2) | R134: =MID(P134,7,2) | S134: G2B | T134: P2 | U134: Multi Cell Hotspot | V134: Inspection | W134: Rejected | X134: =Z134 | Y134: =IF(X134="","",X134-A134) | Z134: 46146 | AF134: =IF(AND($F134="Closed",$X134>=DATE(2026,5,1),$X134<=DATE(2026,5,31)),"Closed in May","Other")
A135: 46106 | B135: 2026 | C135: First Energy | D135: Utility and C&I | F135: Closed | G135: Mr. Gaurav | H135: 9979185999 | I135: PE25032601 | J135: Module Defects | K135: Rajkot | L135: Gujarat | M135: hotspot found | N135: Hotspot | O135: 550 | P135: NSMP2212286574 | Q135: =MID(P135,5,2) | R135: =MID(P135,7,2) | S135: G2B | T135: P2 | U135: Multi Cell Hotspot | V135: Inspection | W135: Rejected | X135: =Z135 | Y135: =IF(X135="","",X135-A135) | Z135: 46146 | AF135: =IF(AND($F135="Closed",$X135>=DATE(2026,5,1),$X135<=DATE(2026,5,31)),"Closed in May","Other")
A136: 46106 | B136: 2026 | C136: First Energy | D136: Utility and C&I | F136: WIP | G136: Mr. Gaurav | H136: 9979185999 | I136: PE25032601 | J136: Module Defects | K136: Rajkot | L136: Gujarat | M136: cell burn | N136: Hotspot | O136: 550 | P136: NSMP2212284084 | Q136: =MID(P136,5,2) | R136: =MID(P136,7,2) | S136: G2B | T136: P2 | U136: Multi Cell Hotspot | V136: Inspection | W136: WIP | Y136: =IF(X136="","",X136-A136) | Z136: 46146 | AF136: =IF(AND($F136="Closed",$X136>=DATE(2026,5,1),$X136<=DATE(2026,5,31)),"Closed in May","Other")
A137: 46106 | B137: 2026 | C137: First Energy | D137: Utility and C&I | F137: Closed | G137: Mr. Gaurav | H137: 9979185999 | I137: PE25032601 | J137: Module Defects | K137: Rajkot | L137: Gujarat | M137: hotspot found | N137: Hotspot | O137: 550 | P137: NSMP2212280000 | Q137: =MID(P137,5,2) | R137: =MID(P137,7,2) | S137: G2B | T137: P2 | U137: Multi Cell Hotspot | V137: Inspection | W137: Rejected | X137: =Z137 | Y137: =IF(X137="","",X137-A137) | Z137: 46146 | AF137: =IF(AND($F137="Closed",$X137>=DATE(2026,5,1),$X137<=DATE(2026,5,31)),"Closed in May","Other")
A138: 46106 | B138: 2026 | C138: First Energy | D138: Utility and C&I | F138: Closed | G138: Mr. Gaurav | H138: 9979185999 | I138: PE25032601 | J138: Module Defects | K138: Rajkot | L138: Gujarat | M138: hotspot found | N138: Hotspot | O138: 550 | P138: NSMP2301333696 | Q138: =MID(P138,5,2) | R138: =MID(P138,7,2) | S138: G2B | T138: P2 | U138: Multi Cell Hotspot | V138: Inspection | W138: Rejected | X138: =Z138 | Y138: =IF(X138="","",X138-A138) | Z138: 46146 | AF138: =IF(AND($F138="Closed",$X138>=DATE(2026,5,1),$X138<=DATE(2026,5,31)),"Closed in May","Other")
A139: 46106 | B139: 2026 | C139: First Energy | D139: Utility and C&I | F139: Closed | G139: Mr. Gaurav | H139: 9979185999 | I139: PE25032601 | J139: Module Defects | K139: Rajkot | L139: Gujarat | M139: hotspot found | N139: Hotspot | O139: 550 | P139: NSMP25032759231 | Q139: =MID(P139,5,2) | R139: =MID(P139,7,2) | S139: G2B | T139: P2 | U139: Single Cell Hotspot | V139: Inspection | W139: Rejected | X139: =Z139 | Y139: =IF(X139="","",X139-A139) | Z139: 46146 | AF139: =IF(AND($F139="Closed",$X139>=DATE(2026,5,1),$X139<=DATE(2026,5,31)),"Closed in May","Other")
A140: 46106 | B140: 2026 | C140: First Energy | D140: Utility and C&I | F140: Closed | G140: Mr. Gaurav | H140: 9979185999 | I140: PE25032601 | J140: Module Defects | K140: Rajkot | L140: Gujarat | M140: hotspot found | N140: Hotspot | O140: 550 | P140: NSMP2301324055 | Q140: =MID(P140,5,2) | R140: =MID(P140,7,2) | S140: G2B | T140: P2 | U140: Multi Cell Hotspot | V140: Inspection | W140: Rejected | X140: =Z140 | Y140: =IF(X140="","",X140-A140) | Z140: 46146 | AF140: =IF(AND($F140="Closed",$X140>=DATE(2026,5,1),$X140<=DATE(2026,5,31)),"Closed in May","Other")
A141: 46106 | B141: 2026 | C141: First Energy | D141: Utility and C&I | F141: Closed | G141: Mr. Gaurav | H141: 9979185999 | I141: PE25032601 | J141: Module Defects | K141: Rajkot | L141: Gujarat | M141: hotspot found | N141: Hotspot | O141: 550 | P141: NSMP2301301245 | Q141: =MID(P141,5,2) | R141: =MID(P141,7,2) | S141: G2B | T141: P2 | U141: Single Cell Hotspot | V141: Inspection | W141: Rejected | X141: =Z141 | Y141: =IF(X141="","",X141-A141) | Z141: 46146 | AF141: =IF(AND($F141="Closed",$X141>=DATE(2026,5,1),$X141<=DATE(2026,5,31)),"Closed in May","Other")
A142: 46106 | B142: 2026 | C142: First Energy | D142: Utility and C&I | F142: Closed | G142: Mr. Gaurav | H142: 9979185999 | I142: PE25032601 | J142: Module Defects | K142: Rajkot | L142: Gujarat | M142: hotspot found | N142: Hotspot | O142: 550 | P142: NSMP2301334356 | Q142: =MID(P142,5,2) | R142: =MID(P142,7,2) | S142: G2B | T142: P2 | U142: Multi Cell Hotspot | V142: Inspection | W142: Rejected | X142: =Z142 | Y142: =IF(X142="","",X142-A142) | Z142: 46146 | AF142: =IF(AND($F142="Closed",$X142>=DATE(2026,5,1),$X142<=DATE(2026,5,31)),"Closed in May","Other")
A143: 46106 | B143: 2026 | C143: First Energy | D143: Utility and C&I | F143: Closed | G143: Mr. Gaurav | H143: 9979185999 | I143: PE25032601 | J143: Module Defects | K143: Rajkot | L143: Gujarat | M143: hotspot found | N143: Hotspot | O143: 550 | P143: NSMP2212266884 | Q143: =MID(P143,5,2) | R143: =MID(P143,7,2) | S143: G2B | T143: P2 | U143: Multi Cell Hotspot | V143: Inspection | W143: Rejected | X143: =Z143 | Y143: =IF(X143="","",X143-A143) | Z143: 46146 | AF143: =IF(AND($F143="Closed",$X143>=DATE(2026,5,1),$X143<=DATE(2026,5,31)),"Closed in May","Other")
A144: 46106 | B144: 2026 | C144: First Energy | D144: Utility and C&I | F144: Closed | G144: Mr. Gaurav | H144: 9979185999 | I144: PE25032601 | J144: Module Defects | K144: Rajkot | L144: Gujarat | M144: hotspot found | N144: Hotspot | O144: 550 | P144: NSMP2212268663 | Q144: =MID(P144,5,2) | R144: =MID(P144,7,2) | S144: G2B | T144: P2 | U144: Multi Cell Hotspot | V144: Inspection | W144: Rejected | X144: =Z144 | Y144: =IF(X144="","",X144-A144) | Z144: 46146 | AF144: =IF(AND($F144="Closed",$X144>=DATE(2026,5,1),$X144<=DATE(2026,5,31)),"Closed in May","Other")
A145: 46106 | B145: 2026 | C145: First Energy | D145: Utility and C&I | F145: Closed | G145: Mr. Gaurav | H145: 9979185999 | I145: PE25032601 | J145: Module Defects | K145: Rajkot | L145: Gujarat | M145: hotspot found | N145: Hotspot | O145: 550 | P145: NSMP2301328816 | Q145: =MID(P145,5,2) | R145: =MID(P145,7,2) | S145: G2B | T145: P2 | U145: Single Cell Hotspot | V145: Inspection | W145: Rejected | X145: =Z145 | Y145: =IF(X145="","",X145-A145) | Z145: 46146 | AF145: =IF(AND($F145="Closed",$X145>=DATE(2026,5,1),$X145<=DATE(2026,5,31)),"Closed in May","Other")
A146: 46106 | B146: 2026 | C146: First Energy | D146: Utility and C&I | F146: Closed | G146: Mr. Gaurav | H146: 9979185999 | I146: PE25032601 | J146: Module Defects | K146: Rajkot | L146: Gujarat | M146: hotspot found | N146: Hotspot | O146: 550 | P146: NSMP2301333878 | Q146: =MID(P146,5,2) | R146: =MID(P146,7,2) | S146: G2B | T146: P2 | U146: Multi Cell Hotspot | V146: Inspection | W146: Rejected | X146: =Z146 | Y146: =IF(X146="","",X146-A146) | Z146: 46146 | AF146: =IF(AND($F146="Closed",$X146>=DATE(2026,5,1),$X146<=DATE(2026,5,31)),"Closed in May","Other")
...

Sheet May-26 Analysis
A1: MAY 2026 - FIELD SERVICE ANALYSIS
B3: KEY PERFORMANCE INDICATORS
B4: Total Complaints | C4: Closed | D4: WIP / Open | E4: Repairable Defects | F4: Closure Rate | G4: May Expense | H4: Per Module cost | I4: Avg Resolution Day
B5: =C5+D5 | C5: =COUNTIFS('Monthly Report May-26 Cleaned'!$F$2:$F$2787,"Closed",'Monthly Report May-26 Cleaned'!$X$2:$X$2787,">="&DATE(2026,5,1),'Monthly Report May-26 Cleaned'!$X$2:$X$2787,"<="&DATE(2026,5,31)) | D5: =COUNTIFS('Monthly Report May-26 Cleaned'!$F$2:$F$2787,"WIP",'Monthly Report May-26 Cleaned'!$Z$2:$Z$2787,">="&DATE(2026,5,1),'Monthly Report May-26 Cleaned'!$Z$2:$Z$2787,"<="&DATE(2026,5,31)) | E5: =COUNTIFS('Monthly Report May-26 Cleaned'!$W$2:$W$2787,"Repair",'Monthly Report May-26 Cleaned'!$X$2:$X$2787,">="&DATE(2026,5,1),'Monthly Report May-26 Cleaned'!$X$2:$X$2787,"<="&DATE(2026,5,31)) | F5: =C5/B5 | G5: 331507.67 | H5: =G5/B5 | I5: =ROUND(AVERAGEIF('Monthly Report May-26 Cleaned'!$Y$2:$Y$2787,">=0"),1)
A10: Metric | B10: Value | C10: Metric | D10: Value
A11: Total Complaints (May) | B11: =B12+B13 | C11: Closure Rate | D11: =B12/B11
A12: Closed Modules | B12: =COUNTIFS('Monthly Report May-26 Cleaned'!$F$2:$F$2787,"Closed",'Monthly Report May-26 Cleaned'!$X$2:$X$2787,">="&DATE(2026,5,1),'Monthly Report May-26 Cleaned'!$X$2:$X$2787,"<="&DATE(2026,5,31)) | C12: WIP Rate | D12: =B13/B11
A13: WIP Modules | B13: =COUNTIFS('Monthly Report May-26 Cleaned'!$F$2:$F$2787,"WIP",'Monthly Report May-26 Cleaned'!$Z$2:$Z$2787,">="&DATE(2026,5,1),'Monthly Report May-26 Cleaned'!$Z$2:$Z$2787,"<="&DATE(2026,5,31))
A14: State covered | B14: =COUNTIF(H19:H27,">0")
A17: COMPLAINTS BY SITE | G17: COMPLAINTS BY STATE
A18: Site | B18: Modules | C18: Closed | D18: WIP | G18: State | H18: Modules | I18: % Share
A19: Blupine | B19: =C19+D19 | C19: =COUNTIFS('Monthly Report May-26 Cleaned'!$C$2:$C$2787,$A19,'Monthly Report May-26 Cleaned'!$F$2:$F$2787,"Closed",'Monthly Report May-26 Cleaned'!$X$2:$X$2787,">="&DATE(2026,5,1),'Monthly Report May-26 Cleaned'!$X$2:$X$2787,"<="&DATE(2026,5,31)) | D19: =COUNTIFS('Monthly Report May-26 Cleaned'!$C$2:$C$2787,$A19,'Monthly Report May-26 Cleaned'!$F$2:$F$2787,"WIP",'Monthly Report May-26 Cleaned'!$Z$2:$Z$2787,">="&DATE(2026,5,1),'Monthly Report May-26 Cleaned'!$Z$2:$Z$2787,"<="&DATE(2026,5,31)) | G19: Gujarat | H19: =COUNTIFS('Monthly Report May-26 Cleaned'!$L$2:$L$2787,$G19,'Monthly Report May-26 Cleaned'!$F$2:$F$2787,"Closed",'Monthly Report May-26 Cleaned'!$X$2:$X$2787,">="&DATE(2026,5,1),'Monthly Report May-26 Cleaned'!$X$2:$X$2787,"<="&DATE(2026,5,31)) | I19: =H19/$H$28
A20: Yanara Power | B20: =C20+D20 | C20: =COUNTIFS('Monthly Report May-26 Cleaned'!$C$2:$C$2787,$A20,'Monthly Report May-26 Cleaned'!$F$2:$F$2787,"Closed",'Monthly Report May-26 Cleaned'!$X$2:$X$2787,">="&DATE(2026,5,1),'Monthly Report May-26 Cleaned'!$X$2:$X$2787,"<="&DATE(2026,5,31)) | D20: =COUNTIFS('Monthly Report May-26 Cleaned'!$C$2:$C$2787,$A20,'Monthly Report May-26 Cleaned'!$F$2:$F$2787,"WIP",'Monthly Report May-26 Cleaned'!$Z$2:$Z$2787,">="&DATE(2026,5,1),'Monthly Report May-26 Cleaned'!$Z$2:$Z$2787,"<="&DATE(2026,5,31)) | G20: Maharashtra | H20: =COUNTIFS('Monthly Report May-26 Cleaned'!$L$2:$L$2787,$G20,'Monthly Report May-26 Cleaned'!$F$2:$F$2787,"Closed",'Monthly Report May-26 Cleaned'!$X$2:$X$2787,">="&DATE(2026,5,1),'Monthly Report May-26 Cleaned'!$X$2:$X$2787,"<="&DATE(2026,5,31)) | I20: =H20/$H$28
A21: Continuum | B21: =C21+D21 | C21: =COUNTIFS('Monthly Report May-26 Cleaned'!$C$2:$C$2787,$A21,'Monthly Report May-26 Cleaned'!$F$2:$F$2787,"Closed",'Monthly Report May-26 Cleaned'!$X$2:$X$2787,">="&DATE(2026,5,1),'Monthly Report May-26 Cleaned'!$X$2:$X$2787,"<="&DATE(2026,5,31)) | D21: =COUNTIFS('Monthly Report May-26 Cleaned'!$C$2:$C$2787,$A21,'Monthly Report May-26 Cleaned'!$F$2:$F$2787,"WIP",'Monthly Report May-26 Cleaned'!$Z$2:$Z$2787,">="&DATE(2026,5,1),'Monthly Report May-26 Cleaned'!$Z$2:$Z$2787,"<="&DATE(2026,5,31)) | G21: Kerala | H21: =COUNTIFS('Monthly Report May-26 Cleaned'!$L$2:$L$2787,$G21,'Monthly Report May-26 Cleaned'!$F$2:$F$2787,"Closed",'Monthly Report May-26 Cleaned'!$X$2:$X$2787,">="&DATE(2026,5,1),'Monthly Report May-26 Cleaned'!$X$2:$X$2787,"<="&DATE(2026,5,31)) | I21: =H21/$H$28
A22: First Energy | B22: =C22+D22 | C22: =COUNTIFS('Monthly Report May-26 Cleaned'!$C$2:$C$2787,$A22,'Monthly Report May-26 Cleaned'!$F$2:$F$2787,"Closed",'Monthly Report May-26 Cleaned'!$X$2:$X$2787,">="&DATE(2026,5,1),'Monthly Report May-26 Cleaned'!$X$2:$X$2787,"<="&DATE(2026,5,31)) | D22: =COUNTIFS('Monthly Report May-26 Cleaned'!$C$2:$C$2787,$A22,'Monthly Report May-26 Cleaned'!$F$2:$F$2787,"WIP",'Monthly Report May-26 Cleaned'!$Z$2:$Z$2787,">="&DATE(2026,5,1),'Monthly Report May-26 Cleaned'!$Z$2:$Z$2787,"<="&DATE(2026,5,31)) | G22: Telangana | H22: =COUNTIFS('Monthly Report May-26 Cleaned'!$L$2:$L$2787,$G22,'Monthly Report May-26 Cleaned'!$F$2:$F$2787,"Closed",'Monthly Report May-26 Cleaned'!$X$2:$X$2787,">="&DATE(2026,5,1),'Monthly Report May-26 Cleaned'!$X$2:$X$2787,"<="&DATE(2026,5,31)) | I22: =H22/$H$28
A23: Solar Square | B23: =C23+D23 | C23: =COUNTIFS('Monthly Report May-26 Cleaned'!$C$2:$C$2787,$A23,'Monthly Report May-26 Cleaned'!$F$2:$F$2787,"Closed",'Monthly Report May-26 Cleaned'!$X$2:$X$2787,">="&DATE(2026,5,1),'Monthly Report May-26 Cleaned'!$X$2:$X$2787,"<="&DATE(2026,5,31)) | D23: =COUNTIFS('Monthly Report May-26 Cleaned'!$C$2:$C$2787,$A23,'Monthly Report May-26 Cleaned'!$F$2:$F$2787,"WIP",'Monthly Report May-26 Cleaned'!$Z$2:$Z$2787,">="&DATE(2026,5,1),'Monthly Report May-26 Cleaned'!$Z$2:$Z$2787,"<="&DATE(2026,5,31)) | G23: UP | H23: =COUNTIFS('Monthly Report May-26 Cleaned'!$L$2:$L$2787,$G23,'Monthly Report May-26 Cleaned'!$F$2:$F$2787,"Closed",'Monthly Report May-26 Cleaned'!$X$2:$X$2787,">="&DATE(2026,5,1),'Monthly Report May-26 Cleaned'!$X$2:$X$2787,"<="&DATE(2026,5,31)) | I23: =H23/$H$28
A24: Oyster Technocon | B24: =C24+D24 | C24: =COUNTIFS('Monthly Report May-26 Cleaned'!$C$2:$C$2787,$A24,'Monthly Report May-26 Cleaned'!$F$2:$F$2787,"Closed",'Monthly Report May-26 Cleaned'!$X$2:$X$2787,">="&DATE(2026,5,1),'Monthly Report May-26 Cleaned'!$X$2:$X$2787,"<="&DATE(2026,5,31)) | D24: =COUNTIFS('Monthly Report May-26 Cleaned'!$C$2:$C$2787,$A24,'Monthly Report May-26 Cleaned'!$F$2:$F$2787,"WIP",'Monthly Report May-26 Cleaned'!$Z$2:$Z$2787,">="&DATE(2026,5,1),'Monthly Report May-26 Cleaned'!$Z$2:$Z$2787,"<="&DATE(2026,5,31)) | G24: MP | H24: =COUNTIFS('Monthly Report May-26 Cleaned'!$L$2:$L$2787,$G24,'Monthly Report May-26 Cleaned'!$F$2:$F$2787,"Closed",'Monthly Report May-26 Cleaned'!$X$2:$X$2787,">="&DATE(2026,5,1),'Monthly Report May-26 Cleaned'!$X$2:$X$2787,"<="&DATE(2026,5,31)) | I24: =H24/$H$28
A25: Panasonic | B25: =C25+D25 | C25: =COUNTIFS('Monthly Report May-26 Cleaned'!$C$2:$C$2787,$A25,'Monthly Report May-26 Cleaned'!$F$2:$F$2787,"Closed",'Monthly Report May-26 Cleaned'!$X$2:$X$2787,">="&DATE(2026,5,1),'Monthly Report May-26 Cleaned'!$X$2:$X$2787,"<="&DATE(2026,5,31)) | D25: =COUNTIFS('Monthly Report May-26 Cleaned'!$C$2:$C$2787,$A25,'Monthly Report May-26 Cleaned'!$F$2:$F$2787,"WIP",'Monthly Report May-26 Cleaned'!$Z$2:$Z$2787,">="&DATE(2026,5,1),'Monthly Report May-26 Cleaned'!$Z$2:$Z$2787,"<="&DATE(2026,5,31)) | G25: Andhra Pradesh | H25: =COUNTIFS('Monthly Report May-26 Cleaned'!$L$2:$L$2787,"*Andhra*",'Monthly Report May-26 Cleaned'!$F$2:$F$2787,"Closed",'Monthly Report May-26 Cleaned'!$X$2:$X$2787,">="&DATE(2026,5,1),'Monthly Report May-26 Cleaned'!$X$2:$X$2787,"<="&DATE(2026,5,31)) | I25: =H25/$H$28
A26: TRUE SUN TRADING COMPANY | B26: =C26+D26 | C26: =COUNTIFS('Monthly Report May-26 Cleaned'!$C$2:$C$2787,$A26,'Monthly Report May-26 Cleaned'!$F$2:$F$2787,"Closed",'Monthly Report May-26 Cleaned'!$X$2:$X$2787,">="&DATE(2026,5,1),'Monthly Report May-26 Cleaned'!$X$2:$X$2787,"<="&DATE(2026,5,31)) | D26: =COUNTIFS('Monthly Report May-26 Cleaned'!$C$2:$C$2787,$A26,'Monthly Report May-26 Cleaned'!$F$2:$F$2787,"WIP",'Monthly Report May-26 Cleaned'!$Z$2:$Z$2787,">="&DATE(2026,5,1),'Monthly Report May-26 Cleaned'!$Z$2:$Z$2787,"<="&DATE(2026,5,31)) | G26: Karnataka | H26: =COUNTIFS('Monthly Report May-26 Cleaned'!$L$2:$L$2787,$G26,'Monthly Report May-26 Cleaned'!$F$2:$F$2787,"Closed",'Monthly Report May-26 Cleaned'!$X$2:$X$2787,">="&DATE(2026,5,1),'Monthly Report May-26 Cleaned'!$X$2:$X$2787,"<="&DATE(2026,5,31)) | I26: =H26/$H$28
A27: Maya Power | B27: =C27+D27 | C27: =COUNTIFS('Monthly Report May-26 Cleaned'!$C$2:$C$2787,$A27,'Monthly Report May-26 Cleaned'!$F$2:$F$2787,"Closed",'Monthly Report May-26 Cleaned'!$X$2:$X$2787,">="&DATE(2026,5,1),'Monthly Report May-26 Cleaned'!$X$2:$X$2787,"<="&DATE(2026,5,31)) | D27: =COUNTIFS('Monthly Report May-26 Cleaned'!$C$2:$C$2787,$A27,'Monthly Report May-26 Cleaned'!$F$2:$F$2787,"WIP",'Monthly Report May-26 Cleaned'!$Z$2:$Z$2787,">="&DATE(2026,5,1),'Monthly Report May-26 Cleaned'!$Z$2:$Z$2787,"<="&DATE(2026,5,31)) | G27: Tamil Nadu | H27: =COUNTIFS('Monthly Report May-26 Cleaned'!$L$2:$L$2787,$G27,'Monthly Report May-26 Cleaned'!$F$2:$F$2787,"Closed",'Monthly Report May-26 Cleaned'!$X$2:$X$2787,">="&DATE(2026,5,1),'Monthly Report May-26 Cleaned'!$X$2:$X$2787,"<="&DATE(2026,5,31)) | I27: =H27/$H$28
A28: Axitec Energy | B28: =C28+D28 | C28: =COUNTIFS('Monthly Report May-26 Cleaned'!$C$2:$C$2787,$A28,'Monthly Report May-26 Cleaned'!$F$2:$F$2787,"Closed",'Monthly Report May-26 Cleaned'!$X$2:$X$2787,">="&DATE(2026,5,1),'Monthly Report May-26 Cleaned'!$X$2:$X$2787,"<="&DATE(2026,5,31)) | D28: =COUNTIFS('Monthly Report May-26 Cleaned'!$C$2:$C$2787,$A28,'Monthly Report May-26 Cleaned'!$F$2:$F$2787,"WIP",'Monthly Report May-26 Cleaned'!$Z$2:$Z$2787,">="&DATE(2026,5,1),'Monthly Report May-26 Cleaned'!$Z$2:$Z$2787,"<="&DATE(2026,5,31)) | G28: TOTAL | H28: =SUM(H19:H27) | I28: =SUM(I19:I27)
A29: Nabhas Constructions | B29: =C29+D29 | C29: =COUNTIFS('Monthly Report May-26 Cleaned'!$C$2:$C$2787,$A29,'Monthly Report May-26 Cleaned'!$F$2:$F$2787,"Closed",'Monthly Report May-26 Cleaned'!$X$2:$X$2787,">="&DATE(2026,5,1),'Monthly Report May-26 Cleaned'!$X$2:$X$2787,"<="&DATE(2026,5,31)) | D29: =COUNTIFS('Monthly Report May-26 Cleaned'!$C$2:$C$2787,$A29,'Monthly Report May-26 Cleaned'!$F$2:$F$2787,"WIP",'Monthly Report May-26 Cleaned'!$Z$2:$Z$2787,">="&DATE(2026,5,1),'Monthly Report May-26 Cleaned'!$Z$2:$Z$2787,"<="&DATE(2026,5,31))
A30: Cresta Solar | B30: =C30+D30 | C30: =COUNTIFS('Monthly Report May-26 Cleaned'!$C$2:$C$2787,$A30,'Monthly Report May-26 Cleaned'!$F$2:$F$2787,"Closed",'Monthly Report May-26 Cleaned'!$X$2:$X$2787,">="&DATE(2026,5,1),'Monthly Report May-26 Cleaned'!$X$2:$X$2787,"<="&DATE(2026,5,31)) | D30: =COUNTIFS('Monthly Report May-26 Cleaned'!$C$2:$C$2787,$A30,'Monthly Report May-26 Cleaned'!$F$2:$F$2787,"WIP",'Monthly Report May-26 Cleaned'!$Z$2:$Z$2787,">="&DATE(2026,5,1),'Monthly Report May-26 Cleaned'!$Z$2:$Z$2787,"<="&DATE(2026,5,31)) | G30: RESOLUTION TYPE
A31: SUNRISE TECHNOLOGIES | B31: =C31+D31 | C31: =COUNTIFS('Monthly Report May-26 Cleaned'!$C$2:$C$2787,$A31,'Monthly Report May-26 Cleaned'!$F$2:$F$2787,"Closed",'Monthly Report May-26 Cleaned'!$X$2:$X$2787,">="&DATE(2026,5,1),'Monthly Report May-26 Cleaned'!$X$2:$X$2787,"<="&DATE(2026,5,31)) | D31: =COUNTIFS('Monthly Report May-26 Cleaned'!$C$2:$C$2787,$A31,'Monthly Report May-26 Cleaned'!$F$2:$F$2787,"WIP",'Monthly Report May-26 Cleaned'!$Z$2:$Z$2787,">="&DATE(2026,5,1),'Monthly Report May-26 Cleaned'!$Z$2:$Z$2787,"<="&DATE(2026,5,31)) | G31: Resolution | H31: Modules | I31: % Share
A32: SILRES Energy Solutions Private Limited | B32: =C32+D32 | C32: =COUNTIFS('Monthly Report May-26 Cleaned'!$C$2:$C$2787,$A32,'Monthly Report May-26 Cleaned'!$F$2:$F$2787,"Closed",'Monthly Report May-26 Cleaned'!$X$2:$X$2787,">="&DATE(2026,5,1),'Monthly Report May-26 Cleaned'!$X$2:$X$2787,"<="&DATE(2026,5,31)) | D32: =COUNTIFS('Monthly Report May-26 Cleaned'!$C$2:$C$2787,$A32,'Monthly Report May-26 Cleaned'!$F$2:$F$2787,"WIP",'Monthly Report May-26 Cleaned'!$Z$2:$Z$2787,">="&DATE(2026,5,1),'Monthly Report May-26 Cleaned'!$Z$2:$Z$2787,"<="&DATE(2026,5,31)) | G32: Retrofit | H32: =COUNTIFS('Monthly Report May-26 Cleaned'!$W$2:$W$2787,"Retrofit",'Monthly Report May-26 Cleaned'!$X$2:$X$2787,">="&DATE(2026,5,1),'Monthly Report May-26 Cleaned'!$X$2:$X$2787,"<="&DATE(2026,5,31)) | I32: =H32/$H$39
A33: RA GREEN ENERGks | B33: =C33+D33 | C33: =COUNTIFS('Monthly Report May-26 Cleaned'!$C$2:$C$2787,$A33,'Monthly Report May-26 Cleaned'!$F$2:$F$2787,"Closed",'Monthly Report May-26 Cleaned'!$X$2:$X$2787,">="&DATE(2026,5,1),'Monthly Report May-26 Cleaned'!$X$2:$X$2787,"<="&DATE(2026,5,31)) | D33: =COUNTIFS('Monthly Report May-26 Cleaned'!$C$2:$C$2787,$A33,'Monthly Report May-26 Cleaned'!$F$2:$F$2787,"WIP",'Monthly Report May-26 Cleaned'!$Z$2:$Z$2787,">="&DATE(2026,5,1),'Monthly Report May-26 Cleaned'!$Z$2:$Z$2787,"<="&DATE(2026,5,31)) | G33: Inspection (WIP) | H33: =COUNTIFS('Monthly Report May-26 Cleaned'!$W$2:$W$2787,"WIP",'Monthly Report May-26 Cleaned'!$Z$2:$Z$2787,">="&DATE(2026,5,1),'Monthly Report May-26 Cleaned'!$Z$2:$Z$2787,"<="&DATE(2026,5,31)) | I33: =H33/$H$39
A34: Uma Trading | B34: =C34+D34 | C34: =COUNTIFS('Monthly Report May-26 Cleaned'!$C$2:$C$2787,$A34,'Monthly Report May-26 Cleaned'!$F$2:$F$2787,"Closed",'Monthly Report May-26 Cleaned'!$X$2:$X$2787,">="&DATE(2026,5,1),'Monthly Report May-26 Cleaned'!$X$2:$X$2787,"<="&DATE(2026,5,31)) | D34: =COUNTIFS('Monthly Report May-26 Cleaned'!$C$2:$C$2787,$A34,'Monthly Report May-26 Cleaned'!$F$2:$F$2787,"WIP",'Monthly Report May-26 Cleaned'!$Z$2:$Z$2787,">="&DATE(2026,5,1),'Monthly Report May-26 Cleaned'!$Z$2:$Z$2787,"<="&DATE(2026,5,31)) | G34: CN (Credit Note) | H34: =COUNTIFS('Monthly Report May-26 Cleaned'!$W$2:$W$2787,"*CN*",'Monthly Report May-26 Cleaned'!$X$2:$X$2787,">="&DATE(2026,5,1),'Monthly Report May-26 Cleaned'!$X$2:$X$2787,"<="&DATE(2026,5,31)) | I34: =H34/$H$39
A35: TOTAL | B35: =SUM(B19:B34) | C35: =SUM(C19:C34) | D35: =SUM(D19:D34) | G35: Repair | H35: =COUNTIFS('Monthly Report May-26 Cleaned'!$W$2:$W$2787,"Repair",'Monthly Report May-26 Cleaned'!$X$2:$X$2787,">="&DATE(2026,5,1),'Monthly Report May-26 Cleaned'!$X$2:$X$2787,"<="&DATE(2026,5,31)) | I35: =H35/$H$39
G36: Rejected | H36: =COUNTIFS('Monthly Report May-26 Cleaned'!$W$2:$W$2787,"Rejected",'Monthly Report May-26 Cleaned'!$X$2:$X$2787,">="&DATE(2026,5,1),'Monthly Report May-26 Cleaned'!$X$2:$X$2787,"<="&DATE(2026,5,31)) | I36: =H36/$H$39
G37: Replacement | H37: =COUNTIFS('Monthly Report May-26 Cleaned'!$W$2:$W$2787,"Replacement",'Monthly Report May-26 Cleaned'!$X$2:$X$2787,">="&DATE(2026,5,1),'Monthly Report May-26 Cleaned'!$X$2:$X$2787,"<="&DATE(2026,5,31)) | I37: =H37/$H$39
A38: DAILY COMPLAINTS TREND - MAY 2026 | G38: Refund | H38: =COUNTIFS('Monthly Report May-26 Cleaned'!$W$2:$W$2787,"Refund",'Monthly Report May-26 Cleaned'!$X$2:$X$2787,">="&DATE(2026,5,1),'Monthly Report May-26 Cleaned'!$X$2:$X$2787,"<="&DATE(2026,5,31)) | I38: =H38/$H$39
A39: Date | B39: Modules Visited | C39: Closed | D39: WIP | G39: TOTAL | H39: =SUM(H32:H38) | I39: =SUM(I32:I38)
A40: 46143 | B40: =COUNTIF('Monthly Report May-26 Cleaned'!$Z$2:$Z$2787,$A40) | C40: =COUNTIFS('Monthly Report May-26 Cleaned'!$Z$2:$Z$2787,$A40,'Monthly Report May-26 Cleaned'!$F$2:$F$2787,"Closed") | D40: =COUNTIFS('Monthly Report May-26 Cleaned'!$Z$2:$Z$2787,$A40,'Monthly Report May-26 Cleaned'!$F$2:$F$2787,"WIP")
A41: 46144 | B41: =COUNTIF('Monthly Report May-26 Cleaned'!$Z$2:$Z$2787,$A41) | C41: =COUNTIFS('Monthly Report May-26 Cleaned'!$Z$2:$Z$2787,$A41,'Monthly Report May-26 Cleaned'!$F$2:$F$2787,"Closed") | D41: =COUNTIFS('Monthly Report May-26 Cleaned'!$Z$2:$Z$2787,$A41,'Monthly Report May-26 Cleaned'!$F$2:$F$2787,"WIP")
A42: 46146 | B42: =COUNTIF('Monthly Report May-26 Cleaned'!$Z$2:$Z$2787,$A42) | C42: =COUNTIFS('Monthly Report May-26 Cleaned'!$Z$2:$Z$2787,$A42,'Monthly Report May-26 Cleaned'!$F$2:$F$2787,"Closed") | D42: =COUNTIFS('Monthly Report May-26 Cleaned'!$Z$2:$Z$2787,$A42,'Monthly Report May-26 Cleaned'!$F$2:$F$2787,"WIP")
A43: 46147 | B43: =COUNTIF('Monthly Report May-26 Cleaned'!$Z$2:$Z$2787,$A43) | C43: =COUNTIFS('Monthly Report May-26 Cleaned'!$Z$2:$Z$2787,$A43,'Monthly Report May-26 Cleaned'!$F$2:$F$2787,"Closed") | D43: =COUNTIFS('Monthly Report May-26 Cleaned'!$Z$2:$Z$2787,$A43,'Monthly Report May-26 Cleaned'!$F$2:$F$2787,"WIP")
A44: 46148 | B44: =COUNTIF('Monthly Report May-26 Cleaned'!$Z$2:$Z$2787,$A44) | C44: =COUNTIFS('Monthly Report May-26 Cleaned'!$Z$2:$Z$2787,$A44,'Monthly Report May-26 Cleaned'!$F$2:$F$2787,"Closed") | D44: =COUNTIFS('Monthly Report May-26 Cleaned'!$Z$2:$Z$2787,$A44,'Monthly Report May-26 Cleaned'!$F$2:$F$2787,"WIP") | G44: WEEK-WISE BREAKDOWN
A45: 46149 | B45: =COUNTIF('Monthly Report May-26 Cleaned'!$Z$2:$Z$2787,$A45) | C45: =COUNTIFS('Monthly Report May-26 Cleaned'!$Z$2:$Z$2787,$A45,'Monthly Report May-26 Cleaned'!$F$2:$F$2787,"Closed") | D45: =COUNTIFS('Monthly Report May-26 Cleaned'!$Z$2:$Z$2787,$A45,'Monthly Report May-26 Cleaned'!$F$2:$F$2787,"WIP") | G45: Week | H45: Modules | I45: % Share
A46: 46150 | B46: =COUNTIF('Monthly Report May-26 Cleaned'!$Z$2:$Z$2787,$A46) | C46: =COUNTIFS('Monthly Report May-26 Cleaned'!$Z$2:$Z$2787,$A46,'Monthly Report May-26 Cleaned'!$F$2:$F$2787,"Closed") | D46: =COUNTIFS('Monthly Report May-26 Cleaned'!$Z$2:$Z$2787,$A46,'Monthly Report May-26 Cleaned'!$F$2:$F$2787,"WIP") | G46: W1 (01-07 May) | H46: =COUNTIFS('Monthly Report May-26 Cleaned'!$Z$2:$Z$2787,">="&DATE(2026,5,1),'Monthly Report May-26 Cleaned'!$Z$2:$Z$2787,"<="&DATE(2026,5,7)) | I46: =H46/$H$51
A47: 46151 | B47: =COUNTIF('Monthly Report May-26 Cleaned'!$Z$2:$Z$2787,$A47) | C47: =COUNTIFS('Monthly Report May-26 Cleaned'!$Z$2:$Z$2787,$A47,'Monthly Report May-26 Cleaned'!$F$2:$F$2787,"Closed") | D47: =COUNTIFS('Monthly Report May-26 Cleaned'!$Z$2:$Z$2787,$A47,'Monthly Report May-26 Cleaned'!$F$2:$F$2787,"WIP") | G47: W2 (08-14 May) | H47: =COUNTIFS('Monthly Report May-26 Cleaned'!$Z$2:$Z$2787,">="&DATE(2026,5,8),'Monthly Report May-26 Cleaned'!$Z$2:$Z$2787,"<="&DATE(2026,5,14)) | I47: =H47/$H$51
A48: 46153 | B48: =COUNTIF('Monthly Report May-26 Cleaned'!$Z$2:$Z$2787,$A48) | C48: =COUNTIFS('Monthly Report May-26 Cleaned'!$Z$2:$Z$2787,$A48,'Monthly Report May-26 Cleaned'!$F$2:$F$2787,"Closed") | D48: =COUNTIFS('Monthly Report May-26 Cleaned'!$Z$2:$Z$2787,$A48,'Monthly Report May-26 Cleaned'!$F$2:$F$2787,"WIP") | G48: W3 (15-21 May) | H48: =COUNTIFS('Monthly Report May-26 Cleaned'!$Z$2:$Z$2787,">="&DATE(2026,5,15),'Monthly Report May-26 Cleaned'!$Z$2:$Z$2787,"<="&DATE(2026,5,21)) | I48: =H48/$H$51
A49: 46154 | B49: =COUNTIF('Monthly Report May-26 Cleaned'!$Z$2:$Z$2787,$A49) | C49: =COUNTIFS('Monthly Report May-26 Cleaned'!$Z$2:$Z$2787,$A49,'Monthly Report May-26 Cleaned'!$F$2:$F$2787,"Closed") | D49: =COUNTIFS('Monthly Report May-26 Cleaned'!$Z$2:$Z$2787,$A49,'Monthly Report May-26 Cleaned'!$F$2:$F$2787,"WIP") | G49: W4 (22-28 May) | H49: =COUNTIFS('Monthly Report May-26 Cleaned'!$Z$2:$Z$2787,">="&DATE(2026,5,22),'Monthly Report May-26 Cleaned'!$Z$2:$Z$2787,"<="&DATE(2026,5,28)) | I49: =H49/$H$51
A50: 46155 | B50: =COUNTIF('Monthly Report May-26 Cleaned'!$Z$2:$Z$2787,$A50) | C50: =COUNTIFS('Monthly Report May-26 Cleaned'!$Z$2:$Z$2787,$A50,'Monthly Report May-26 Cleaned'!$F$2:$F$2787,"Closed") | D50: =COUNTIFS('Monthly Report May-26 Cleaned'!$Z$2:$Z$2787,$A50,'Monthly Report May-26 Cleaned'!$F$2:$F$2787,"WIP") | G50: W5 (29-31 May) | H50: =COUNTIFS('Monthly Report May-26 Cleaned'!$Z$2:$Z$2787,">="&DATE(2026,5,29),'Monthly Report May-26 Cleaned'!$Z$2:$Z$2787,"<="&DATE(2026,5,31)) | I50: =H50/$H$51
A51: 46156 | B51: =COUNTIF('Monthly Report May-26 Cleaned'!$Z$2:$Z$2787,$A51) | C51: =COUNTIFS('Monthly Report May-26 Cleaned'!$Z$2:$Z$2787,$A51,'Monthly Report May-26 Cleaned'!$F$2:$F$2787,"Closed") | D51: =COUNTIFS('Monthly Report May-26 Cleaned'!$Z$2:$Z$2787,$A51,'Monthly Report May-26 Cleaned'!$F$2:$F$2787,"WIP") | G51: TOTAL | H51: =SUM(H46:H50) | I51: =SUM(I46:I50)
A52: 46157 | B52: =COUNTIF('Monthly Report May-26 Cleaned'!$Z$2:$Z$2787,$A52) | C52: =COUNTIFS('Monthly Report May-26 Cleaned'!$Z$2:$Z$2787,$A52,'Monthly Report May-26 Cleaned'!$F$2:$F$2787,"Closed") | D52: =COUNTIFS('Monthly Report May-26 Cleaned'!$Z$2:$Z$2787,$A52,'Monthly Report May-26 Cleaned'!$F$2:$F$2787,"WIP")
A53: 46158 | B53: =COUNTIF('Monthly Report May-26 Cleaned'!$Z$2:$Z$2787,$A53) | C53: =COUNTIFS('Monthly Report May-26 Cleaned'!$Z$2:$Z$2787,$A53,'Monthly Report May-26 Cleaned'!$F$2:$F$2787,"Closed") | D53: =COUNTIFS('Monthly Report May-26 Cleaned'!$Z$2:$Z$2787,$A53,'Monthly Report May-26 Cleaned'!$F$2:$F$2787,"WIP")
A54: 46159 | B54: =COUNTIF('Monthly Report May-26 Cleaned'!$Z$2:$Z$2787,$A54) | C54: =COUNTIFS('Monthly Report May-26 Cleaned'!$Z$2:$Z$2787,$A54,'Monthly Report May-26 Cleaned'!$F$2:$F$2787,"Closed") | D54: =COUNTIFS('Monthly Report May-26 Cleaned'!$Z$2:$Z$2787,$A54,'Monthly Report May-26 Cleaned'!$F$2:$F$2787,"WIP") | G54: MANUFACTURING PLANT-WISE
A55: 46160 | B55: =COUNTIF('Monthly Report May-26 Cleaned'!$Z$2:$Z$2787,$A55) | C55: =COUNTIFS('Monthly Report May-26 Cleaned'!$Z$2:$Z$2787,$A55,'Monthly Report May-26 Cleaned'!$F$2:$F$2787,"Closed") | D55: =COUNTIFS('Monthly Report May-26 Cleaned'!$Z$2:$Z$2787,$A55,'Monthly Report May-26 Cleaned'!$F$2:$F$2787,"WIP") | G55: Plant | H55: Modules | I55: % Share
A56: 46161 | B56: =COUNTIF('Monthly Report May-26 Cleaned'!$Z$2:$Z$2787,$A56) | C56: =COUNTIFS('Monthly Report May-26 Cleaned'!$Z$2:$Z$2787,$A56,'Monthly Report May-26 Cleaned'!$F$2:$F$2787,"Closed") | D56: =COUNTIFS('Monthly Report May-26 Cleaned'!$Z$2:$Z$2787,$A56,'Monthly Report May-26 Cleaned'!$F$2:$F$2787,"WIP") | G56: P4 | H56: =COUNTIFS('Monthly Report May-26 Cleaned'!$T$2:$T$2787,$G56,'Monthly Report May-26 Cleaned'!$F$2:$F$2787,"Closed",'Monthly Report May-26 Cleaned'!$X$2:$X$2787,">="&DATE(2026,5,1),'Monthly Report May-26 Cleaned'!$X$2:$X$2787,"<="&DATE(2026,5,31)) | I56: =H56/$H$60
A57: 46162 | B57: =COUNTIF('Monthly Report May-26 Cleaned'!$Z$2:$Z$2787,$A57) | C57: =COUNTIFS('Monthly Report May-26 Cleaned'!$Z$2:$Z$2787,$A57,'Monthly Report May-26 Cleaned'!$F$2:$F$2787,"Closed") | D57: =COUNTIFS('Monthly Report May-26 Cleaned'!$Z$2:$Z$2787,$A57,'Monthly Report May-26 Cleaned'!$F$2:$F$2787,"WIP") | G57: P2 | H57: =COUNTIFS('Monthly Report May-26 Cleaned'!$T$2:$T$2787,$G57,'Monthly Report May-26 Cleaned'!$F$2:$F$2787,"Closed",'Monthly Report May-26 Cleaned'!$X$2:$X$2787,">="&DATE(2026,5,1),'Monthly Report May-26 Cleaned'!$X$2:$X$2787,"<="&DATE(2026,5,31)) | I57: =H57/$H$60
A58: 46163 | B58: =COUNTIF('Monthly Report May-26 Cleaned'!$Z$2:$Z$2787,$A58) | C58: =COUNTIFS('Monthly Report May-26 Cleaned'!$Z$2:$Z$2787,$A58,'Monthly Report May-26 Cleaned'!$F$2:$F$2787,"Closed") | D58: =COUNTIFS('Monthly Report May-26 Cleaned'!$Z$2:$Z$2787,$A58,'Monthly Report May-26 Cleaned'!$F$2:$F$2787,"WIP") | G58: P1 | H58: =COUNTIFS('Monthly Report May-26 Cleaned'!$T$2:$T$2787,$G58,'Monthly Report May-26 Cleaned'!$F$2:$F$2787,"Closed",'Monthly Report May-26 Cleaned'!$X$2:$X$2787,">="&DATE(2026,5,1),'Monthly Report May-26 Cleaned'!$X$2:$X$2787,"<="&DATE(2026,5,31)) | I58: =H58/$H$60
A59: 46164 | B59: =COUNTIF('Monthly Report May-26 Cleaned'!$Z$2:$Z$2787,$A59) | C59: =COUNTIFS('Monthly Report May-26 Cleaned'!$Z$2:$Z$2787,$A59,'Monthly Report May-26 Cleaned'!$F$2:$F$2787,"Closed") | D59: =COUNTIFS('Monthly Report May-26 Cleaned'!$Z$2:$Z$2787,$A59,'Monthly Report May-26 Cleaned'!$F$2:$F$2787,"WIP") | G59: Prime Pack | H59: =COUNTIFS('Monthly Report May-26 Cleaned'!$T$2:$T$2787,$G59,'Monthly Report May-26 Cleaned'!$F$2:$F$2787,"Closed",'Monthly Report May-26 Cleaned'!$X$2:$X$2787,">="&DATE(2026,5,1),'Monthly Report May-26 Cleaned'!$X$2:$X$2787,"<="&DATE(2026,5,31)) | I59: =H59/$H$60
A60: 46165 | B60: =COUNTIF('Monthly Report May-26 Cleaned'!$Z$2:$Z$2787,$A60) | C60: =COUNTIFS('Monthly Report May-26 Cleaned'!$Z$2:$Z$2787,$A60,'Monthly Report May-26 Cleaned'!$F$2:$F$2787,"Closed") | D60: =COUNTIFS('Monthly Report May-26 Cleaned'!$Z$2:$Z$2787,$A60,'Monthly Report May-26 Cleaned'!$F$2:$F$2787,"WIP") | G60: TOTAL | H60: =SUM(H56:H59) | I60: =SUM(I56:I59)
A61: 46166 | B61: =COUNTIF('Monthly Report May-26 Cleaned'!$Z$2:$Z$2787,$A61) | C61: =COUNTIFS('Monthly Report May-26 Cleaned'!$Z$2:$Z$2787,$A61,'Monthly Report May-26 Cleaned'!$F$2:$F$2787,"Closed") | D61: =COUNTIFS('Monthly Report May-26 Cleaned'!$Z$2:$Z$2787,$A61,'Monthly Report May-26 Cleaned'!$F$2:$F$2787,"WIP")
A62: 46167 | B62: =COUNTIF('Monthly Report May-26 Cleaned'!$Z$2:$Z$2787,$A62) | C62: =COUNTIFS('Monthly Report May-26 Cleaned'!$Z$2:$Z$2787,$A62,'Monthly Report May-26 Cleaned'!$F$2:$F$2787,"Closed") | D62: =COUNTIFS('Monthly Report May-26 Cleaned'!$Z$2:$Z$2787,$A62,'Monthly Report May-26 Cleaned'!$F$2:$F$2787,"WIP")
A63: 46168 | B63: =COUNTIF('Monthly Report May-26 Cleaned'!$Z$2:$Z$2787,$A63) | C63: =COUNTIFS('Monthly Report May-26 Cleaned'!$Z$2:$Z$2787,$A63,'Monthly Report May-26 Cleaned'!$F$2:$F$2787,"Closed") | D63: =COUNTIFS('Monthly Report May-26 Cleaned'!$Z$2:$Z$2787,$A63,'Monthly Report May-26 Cleaned'!$F$2:$F$2787,"WIP")
A64: 46169 | B64: =COUNTIF('Monthly Report May-26 Cleaned'!$Z$2:$Z$2787,$A64) | C64: =COUNTIFS('Monthly Report May-26 Cleaned'!$Z$2:$Z$2787,$A64,'Monthly Report May-26 Cleaned'!$F$2:$F$2787,"Closed") | D64: =COUNTIFS('Monthly Report May-26 Cleaned'!$Z$2:$Z$2787,$A64,'Monthly Report May-26 Cleaned'!$F$2:$F$2787,"WIP") | G64: TAT - COMPLAINT RAISED vs CLOSED
A65: 46170 | B65: =COUNTIF('Monthly Report May-26 Cleaned'!$Z$2:$Z$2787,$A65) | C65: =COUNTIFS('Monthly Report May-26 Cleaned'!$Z$2:$Z$2787,$A65,'Monthly Report May-26 Cleaned'!$F$2:$F$2787,"Closed") | D65: =COUNTIFS('Monthly Report May-26 Cleaned'!$Z$2:$Z$2787,$A65,'Monthly Report May-26 Cleaned'!$F$2:$F$2787,"WIP") | G65: TAT Bucket (Days) | H65: Modules
A66: 46171 | B66: =COUNTIF('Monthly Report May-26 Cleaned'!$Z$2:$Z$2787,$A66) | C66: =COUNTIFS('Monthly Report May-26 Cleaned'!$Z$2:$Z$2787,$A66,'Monthly Report May-26 Cleaned'!$F$2:$F$2787,"Closed") | D66: =COUNTIFS('Monthly Report May-26 Cleaned'!$Z$2:$Z$2787,$A66,'Monthly Report May-26 Cleaned'!$F$2:$F$2787,"WIP") | G66: 0 - 3 days | H66: =COUNTIFS('Monthly Report May-26 Cleaned'!$Y$2:$Y$2787,">=0",'Monthly Report May-26 Cleaned'!$Y$2:$Y$2787,"<=3",'Monthly Report May-26 Cleaned'!$F$2:$F$2787,"Closed",'Monthly Report May-26 Cleaned'!$X$2:$X$2787,">="&DATE(2026,5,1),'Monthly Report May-26 Cleaned'!$X$2:$X$2787,"<="&DATE(2026,5,31)) | I66: =H66/$H$71
A67: 46172 | B67: =COUNTIF('Monthly Report May-26 Cleaned'!$Z$2:$Z$2787,$A67) | C67: =COUNTIFS('Monthly Report May-26 Cleaned'!$Z$2:$Z$2787,$A67,'Monthly Report May-26 Cleaned'!$F$2:$F$2787,"Closed") | D67: =COUNTIFS('Monthly Report May-26 Cleaned'!$Z$2:$Z$2787,$A67,'Monthly Report May-26 Cleaned'!$F$2:$F$2787,"WIP") | G67: 4 - 7 days | H67: =COUNTIFS('Monthly Report May-26 Cleaned'!$Y$2:$Y$2787,">=4",'Monthly Report May-26 Cleaned'!$Y$2:$Y$2787,"<=7",'Monthly Report May-26 Cleaned'!$F$2:$F$2787,"Closed",'Monthly Report May-26 Cleaned'!$X$2:$X$2787,">="&DATE(2026,5,1),'Monthly Report May-26 Cleaned'!$X$2:$X$2787,"<="&DATE(2026,5,31)) | I67: =H67/$H$71
A68: 46173 | B68: =COUNTIF('Monthly Report May-26 Cleaned'!$Z$2:$Z$2787,$A68) | C68: =COUNTIFS('Monthly Report May-26 Cleaned'!$Z$2:$Z$2787,$A68,'Monthly Report May-26 Cleaned'!$F$2:$F$2787,"Closed") | D68: =COUNTIFS('Monthly Report May-26 Cleaned'!$Z$2:$Z$2787,$A68,'Monthly Report May-26 Cleaned'!$F$2:$F$2787,"WIP") | G68: 8 - 15 days | H68: =COUNTIFS('Monthly Report May-26 Cleaned'!$Y$2:$Y$2787,">=8",'Monthly Report May-26 Cleaned'!$Y$2:$Y$2787,"<=15",'Monthly Report May-26 Cleaned'!$F$2:$F$2787,"Closed",'Monthly Report May-26 Cleaned'!$X$2:$X$2787,">="&DATE(2026,5,1),'Monthly Report May-26 Cleaned'!$X$2:$X$2787,"<="&DATE(2026,5,31)) | I68: =H68/$H$71
G69: 16 - 30 days | H69: =COUNTIFS('Monthly Report May-26 Cleaned'!$Y$2:$Y$2787,">=16",'Monthly Report May-26 Cleaned'!$Y$2:$Y$2787,"<=30",'Monthly Report May-26 Cleaned'!$F$2:$F$2787,"Closed",'Monthly Report May-26 Cleaned'!$X$2:$X$2787,">="&DATE(2026,5,1),'Monthly Report May-26 Cleaned'!$X$2:$X$2787,"<="&DATE(2026,5,31)) | I69: =H69/$H$71
G70: > 30 days | H70: =COUNTIFS('Monthly Report May-26 Cleaned'!$Y$2:$Y$2787,">30",'Monthly Report May-26 Cleaned'!$F$2:$F$2787,"Closed",'Monthly Report May-26 Cleaned'!$X$2:$X$2787,">="&DATE(2026,5,1),'Monthly Report May-26 Cleaned'!$X$2:$X$2787,"<="&DATE(2026,5,31)) | I70: =H70/$H$71
G71: TOTAL | H71: =SUM(H66:H70) | I71: =SUM(I66:I70)
G72: Avg TAT (days) | H72: =ROUND(AVERAGEIFS('Monthly Report May-26 Cleaned'!$Y$2:$Y$2787,'Monthly Report May-26 Cleaned'!$Y$2:$Y$2787,">=0",'Monthly Report May-26 Cleaned'!$F$2:$F$2787,"Closed",'Monthly Report May-26 Cleaned'!$X$2:$X$2787,">="&DATE(2026,5,1),'Monthly Report May-26 Cleaned'!$X$2:$X$2787,"<="&DATE(2026,5,31)),1)
A74: MODULE TYPE DEFECT ANALYSIS - MAY 2026
A75: Defect Type (Our Evaluation) | B75: G2B | C75: G2TB | D75: G2G | E75: Grand Total
A76: Cold Soldering | B76: =COUNTIFS('Monthly Report May-26 Cleaned'!$N$2:$N$2680,A76,'Monthly Report May-26 Cleaned'!$S$2:$S$2680,B$75,'Monthly Report May-26 Cleaned'!$AF$2:$AF$2680,"Closed in May") | C76: =COUNTIFS('Monthly Report May-26 Cleaned'!$N$2:$N$2680,A76,'Monthly Report May-26 Cleaned'!$S$2:$S$2680,C$75,'Monthly Report May-26 Cleaned'!$AF$2:$AF$2680,"Closed in May") | D76: =COUNTIFS('Monthly Report May-26 Cleaned'!$N$2:$N$2680,A76,'Monthly Report May-26 Cleaned'!$S$2:$S$2680,D$75,'Monthly Report May-26 Cleaned'!$AF$2:$AF$2680,"Closed in May") | E76: =SUM(B76:D76)
A77: Hotspot | B77: =COUNTIFS('Monthly Report May-26 Cleaned'!$N$2:$N$2680,A77,'Monthly Report May-26 Cleaned'!$S$2:$S$2680,B$75,'Monthly Report May-26 Cleaned'!$AF$2:$AF$2680,"Closed in May") | C77: =COUNTIFS('Monthly Report May-26 Cleaned'!$N$2:$N$2680,A77,'Monthly Report May-26 Cleaned'!$S$2:$S$2680,C$75,'Monthly Report May-26 Cleaned'!$AF$2:$AF$2680,"Closed in May") | D77: =COUNTIFS('Monthly Report May-26 Cleaned'!$N$2:$N$2680,A77,'Monthly Report May-26 Cleaned'!$S$2:$S$2680,D$75,'Monthly Report May-26 Cleaned'!$AF$2:$AF$2680,"Closed in May") | E77: =SUM(B77:D77)
A78: JB Issue | B78: =COUNTIFS('Monthly Report May-26 Cleaned'!$N$2:$N$2680,A78,'Monthly Report May-26 Cleaned'!$S$2:$S$2680,B$75,'Monthly Report May-26 Cleaned'!$AF$2:$AF$2680,"Closed in May") | C78: =COUNTIFS('Monthly Report May-26 Cleaned'!$N$2:$N$2680,A78,'Monthly Report May-26 Cleaned'!$S$2:$S$2680,C$75,'Monthly Report May-26 Cleaned'!$AF$2:$AF$2680,"Closed in May") | D78: =COUNTIFS('Monthly Report May-26 Cleaned'!$N$2:$N$2680,A78,'Monthly Report May-26 Cleaned'!$S$2:$S$2680,D$75,'Monthly Report May-26 Cleaned'!$AF$2:$AF$2680,"Closed in May") | E78: =SUM(B78:D78)
A79: Glass Breakage | B79: =COUNTIFS('Monthly Report May-26 Cleaned'!$N$2:$N$2680,A79,'Monthly Report May-26 Cleaned'!$S$2:$S$2680,B$75,'Monthly Report May-26 Cleaned'!$AF$2:$AF$2680,"Closed in May") | C79: =COUNTIFS('Monthly Report May-26 Cleaned'!$N$2:$N$2680,A79,'Monthly Report May-26 Cleaned'!$S$2:$S$2680,C$75,'Monthly Report May-26 Cleaned'!$AF$2:$AF$2680,"Closed in May") | D79: =COUNTIFS('Monthly Report May-26 Cleaned'!$N$2:$N$2680,A79,'Monthly Report May-26 Cleaned'!$S$2:$S$2680,D$75,'Monthly Report May-26 Cleaned'!$AF$2:$AF$2680,"Closed in May") | E79: =SUM(B79:D79)
A80: No Issue | B80: =COUNTIFS('Monthly Report May-26 Cleaned'!$N$2:$N$2680,A80,'Monthly Report May-26 Cleaned'!$S$2:$S$2680,B$75,'Monthly Report May-26 Cleaned'!$AF$2:$AF$2680,"Closed in May") | C80: =COUNTIFS('Monthly Report May-26 Cleaned'!$N$2:$N$2680,A80,'Monthly Report May-26 Cleaned'!$S$2:$S$2680,C$75,'Monthly Report May-26 Cleaned'!$AF$2:$AF$2680,"Closed in May") | D80: =COUNTIFS('Monthly Report May-26 Cleaned'!$N$2:$N$2680,A80,'Monthly Report May-26 Cleaned'!$S$2:$S$2680,D$75,'Monthly Report May-26 Cleaned'!$AF$2:$AF$2680,"Closed in May") | E80: =SUM(B80:D80)
A81: Tab lead Burn | B81: =COUNTIFS('Monthly Report May-26 Cleaned'!$N$2:$N$2680,A81,'Monthly Report May-26 Cleaned'!$S$2:$S$2680,B$75,'Monthly Report May-26 Cleaned'!$AF$2:$AF$2680,"Closed in May") | C81: =COUNTIFS('Monthly Report May-26 Cleaned'!$N$2:$N$2680,A81,'Monthly Report May-26 Cleaned'!$S$2:$S$2680,C$75,'Monthly Report May-26 Cleaned'!$AF$2:$AF$2680,"Closed in May") | D81: =COUNTIFS('Monthly Report May-26 Cleaned'!$N$2:$N$2680,A81,'Monthly Report May-26 Cleaned'!$S$2:$S$2680,D$75,'Monthly Report May-26 Cleaned'!$AF$2:$AF$2680,"Closed in May") | E81: =SUM(B81:D81)
A82: Backsheet Scratches | B82: =COUNTIFS('Monthly Report May-26 Cleaned'!$N$2:$N$2680,A82,'Monthly Report May-26 Cleaned'!$S$2:$S$2680,B$75,'Monthly Report May-26 Cleaned'!$AF$2:$AF$2680,"Closed in May") | C82: =COUNTIFS('Monthly Report May-26 Cleaned'!$N$2:$N$2680,A82,'Monthly Report May-26 Cleaned'!$S$2:$S$2680,C$75,'Monthly Report May-26 Cleaned'!$AF$2:$AF$2680,"Closed in May") | D82: =COUNTIFS('Monthly Report May-26 Cleaned'!$N$2:$N$2680,A82,'Monthly Report May-26 Cleaned'!$S$2:$S$2680,D$75,'Monthly Report May-26 Cleaned'!$AF$2:$AF$2680,"Closed in May") | E82: =SUM(B82:D82)
A83: Cell Contamination | B83: =COUNTIFS('Monthly Report May-26 Cleaned'!$N$2:$N$2680,A83,'Monthly Report May-26 Cleaned'!$S$2:$S$2680,B$75,'Monthly Report May-26 Cleaned'!$AF$2:$AF$2680,"Closed in May") | C83: =COUNTIFS('Monthly Report May-26 Cleaned'!$N$2:$N$2680,A83,'Monthly Report May-26 Cleaned'!$S$2:$S$2680,C$75,'Monthly Report May-26 Cleaned'!$AF$2:$AF$2680,"Closed in May") | D83: =COUNTIFS('Monthly Report May-26 Cleaned'!$N$2:$N$2680,A83,'Monthly Report May-26 Cleaned'!$S$2:$S$2680,D$75,'Monthly Report May-26 Cleaned'!$AF$2:$AF$2680,"Closed in May") | E83: =SUM(B83:D83)
A84: Cell Chip | B84: =COUNTIFS('Monthly Report May-26 Cleaned'!$N$2:$N$2680,A84,'Monthly Report May-26 Cleaned'!$S$2:$S$2680,B$75,'Monthly Report May-26 Cleaned'!$AF$2:$AF$2680,"Closed in May") | C84: =COUNTIFS('Monthly Report May-26 Cleaned'!$N$2:$N$2680,A84,'Monthly Report May-26 Cleaned'!$S$2:$S$2680,C$75,'Monthly Report May-26 Cleaned'!$AF$2:$AF$2680,"Closed in May") | D84: =COUNTIFS('Monthly Report May-26 Cleaned'!$N$2:$N$2680,A84,'Monthly Report May-26 Cleaned'!$S$2:$S$2680,D$75,'Monthly Report May-26 Cleaned'!$AF$2:$AF$2680,"Closed in May") | E84: =SUM(B84:D84)
A85: Cell Crack | B85: =COUNTIFS('Monthly Report May-26 Cleaned'!$N$2:$N$2680,A85,'Monthly Report May-26 Cleaned'!$S$2:$S$2680,B$75,'Monthly Report May-26 Cleaned'!$AF$2:$AF$2680,"Closed in May") | C85: =COUNTIFS('Monthly Report May-26 Cleaned'!$N$2:$N$2680,A85,'Monthly Report May-26 Cleaned'!$S$2:$S$2680,C$75,'Monthly Report May-26 Cleaned'!$AF$2:$AF$2680,"Closed in May") | D85: =COUNTIFS('Monthly Report May-26 Cleaned'!$N$2:$N$2680,A85,'Monthly Report May-26 Cleaned'!$S$2:$S$2680,D$75,'Monthly Report May-26 Cleaned'!$AF$2:$AF$2680,"Closed in May") | E85: =SUM(B85:D85)
A86: Improper Ribbon Soldering | B86: =COUNTIFS('Monthly Report May-26 Cleaned'!$N$2:$N$2680,A86,'Monthly Report May-26 Cleaned'!$S$2:$S$2680,B$75,'Monthly Report May-26 Cleaned'!$AF$2:$AF$2680,"Closed in May") | C86: =COUNTIFS('Monthly Report May-26 Cleaned'!$N$2:$N$2680,A86,'Monthly Report May-26 Cleaned'!$S$2:$S$2680,C$75,'Monthly Report May-26 Cleaned'!$AF$2:$AF$2680,"Closed in May") | D86: =COUNTIFS('Monthly Report May-26 Cleaned'!$N$2:$N$2680,A86,'Monthly Report May-26 Cleaned'!$S$2:$S$2680,D$75,'Monthly Report May-26 Cleaned'!$AF$2:$AF$2680,"Closed in May") | E86: =SUM(B86:D86)
A87: Forign Particle - Cell Piece | B87: =COUNTIFS('Monthly Report May-26 Cleaned'!$N$2:$N$2680,A87,'Monthly Report May-26 Cleaned'!$S$2:$S$2680,B$75,'Monthly Report May-26 Cleaned'!$AF$2:$AF$2680,"Closed in May") | C87: =COUNTIFS('Monthly Report May-26 Cleaned'!$N$2:$N$2680,A87,'Monthly Report May-26 Cleaned'!$S$2:$S$2680,C$75,'Monthly Report May-26 Cleaned'!$AF$2:$AF$2680,"Closed in May") | D87: =COUNTIFS('Monthly Report May-26 Cleaned'!$N$2:$N$2680,A87,'Monthly Report May-26 Cleaned'!$S$2:$S$2680,D$75,'Monthly Report May-26 Cleaned'!$AF$2:$AF$2680,"Closed in May") | E87: =SUM(B87:D87)
... A91: Transparent backsheet melt down | B91: =COUNTIFS('Monthly Report May-26 Cleaned'!$N$2:$N$2680,A91,'Monthly Report May-26 Cleaned'!$S$2:$S$2680,B$75,'Monthly Report May-26 Cleaned'!$AF$2:$AF$2680,"Closed in May") | C91: =COUNTIFS('Monthly Report May-26 Cleaned'!$N$2:$N$2680,A91,'Monthly Report May-26 Cleaned'!$S$2:$S$2680,C$75,'Monthly Report May-26 Cleaned'!$AF$2:$AF$2680,"Closed in May") | D91: =COUNTIFS('Monthly Report May-26 Cleaned'!$N$2:$N$2680,A91,'Monthly Report May-26 Cleaned'!$S$2:$S$2680,D$75,'Monthly Report May-26 Cleaned'!$AF$2:$AF$2680,"Closed in May") | E91: =SUM(B91:D91)
A92: Grand Total | B92: =SUM(B76:B90) | C92: =SUM(C76:C90) | D92: =SUM(D76:D90) | E92: =SUM(E76:E91)

Sheet Defect Analysis May-26
A1: MAY 2026 - DEFECT ANALYSIS (PIVOT)
A3: May Closed Flag | B3: (Multiple Items)
A5: Row Labels | B5: Module Count
A6: Air entrapment during the lamination process | B6: 1
A7: Cell Chip | B7: 1
A8: Cell Crack | B8: 1
A9: Cold Soldering | B9: 2190
A10: Forign Particle - Cell Piece | B10: 1
A11: Glass Breakage | B11: 2
A12: Improper Ribbon Soldering | B12: 1
A13: JB Issue | B13: 205
A14: MC4 connectors damaged | B14: 1
A15: No Issue | B15: 70
A16: Tab lead Burn | B16: 5
A17: Transparent backsheet melt down | B17: 1
... A19: Grand Total | B19: 2481
